Workbook

Sheet Production
A1: Assumption
A2: capital's share | B2: 0.35
A3: annual depreciation rate | B3: =AVERAGE('CFC data'!E22:E29)
K4: HP Filter
D5: K | E5: Real GDP | F5: LnK | G5: LnY | K5: LnZ | L5: LnZ_HP | M5: Second-order difference | N5: LnA-Trend(Check) | O5: =SUMXMY2($K$6:$K$27,$L$6:$L$27)+100*SUMSQ($M$8:$M$27)
C6: 2002 | D6: =XLOOKUP(C6,PWT!$A$2:$A$35,PWT!$C$2:$C$35,"",0) | E6: =XLOOKUP(C6,WEO_Data!$B$8:$B$51,WEO_Data!$C$8:$C$51,"",0) | F6: =IF(D6="","",LN(D6)) | G6: =IF(E6="","",LN(E6)) | K6: =IF(OR(F6="",G6=""),"",G6-$B$2*F6) | L6: =K6 | N6: =IF(OR(K6="",L6=""),"",K6-L6)
C7: 2003 | D7: =XLOOKUP(C7,PWT!$A$2:$A$35,PWT!$C$2:$C$35,"",0) | E7: =XLOOKUP(C7,WEO_Data!$B$8:$B$51,WEO_Data!$C$8:$C$51,"",0) | F7: =IF(D7="","",LN(D7)) | G7: =IF(E7="","",LN(E7)) | K7: =IF(OR(F7="",G7=""),"",G7-$B$2*F7) | L7: =K7 | N7: =IF(OR(K7="",L7=""),"",K7-L7)
C8: 2004 | D8: =XLOOKUP(C8,PWT!$A$2:$A$35,PWT!$C$2:$C$35,"",0) | E8: =XLOOKUP(C8,WEO_Data!$B$8:$B$51,WEO_Data!$C$8:$C$51,"",0) | F8: =IF(D8="","",LN(D8)) | G8: =IF(E8="","",LN(E8)) | K8: =IF(OR(F8="",G8=""),"",G8-$B$2*F8) | L8: =K8 | M8: =L8-2*L7+L6 | N8: =IF(OR(K8="",L8=""),"",K8-L8)
C9: 2005 | D9: =XLOOKUP(C9,PWT!$A$2:$A$35,PWT!$C$2:$C$35,"",0) | E9: =XLOOKUP(C9,WEO_Data!$B$8:$B$51,WEO_Data!$C$8:$C$51,"",0) | F9: =IF(D9="","",LN(D9)) | G9: =IF(E9="","",LN(E9)) | K9: =IF(OR(F9="",G9=""),"",G9-$B$2*F9) | L9: =K9 | M9: =L9-2*L8+L7 | N9: =IF(OR(K9="",L9=""),"",K9-L9)
C10: 2006 | D10: =XLOOKUP(C10,PWT!$A$2:$A$35,PWT!$C$2:$C$35,"",0) | E10: =XLOOKUP(C10,WEO_Data!$B$8:$B$51,WEO_Data!$C$8:$C$51,"",0) | F10: =IF(D10="","",LN(D10)) | G10: =IF(E10="","",LN(E10)) | K10: =IF(OR(F10="",G10=""),"",G10-$B$2*F10) | L10: =K10 | M10: =L10-2*L9+L8 | N10: =IF(OR(K10="",L10=""),"",K10-L10)
C11: 2007 | D11: =XLOOKUP(C11,PWT!$A$2:$A$35,PWT!$C$2:$C$35,"",0) | E11: =XLOOKUP(C11,WEO_Data!$B$8:$B$51,WEO_Data!$C$8:$C$51,"",0) | F11: =IF(D11="","",LN(D11)) | G11: =IF(E11="","",LN(E11)) | K11: =IF(OR(F11="",G11=""),"",G11-$B$2*F11) | L11: =K11 | M11: =L11-2*L10+L9 | N11: =IF(OR(K11="",L11=""),"",K11-L11)
C12: 2008 | D12: =XLOOKUP(C12,PWT!$A$2:$A$35,PWT!$C$2:$C$35,"",0) | E12: =XLOOKUP(C12,WEO_Data!$B$8:$B$51,WEO_Data!$C$8:$C$51,"",0) | F12: =IF(D12="","",LN(D12)) | G12: =IF(E12="","",LN(E12)) | K12: =IF(OR(F12="",G12=""),"",G12-$B$2*F12) | L12: =K12 | M12: =L12-2*L11+L10 | N12: =IF(OR(K12="",L12=""),"",K12-L12)
C13: 2009 | D13: =XLOOKUP(C13,PWT!$A$2:$A$35,PWT!$C$2:$C$35,"",0) | E13: =XLOOKUP(C13,WEO_Data!$B$8:$B$51,WEO_Data!$C$8:$C$51,"",0) | F13: =IF(D13="","",LN(D13)) | G13: =IF(E13="","",LN(E13)) | K13: =IF(OR(F13="",G13=""),"",G13-$B$2*F13) | L13: =K13 | M13: =L13-2*L12+L11 | N13: =IF(OR(K13="",L13=""),"",K13-L13)
C14: 2010 | D14: =XLOOKUP(C14,PWT!$A$2:$A$35,PWT!$C$2:$C$35,"",0) | E14: =XLOOKUP(C14,WEO_Data!$B$8:$B$51,WEO_Data!$C$8:$C$51,"",0) | F14: =IF(D14="","",LN(D14)) | G14: =IF(E14="","",LN(E14)) | K14: =IF(OR(F14="",G14=""),"",G14-$B$2*F14) | L14: =K14 | M14: =L14-2*L13+L12 | N14: =IF(OR(K14="",L14=""),"",K14-L14)
C15: 2011 | D15: =XLOOKUP(C15,PWT!$A$2:$A$35,PWT!$C$2:$C$35,"",0) | E15: =XLOOKUP(C15,WEO_Data!$B$8:$B$51,WEO_Data!$C$8:$C$51,"",0) | F15: =IF(D15="","",LN(D15)) | G15: =IF(E15="","",LN(E15)) | K15: =IF(OR(F15="",G15=""),"",G15-$B$2*F15) | L15: =K15 | M15: =L15-2*L14+L13 | N15: =IF(OR(K15="",L15=""),"",K15-L15)
C16: 2012 | D16: =XLOOKUP(C16,PWT!$A$2:$A$35,PWT!$C$2:$C$35,"",0) | E16: =XLOOKUP(C16,WEO_Data!$B$8:$B$51,WEO_Data!$C$8:$C$51,"",0) | F16: =IF(D16="","",LN(D16)) | G16: =IF(E16="","",LN(E16)) | K16: =IF(OR(F16="",G16=""),"",G16-$B$2*F16) | L16: =K16 | M16: =L16-2*L15+L14 | N16: =IF(OR(K16="",L16=""),"",K16-L16)
C17: 2013 | D17: =XLOOKUP(C17,PWT!$A$2:$A$35,PWT!$C$2:$C$35,"",0) | E17: =XLOOKUP(C17,WEO_Data!$B$8:$B$51,WEO_Data!$C$8:$C$51,"",0) | F17: =IF(D17="","",LN(D17)) | G17: =IF(E17="","",LN(E17)) | K17: =IF(OR(F17="",G17=""),"",G17-$B$2*F17) | L17: =K17 | M17: =L17-2*L16+L15 | N17: =IF(OR(K17="",L17=""),"",K17-L17)
C18: 2014 | D18: =XLOOKUP(C18,PWT!$A$2:$A$35,PWT!$C$2:$C$35,"",0) | E18: =XLOOKUP(C18,WEO_Data!$B$8:$B$51,WEO_Data!$C$8:$C$51,"",0) | F18: =IF(D18="","",LN(D18)) | G18: =IF(E18="","",LN(E18)) | K18: =IF(OR(F18="",G18=""),"",G18-$B$2*F18) | L18: =K18 | M18: =L18-2*L17+L16 | N18: =IF(OR(K18="",L18=""),"",K18-L18)
C19: 2015 | D19: =XLOOKUP(C19,PWT!$A$2:$A$35,PWT!$C$2:$C$35,"",0) | E19: =XLOOKUP(C19,WEO_Data!$B$8:$B$51,WEO_Data!$C$8:$C$51,"",0) | F19: =IF(D19="","",LN(D19)) | G19: =IF(E19="","",LN(E19)) | K19: =IF(OR(F19="",G19=""),"",G19-$B$2*F19) | L19: =K19 | M19: =L19-2*L18+L17 | N19: =IF(OR(K19="",L19=""),"",K19-L19)
... C27: 2023 | D27: =XLOOKUP(C27,PWT!$A$2:$A$35,PWT!$C$2:$C$35,"",0) | E27: =XLOOKUP(C27,WEO_Data!$B$8:$B$51,WEO_Data!$C$8:$C$51,"",0) | F27: =IF(D27="","",LN(D27)) | G27: =IF(E27="","",LN(E27)) | K27: =IF(OR(F27="",G27=""),"",G27-$B$2*F27) | L27: =K27 | M27: =L27-2*L26+L25 | N27: =IF(OR(K27="",L27=""),"",K27-L27)
C34: K/Y anchor (avg 2015-2023) | D34: =AVERAGE(D49:D57)
D35: K/Y | E35: K | F35: Y | G35: LnZ trend | H35: Ystar_base | I35: Investment | J35: ΔK | K35: K_With | L35: Ystar_with | M35: Uplift | N35: Projected GDP | O35: Projected GDP Growth | P35: Baseline GDP Growth
C36: 2002 | D36: =IF(OR(E36="",F36=""),"",E36/F36) | E36: =XLOOKUP(C36,PWT!$A$2:$A$35,PWT!$C$2:$C$35,"",0) | F36: =XLOOKUP(C36,WEO_Data!$B$8:$B$51,WEO_Data!$C$8:$C$51,"",0) | G36: =XLOOKUP(C36,$C$6:$C$27,$L$6:$L$27,"",0) | H36: =IF(OR(E36="",G36=""),"",EXP(G36)*(E36^$B$2)) | I36: =IFERROR(XLOOKUP(C36,Investment!$B$2:$B$9,Investment!$C$2:$C$9,0,0),0) | J36: 0 | K36: =IF(E36="","",E36+J36) | L36: =IF(OR(K36="",G36=""),"",EXP(G36)*(K36^$B$2)) | M36: =IF(OR(L36="",H36=""),"",L36/H36-1) | N36: =IF(OR(F36="",M36=""),"",F36*(1+M36)) | P36: =IFERROR(XLOOKUP(C36,WEO_Data!$B$8:$B$51,WEO_Data!$D$8:$D$51,0,0)/100,"")
C37: 2003 | D37: =IF(OR(E37="",F37=""),"",E37/F37) | E37: =XLOOKUP(C37,PWT!$A$2:$A$35,PWT!$C$2:$C$35,"",0) | F37: =XLOOKUP(C37,WEO_Data!$B$8:$B$51,WEO_Data!$C$8:$C$51,"",0) | G37: =XLOOKUP(C37,$C$6:$C$27,$L$6:$L$27,"",0) | H37: =IF(OR(E37="",G37=""),"",EXP(G37)*(E37^$B$2)) | I37: =IFERROR(XLOOKUP(C37,Investment!$B$2:$B$9,Investment!$C$2:$C$9,0,0),0) | J37: 0 | K37: =IF(E37="","",E37+J37) | L37: =IF(OR(K37="",G37=""),"",EXP(G37)*(K37^$B$2)) | M37: =IF(OR(L37="",H37=""),"",L37/H37-1) | N37: =IF(OR(F37="",M37=""),"",F37*(1+M37)) | O37: =IF(OR(N36="",N37=""),"",N37/N36-1) | P37: =IFERROR(XLOOKUP(C37,WEO_Data!$B$8:$B$51,WEO_Data!$D$8:$D$51,0,0)/100,"")
C38: 2004 | D38: =IF(OR(E38="",F38=""),"",E38/F38) | E38: =XLOOKUP(C38,PWT!$A$2:$A$35,PWT!$C$2:$C$35,"",0) | F38: =XLOOKUP(C38,WEO_Data!$B$8:$B$51,WEO_Data!$C$8:$C$51,"",0) | G38: =XLOOKUP(C38,$C$6:$C$27,$L$6:$L$27,"",0) | H38: =IF(OR(E38="",G38=""),"",EXP(G38)*(E38^$B$2)) | I38: =IFERROR(XLOOKUP(C38,Investment!$B$2:$B$9,Investment!$C$2:$C$9,0,0),0) | J38: 0 | K38: =IF(E38="","",E38+J38) | L38: =IF(OR(K38="",G38=""),"",EXP(G38)*(K38^$B$2)) | M38: =IF(OR(L38="",H38=""),"",L38/H38-1) | N38: =IF(OR(F38="",M38=""),"",F38*(1+M38)) | O38: =IF(OR(N37="",N38=""),"",N38/N37-1) | P38: =IFERROR(XLOOKUP(C38,WEO_Data!$B$8:$B$51,WEO_Data!$D$8:$D$51,0,0)/100,"")
C39: 2005 | D39: =IF(OR(E39="",F39=""),"",E39/F39) | E39: =XLOOKUP(C39,PWT!$A$2:$A$35,PWT!$C$2:$C$35,"",0) | F39: =XLOOKUP(C39,WEO_Data!$B$8:$B$51,WEO_Data!$C$8:$C$51,"",0) | G39: =XLOOKUP(C39,$C$6:$C$27,$L$6:$L$27,"",0) | H39: =IF(OR(E39="",G39=""),"",EXP(G39)*(E39^$B$2)) | I39: =IFERROR(XLOOKUP(C39,Investment!$B$2:$B$9,Investment!$C$2:$C$9,0,0),0) | J39: 0 | K39: =IF(E39="","",E39+J39) | L39: =IF(OR(K39="",G39=""),"",EXP(G39)*(K39^$B$2)) | M39: =IF(OR(L39="",H39=""),"",L39/H39-1) | N39: =IF(OR(F39="",M39=""),"",F39*(1+M39)) | O39: =IF(OR(N38="",N39=""),"",N39/N38-1) | P39: =IFERROR(XLOOKUP(C39,WEO_Data!$B$8:$B$51,WEO_Data!$D$8:$D$51,0,0)/100,"")
C40: 2006 | D40: =IF(OR(E40="",F40=""),"",E40/F40) | E40: =XLOOKUP(C40,PWT!$A$2:$A$35,PWT!$C$2:$C$35,"",0) | F40: =XLOOKUP(C40,WEO_Data!$B$8:$B$51,WEO_Data!$C$8:$C$51,"",0) | G40: =XLOOKUP(C40,$C$6:$C$27,$L$6:$L$27,"",0) | H40: =IF(OR(E40="",G40=""),"",EXP(G40)*(E40^$B$2)) | I40: =IFERROR(XLOOKUP(C40,Investment!$B$2:$B$9,Investment!$C$2:$C$9,0,0),0) | J40: 0 | K40: =IF(E40="","",E40+J40) | L40: =IF(OR(K40="",G40=""),"",EXP(G40)*(K40^$B$2)) | M40: =IF(OR(L40="",H40=""),"",L40/H40-1) | N40: =IF(OR(F40="",M40=""),"",F40*(1+M40)) | O40: =IF(OR(N39="",N40=""),"",N40/N39-1) | P40: =IFERROR(XLOOKUP(C40,WEO_Data!$B$8:$B$51,WEO_Data!$D$8:$D$51,0,0)/100,"")
C41: 2007 | D41: =IF(OR(E41="",F41=""),"",E41/F41) | E41: =XLOOKUP(C41,PWT!$A$2:$A$35,PWT!$C$2:$C$35,"",0) | F41: =XLOOKUP(C41,WEO_Data!$B$8:$B$51,WEO_Data!$C$8:$C$51,"",0) | G41: =XLOOKUP(C41,$C$6:$C$27,$L$6:$L$27,"",0) | H41: =IF(OR(E41="",G41=""),"",EXP(G41)*(E41^$B$2)) | I41: =IFERROR(XLOOKUP(C41,Investment!$B$2:$B$9,Investment!$C$2:$C$9,0,0),0) | J41: 0 | K41: =IF(E41="","",E41+J41) | L41: =IF(OR(K41="",G41=""),"",EXP(G41)*(K41^$B$2)) | M41: =IF(OR(L41="",H41=""),"",L41/H41-1) | N41: =IF(OR(F41="",M41=""),"",F41*(1+M41)) | O41: =IF(OR(N40="",N41=""),"",N41/N40-1) | P41: =IFERROR(XLOOKUP(C41,WEO_Data!$B$8:$B$51,WEO_Data!$D$8:$D$51,0,0)/100,"")
C42: 2008 | D42: =IF(OR(E42="",F42=""),"",E42/F42) | E42: =XLOOKUP(C42,PWT!$A$2:$A$35,PWT!$C$2:$C$35,"",0) | F42: =XLOOKUP(C42,WEO_Data!$B$8:$B$51,WEO_Data!$C$8:$C$51,"",0) | G42: =XLOOKUP(C42,$C$6:$C$27,$L$6:$L$27,"",0) | H42: =IF(OR(E42="",G42=""),"",EXP(G42)*(E42^$B$2)) | I42: =IFERROR(XLOOKUP(C42,Investment!$B$2:$B$9,Investment!$C$2:$C$9,0,0),0) | J42: 0 | K42: =IF(E42="","",E42+J42) | L42: =IF(OR(K42="",G42=""),"",EXP(G42)*(K42^$B$2)) | M42: =IF(OR(L42="",H42=""),"",L42/H42-1) | N42: =IF(OR(F42="",M42=""),"",F42*(1+M42)) | O42: =IF(OR(N41="",N42=""),"",N42/N41-1) | P42: =IFERROR(XLOOKUP(C42,WEO_Data!$B$8:$B$51,WEO_Data!$D$8:$D$51,0,0)/100,"")
C43: 2009 | D43: =IF(OR(E43="",F43=""),"",E43/F43) | E43: =XLOOKUP(C43,PWT!$A$2:$A$35,PWT!$C$2:$C$35,"",0) | F43: =XLOOKUP(C43,WEO_Data!$B$8:$B$51,WEO_Data!$C$8:$C$51,"",0) | G43: =XLOOKUP(C43,$C$6:$C$27,$L$6:$L$27,"",0) | H43: =IF(OR(E43="",G43=""),"",EXP(G43)*(E43^$B$2)) | I43: =IFERROR(XLOOKUP(C43,Investment!$B$2:$B$9,Investment!$C$2:$C$9,0,0),0) | J43: 0 | K43: =IF(E43="","",E43+J43) | L43: =IF(OR(K43="",G43=""),"",EXP(G43)*(K43^$B$2)) | M43: =IF(OR(L43="",H43=""),"",L43/H43-1) | N43: =IF(OR(F43="",M43=""),"",F43*(1+M43)) | O43: =IF(OR(N42="",N43=""),"",N43/N42-1) | P43: =IFERROR(XLOOKUP(C43,WEO_Data!$B$8:$B$51,WEO_Data!$D$8:$D$51,0,0)/100,"")
C44: 2010 | D44: =IF(OR(E44="",F44=""),"",E44/F44) | E44: =XLOOKUP(C44,PWT!$A$2:$A$35,PWT!$C$2:$C$35,"",0) | F44: =XLOOKUP(C44,WEO_Data!$B$8:$B$51,WEO_Data!$C$8:$C$51,"",0) | G44: =XLOOKUP(C44,$C$6:$C$27,$L$6:$L$27,"",0) | H44: =IF(OR(E44="",G44=""),"",EXP(G44)*(E44^$B$2)) | I44: =IFERROR(XLOOKUP(C44,Investment!$B$2:$B$9,Investment!$C$2:$C$9,0,0),0) | J44: 0 | K44: =IF(E44="","",E44+J44) | L44: =IF(OR(K44="",G44=""),"",EXP(G44)*(K44^$B$2)) | M44: =IF(OR(L44="",H44=""),"",L44/H44-1) | N44: =IF(OR(F44="",M44=""),"",F44*(1+M44)) | O44: =IF(OR(N43="",N44=""),"",N44/N43-1) | P44: =IFERROR(XLOOKUP(C44,WEO_Data!$B$8:$B$51,WEO_Data!$D$8:$D$51,0,0)/100,"")
C45: 2011 | D45: =IF(OR(E45="",F45=""),"",E45/F45) | E45: =XLOOKUP(C45,PWT!$A$2:$A$35,PWT!$C$2:$C$35,"",0) | F45: =XLOOKUP(C45,WEO_Data!$B$8:$B$51,WEO_Data!$C$8:$C$51,"",0) | G45: =XLOOKUP(C45,$C$6:$C$27,$L$6:$L$27,"",0) | H45: =IF(OR(E45="",G45=""),"",EXP(G45)*(E45^$B$2)) | I45: =IFERROR(XLOOKUP(C45,Investment!$B$2:$B$9,Investment!$C$2:$C$9,0,0),0) | J45: 0 | K45: =IF(E45="","",E45+J45) | L45: =IF(OR(K45="",G45=""),"",EXP(G45)*(K45^$B$2)) | M45: =IF(OR(L45="",H45=""),"",L45/H45-1) | N45: =IF(OR(F45="",M45=""),"",F45*(1+M45)) | O45: =IF(OR(N44="",N45=""),"",N45/N44-1) | P45: =IFERROR(XLOOKUP(C45,WEO_Data!$B$8:$B$51,WEO_Data!$D$8:$D$51,0,0)/100,"")
C46: 2012 | D46: =IF(OR(E46="",F46=""),"",E46/F46) | E46: =XLOOKUP(C46,PWT!$A$2:$A$35,PWT!$C$2:$C$35,"",0) | F46: =XLOOKUP(C46,WEO_Data!$B$8:$B$51,WEO_Data!$C$8:$C$51,"",0) | G46: =XLOOKUP(C46,$C$6:$C$27,$L$6:$L$27,"",0) | H46: =IF(OR(E46="",G46=""),"",EXP(G46)*(E46^$B$2)) | I46: =IFERROR(XLOOKUP(C46,Investment!$B$2:$B$9,Investment!$C$2:$C$9,0,0),0) | J46: 0 | K46: =IF(E46="","",E46+J46) | L46: =IF(OR(K46="",G46=""),"",EXP(G46)*(K46^$B$2)) | M46: =IF(OR(L46="",H46=""),"",L46/H46-1) | N46: =IF(OR(F46="",M46=""),"",F46*(1+M46)) | O46: =IF(OR(N45="",N46=""),"",N46/N45-1) | P46: =IFERROR(XLOOKUP(C46,WEO_Data!$B$8:$B$51,WEO_Data!$D$8:$D$51,0,0)/100,"")
C47: 2013 | D47: =IF(OR(E47="",F47=""),"",E47/F47) | E47: =XLOOKUP(C47,PWT!$A$2:$A$35,PWT!$C$2:$C$35,"",0) | F47: =XLOOKUP(C47,WEO_Data!$B$8:$B$51,WEO_Data!$C$8:$C$51,"",0) | G47: =XLOOKUP(C47,$C$6:$C$27,$L$6:$L$27,"",0) | H47: =IF(OR(E47="",G47=""),"",EXP(G47)*(E47^$B$2)) | I47: =IFERROR(XLOOKUP(C47,Investment!$B$2:$B$9,Investment!$C$2:$C$9,0,0),0) | J47: 0 | K47: =IF(E47="","",E47+J47) | L47: =IF(OR(K47="",G47=""),"",EXP(G47)*(K47^$B$2)) | M47: =IF(OR(L47="",H47=""),"",L47/H47-1) | N47: =IF(OR(F47="",M47=""),"",F47*(1+M47)) | O47: =IF(OR(N46="",N47=""),"",N47/N46-1) | P47: =IFERROR(XLOOKUP(C47,WEO_Data!$B$8:$B$51,WEO_Data!$D$8:$D$51,0,0)/100,"")
C48: 2014 | D48: =IF(OR(E48="",F48=""),"",E48/F48) | E48: =XLOOKUP(C48,PWT!$A$2:$A$35,PWT!$C$2:$C$35,"",0) | F48: =XLOOKUP(C48,WEO_Data!$B$8:$B$51,WEO_Data!$C$8:$C$51,"",0) | G48: =XLOOKUP(C48,$C$6:$C$27,$L$6:$L$27,"",0) | H48: =IF(OR(E48="",G48=""),"",EXP(G48)*(E48^$B$2)) | I48: =IFERROR(XLOOKUP(C48,Investment!$B$2:$B$9,Investment!$C$2:$C$9,0,0),0) | J48: 0 | K48: =IF(E48="","",E48+J48) | L48: =IF(OR(K48="",G48=""),"",EXP(G48)*(K48^$B$2)) | M48: =IF(OR(L48="",H48=""),"",L48/H48-1) | N48: =IF(OR(F48="",M48=""),"",F48*(1+M48)) | O48: =IF(OR(N47="",N48=""),"",N48/N47-1) | P48: =IFERROR(XLOOKUP(C48,WEO_Data!$B$8:$B$51,WEO_Data!$D$8:$D$51,0,0)/100,"")
... C53: 2019 | D53: =IF(OR(E53="",F53=""),"",E53/F53) | E53: =XLOOKUP(C53,PWT!$A$2:$A$35,PWT!$C$2:$C$35,"",0) | F53: =XLOOKUP(C53,WEO_Data!$B$8:$B$51,WEO_Data!$C$8:$C$51,"",0) | G53: =XLOOKUP(C53,$C$6:$C$27,$L$6:$L$27,"",0) | H53: =IF(OR(E53="",G53=""),"",EXP(G53)*(E53^$B$2)) | I53: =IFERROR(XLOOKUP(C53,Investment!$B$2:$B$9,Investment!$C$2:$C$9,0,0),0) | J53: 0 | K53: =IF(E53="","",E53+J53) | L53: =IF(OR(K53="",G53=""),"",EXP(G53)*(K53^$B$2)) | M53: =IF(OR(L53="",H53=""),"",L53/H53-1) | N53: =IF(OR(F53="",M53=""),"",F53*(1+M53)) | O53: =IF(OR(N52="",N53=""),"",N53/N52-1) | P53: =IFERROR(XLOOKUP(C53,WEO_Data!$B$8:$B$51,WEO_Data!$D$8:$D$51,0,0)/100,"")
C54: 2020 | D54: =$D$34 | E54: =$D$34*F54 | F54: =XLOOKUP(C54,WEO_Data!$B$8:$B$51,WEO_Data!$C$8:$C$51,"",0) | G54: =XLOOKUP(C54,$C$6:$C$27,$L$6:$L$27,"",0) | H54: =IF(OR(E54="",G54=""),"",EXP(G54)*(E54^$B$2)) | I54: =IFERROR(XLOOKUP(C54,Investment!$B$2:$B$9,Investment!$C$2:$C$9,0,0),0) | J54: 0 | K54: =IF(E54="","",E54+J54) | L54: =IF(OR(K54="",G54=""),"",EXP(G54)*(K54^$B$2)) | M54: =IF(OR(L54="",H54=""),"",L54/H54-1) | N54: =IF(OR(F54="",M54=""),"",F54*(1+M54)) | O54: =IF(OR(N53="",N54=""),"",N54/N53-1) | P54: =IFERROR(XLOOKUP(C54,WEO_Data!$B$8:$B$51,WEO_Data!$D$8:$D$51,0,0)/100,"")
C55: 2021 | D55: =$D$34 | E55: =$D$34*F55 | F55: =XLOOKUP(C55,WEO_Data!$B$8:$B$51,WEO_Data!$C$8:$C$51,"",0) | G55: =XLOOKUP(C55,$C$6:$C$27,$L$6:$L$27,"",0) | H55: =IF(OR(E55="",G55=""),"",EXP(G55)*(E55^$B$2)) | I55: =IFERROR(XLOOKUP(C55,Investment!$B$2:$B$9,Investment!$C$2:$C$9,0,0),0) | J55: 0 | K55: =IF(E55="","",E55+J55) | L55: =IF(OR(K55="",G55=""),"",EXP(G55)*(K55^$B$2)) | M55: =IF(OR(L55="",H55=""),"",L55/H55-1) | N55: =IF(OR(F55="",M55=""),"",F55*(1+M55)) | O55: =IF(OR(N54="",N55=""),"",N55/N54-1) | P55: =IFERROR(XLOOKUP(C55,WEO_Data!$B$8:$B$51,WEO_Data!$D$8:$D$51,0,0)/100,"")
C56: 2022 | D56: =$D$34 | E56: =$D$34*F56 | F56: =XLOOKUP(C56,WEO_Data!$B$8:$B$51,WEO_Data!$C$8:$C$51,"",0) | G56: =XLOOKUP(C56,$C$6:$C$27,$L$6:$L$27,"",0) | H56: =IF(OR(E56="",G56=""),"",EXP(G56)*(E56^$B$2)) | I56: =IFERROR(XLOOKUP(C56,Investment!$B$2:$B$9,Investment!$C$2:$C$9,0,0),0) | J56: 0 | K56: =IF(E56="","",E56+J56) | L56: =IF(OR(K56="",G56=""),"",EXP(G56)*(K56^$B$2)) | M56: =IF(OR(L56="",H56=""),"",L56/H56-1) | N56: =IF(OR(F56="",M56=""),"",F56*(1+M56)) | O56: =IF(OR(N55="",N56=""),"",N56/N55-1) | P56: =IFERROR(XLOOKUP(C56,WEO_Data!$B$8:$B$51,WEO_Data!$D$8:$D$51,0,0)/100,"")
C57: 2023 | D57: =$D$34 | E57: =$D$34*F57 | F57: =XLOOKUP(C57,WEO_Data!$B$8:$B$51,WEO_Data!$C$8:$C$51,"",0) | G57: =XLOOKUP(C57,$C$6:$C$27,$L$6:$L$27,"",0) | H57: =IF(OR(E57="",G57=""),"",EXP(G57)*(E57^$B$2)) | I57: =IFERROR(XLOOKUP(C57,Investment!$B$2:$B$9,Investment!$C$2:$C$9,0,0),0) | J57: 0 | K57: =IF(E57="","",E57+J57) | L57: =IF(OR(K57="",G57=""),"",EXP(G57)*(K57^$B$2)) | M57: =IF(OR(L57="",H57=""),"",L57/H57-1) | N57: =IF(OR(F57="",M57=""),"",F57*(1+M57)) | O57: =IF(OR(N56="",N57=""),"",N57/N56-1) | P57: =IFERROR(XLOOKUP(C57,WEO_Data!$B$8:$B$51,WEO_Data!$D$8:$D$51,0,0)/100,"")
C58: 2024 | D58: =$D$34 | E58: =$D$34*F58 | F58: =XLOOKUP(C58,WEO_Data!$B$8:$B$51,WEO_Data!$C$8:$C$51,"",0) | G58: =TREND($G$36:$G$57,$C$36:$C$57,C58) | H58: =IF(OR(E58="",G58=""),"",EXP(G58)*(E58^$B$2)) | I58: =IFERROR(XLOOKUP(C58,Investment!$B$2:$B$9,Investment!$C$2:$C$9,0,0),0) | J58: 0 | K58: =IF(E58="","",E58+J58) | L58: =IF(OR(K58="",G58=""),"",EXP(G58)*(K58^$B$2)) | M58: =IF(OR(L58="",H58=""),"",L58/H58-1) | N58: =IF(OR(F58="",M58=""),"",F58*(1+M58)) | O58: =IF(OR(N57="",N58=""),"",N58/N57-1) | P58: =IFERROR(XLOOKUP(C58,WEO_Data!$B$8:$B$51,WEO_Data!$D$8:$D$51,0,0)/100,"")
C59: 2025 | D59: =$D$34 | E59: =$D$34*F59 | F59: =XLOOKUP(C59,WEO_Data!$B$8:$B$51,WEO_Data!$C$8:$C$51,"",0) | G59: =TREND($G$36:$G$57,$C$36:$C$57,C59) | H59: =IF(OR(E59="",G59=""),"",EXP(G59)*(E59^$B$2)) | I59: =IFERROR(XLOOKUP(C59,Investment!$B$2:$B$9,Investment!$C$2:$C$9,0,0),0) | J59: 0 | K59: =IF(E59="","",E59+J59) | L59: =IF(OR(K59="",G59=""),"",EXP(G59)*(K59^$B$2)) | M59: =IF(OR(L59="",H59=""),"",L59/H59-1) | N59: =IF(OR(F59="",M59=""),"",F59*(1+M59)) | O59: =IF(OR(N58="",N59=""),"",N59/N58-1) | P59: =IFERROR(XLOOKUP(C59,WEO_Data!$B$8:$B$51,WEO_Data!$D$8:$D$51,0,0)/100,"")
C60: 2026 | D60: =$D$34 | E60: =$D$34*F60 | F60: =XLOOKUP(C60,WEO_Data!$B$8:$B$51,WEO_Data!$C$8:$C$51,"",0) | G60: =TREND($G$36:$G$57,$C$36:$C$57,C60) | H60: =IF(OR(E60="",G60=""),"",EXP(G60)*(E60^$B$2)) | I60: =IFERROR(XLOOKUP(C60,Investment!$B$2:$B$9,Investment!$C$2:$C$9,0,0),0) | J60: =(1-$B$3)*J59+I60 | K60: =IF(E60="","",E60+J60) | L60: =IF(OR(K60="",G60=""),"",EXP(G60)*(K60^$B$2)) | M60: =IF(OR(L60="",H60=""),"",L60/H60-1) | N60: =IF(OR(F60="",M60=""),"",F60*(1+M60)) | O60: =IF(OR(N59="",N60=""),"",N60/N59-1) | P60: =IFERROR(XLOOKUP(C60,WEO_Data!$B$8:$B$51,WEO_Data!$D$8:$D$51,0,0)/100,"")
C61: 2027 | D61: =$D$34 | E61: =$D$34*F61 | F61: =XLOOKUP(C61,WEO_Data!$B$8:$B$51,WEO_Data!$C$8:$C$51,"",0) | G61: =TREND($G$36:$G$57,$C$36:$C$57,C61) | H61: =IF(OR(E61="",G61=""),"",EXP(G61)*(E61^$B$2)) | I61: =IFERROR(XLOOKUP(C61,Investment!$B$2:$B$9,Investment!$C$2:$C$9,0,0),0) | J61: =(1-$B$3)*J60+I61 | K61: =IF(E61="","",E61+J61) | L61: =IF(OR(K61="",G61=""),"",EXP(G61)*(K61^$B$2)) | M61: =IF(OR(L61="",H61=""),"",L61/H61-1) | N61: =IF(OR(F61="",M61=""),"",F61*(1+M61)) | O61: =IF(OR(N60="",N61=""),"",N61/N60-1) | P61: =IFERROR(XLOOKUP(C61,WEO_Data!$B$8:$B$51,WEO_Data!$D$8:$D$51,0,0)/100,"")
C62: 2028 | D62: =$D$34 | E62: =$D$34*F62 | F62: =XLOOKUP(C62,WEO_Data!$B$8:$B$51,WEO_Data!$C$8:$C$51,"",0) | G62: =TREND($G$36:$G$57,$C$36:$C$57,C62) | H62: =IF(OR(E62="",G62=""),"",EXP(G62)*(E62^$B$2)) | I62: =IFERROR(XLOOKUP(C62,Investment!$B$2:$B$9,Investment!$C$2:$C$9,0,0),0) | J62: =(1-$B$3)*J61+I62 | K62: =IF(E62="","",E62+J62) | L62: =IF(OR(K62="",G62=""),"",EXP(G62)*(K62^$B$2)) | M62: =IF(OR(L62="",H62=""),"",L62/H62-1) | N62: =IF(OR(F62="",M62=""),"",F62*(1+M62)) | O62: =IF(OR(N61="",N62=""),"",N62/N61-1) | P62: =IFERROR(XLOOKUP(C62,WEO_Data!$B$8:$B$51,WEO_Data!$D$8:$D$51,0,0)/100,"")
C63: 2029 | D63: =$D$34 | E63: =$D$34*F63 | F63: =XLOOKUP(C63,WEO_Data!$B$8:$B$51,WEO_Data!$C$8:$C$51,"",0) | G63: =TREND($G$36:$G$57,$C$36:$C$57,C63) | H63: =IF(OR(E63="",G63=""),"",EXP(G63)*(E63^$B$2)) | I63: =IFERROR(XLOOKUP(C63,Investment!$B$2:$B$9,Investment!$C$2:$C$9,0,0),0) | J63: =(1-$B$3)*J62+I63 | K63: =IF(E63="","",E63+J63) | L63: =IF(OR(K63="",G63=""),"",EXP(G63)*(K63^$B$2)) | M63: =IF(OR(L63="",H63=""),"",L63/H63-1) | N63: =IF(OR(F63="",M63=""),"",F63*(1+M63)) | O63: =IF(OR(N62="",N63=""),"",N63/N62-1) | P63: =IFERROR(XLOOKUP(C63,WEO_Data!$B$8:$B$51,WEO_Data!$D$8:$D$51,0,0)/100,"")
C64: 2030 | D64: =$D$34 | E64: =$D$34*F64 | F64: =XLOOKUP(C64,WEO_Data!$B$8:$B$51,WEO_Data!$C$8:$C$51,"",0) | G64: =TREND($G$36:$G$57,$C$36:$C$57,C64) | H64: =IF(OR(E64="",G64=""),"",EXP(G64)*(E64^$B$2)) | I64: =IFERROR(XLOOKUP(C64,Investment!$B$2:$B$9,Investment!$C$2:$C$9,0,0),0) | J64: =(1-$B$3)*J63+I64 | K64: =IF(E64="","",E64+J64) | L64: =IF(OR(K64="",G64=""),"",EXP(G64)*(K64^$B$2)) | M64: =IF(OR(L64="",H64=""),"",L64/H64-1) | N64: =IF(OR(F64="",M64=""),"",F64*(1+M64)) | O64: =IF(OR(N63="",N64=""),"",N64/N63-1) | P64: =IFERROR(XLOOKUP(C64,WEO_Data!$B$8:$B$51,WEO_Data!$D$8:$D$51,0,0)/100,"")
C65: 2031 | D65: =$D$34 | E65: =$D$34*F65 | F65: =XLOOKUP(C65,WEO_Data!$B$8:$B$51,WEO_Data!$C$8:$C$51,"",0) | G65: =TREND($G$36:$G$57,$C$36:$C$57,C65) | H65: =IF(OR(E65="",G65=""),"",EXP(G65)*(E65^$B$2)) | I65: =IFERROR(XLOOKUP(C65,Investment!$B$2:$B$9,Investment!$C$2:$C$9,0,0),0) | J65: =(1-$B$3)*J64+I65 | K65: =IF(E65="","",E65+J65) | L65: =IF(OR(K65="",G65=""),"",EXP(G65)*(K65^$B$2)) | M65: =IF(OR(L65="",H65=""),"",L65/H65-1) | N65: =IF(OR(F65="",M65=""),"",F65*(1+M65)) | O65: =IF(OR(N64="",N65=""),"",N65/N64-1) | P65: =IFERROR(XLOOKUP(C65,WEO_Data!$B$8:$B$51,WEO_Data!$D$8:$D$51,0,0)/100,"")
C66: 2032 | D66: =$D$34 | E66: =$D$34*F66 | F66: =XLOOKUP(C66,WEO_Data!$B$8:$B$51,WEO_Data!$C$8:$C$51,"",0) | G66: =TREND($G$36:$G$57,$C$36:$C$57,C66) | H66: =IF(OR(E66="",G66=""),"",EXP(G66)*(E66^$B$2)) | I66: =IFERROR(XLOOKUP(C66,Investment!$B$2:$B$9,Investment!$C$2:$C$9,0,0),0) | J66: =(1-$B$3)*J65+I66 | K66: =IF(E66="","",E66+J66) | L66: =IF(OR(K66="",G66=""),"",EXP(G66)*(K66^$B$2)) | M66: =IF(OR(L66="",H66=""),"",L66/H66-1) | N66: =IF(OR(F66="",M66=""),"",F66*(1+M66)) | O66: =IF(OR(N65="",N66=""),"",N66/N65-1) | P66: =IFERROR(XLOOKUP(C66,WEO_Data!$B$8:$B$51,WEO_Data!$D$8:$D$51,0,0)/100,"")
C67: 2033 | D67: =$D$34 | E67: =$D$34*F67 | F67: =XLOOKUP(C67,WEO_Data!$B$8:$B$51,WEO_Data!$C$8:$C$51,"",0) | G67: =TREND($G$36:$G$57,$C$36:$C$57,C67) | H67: =IF(OR(E67="",G67=""),"",EXP(G67)*(E67^$B$2)) | I67: =IFERROR(XLOOKUP(C67,Investment!$B$2:$B$9,Investment!$C$2:$C$9,0,0),0) | J67: =(1-$B$3)*J66+I67 | K67: =IF(E67="","",E67+J67) | L67: =IF(OR(K67="",G67=""),"",EXP(G67)*(K67^$B$2)) | M67: =IF(OR(L67="",H67=""),"",L67/H67-1) | N67: =IF(OR(F67="",M67=""),"",F67*(1+M67)) | O67: =IF(OR(N66="",N67=""),"",N67/N66-1) | P67: =IFERROR(XLOOKUP(C67,WEO_Data!$B$8:$B$51,WEO_Data!$D$8:$D$51,0,0)/100,"")
C68: 2034 | D68: =$D$34 | E68: =$D$34*F68 | F68: =XLOOKUP(C68,WEO_Data!$B$8:$B$51,WEO_Data!$C$8:$C$51,"",0) | G68: =TREND($G$36:$G$57,$C$36:$C$57,C68) | H68: =IF(OR(E68="",G68=""),"",EXP(G68)*(E68^$B$2)) | I68: =IFERROR(XLOOKUP(C68,Investment!$B$2:$B$9,Investment!$C$2:$C$9,0,0),0) | J68: =(1-$B$3)*J67+I68 | K68: =IF(E68="","",E68+J68) | L68: =IF(OR(K68="",G68=""),"",EXP(G68)*(K68^$B$2)) | M68: =IF(OR(L68="",H68=""),"",L68/H68-1) | N68: =IF(OR(F68="",M68=""),"",F68*(1+M68)) | O68: =IF(OR(N67="",N68=""),"",N68/N67-1) | P68: =IFERROR(XLOOKUP(C68,WEO_Data!$B$8:$B$51,WEO_Data!$D$8:$D$51,0,0)/100,"")
C69: 2035 | D69: =$D$34 | E69: =$D$34*F69 | F69: =XLOOKUP(C69,WEO_Data!$B$8:$B$51,WEO_Data!$C$8:$C$51,"",0) | G69: =TREND($G$36:$G$57,$C$36:$C$57,C69) | H69: =IF(OR(E69="",G69=""),"",EXP(G69)*(E69^$B$2)) | I69: =IFERROR(XLOOKUP(C69,Investment!$B$2:$B$9,Investment!$C$2:$C$9,0,0),0) | J69: =(1-$B$3)*J68+I69 | K69: =IF(E69="","",E69+J69) | L69: =IF(OR(K69="",G69=""),"",EXP(G69)*(K69^$B$2)) | M69: =IF(OR(L69="",H69=""),"",L69/H69-1) | N69: =IF(OR(F69="",M69=""),"",F69*(1+M69)) | O69: =IF(OR(N68="",N69=""),"",N69/N68-1) | P69: =IFERROR(XLOOKUP(C69,WEO_Data!$B$8:$B$51,WEO_Data!$D$8:$D$51,0,0)/100,"")
C70: 2036 | D70: =$D$34 | E70: =$D$34*F70 | F70: =XLOOKUP(C70,WEO_Data!$B$8:$B$51,WEO_Data!$C$8:$C$51,"",0) | G70: =TREND($G$36:$G$57,$C$36:$C$57,C70) | H70: =IF(OR(E70="",G70=""),"",EXP(G70)*(E70^$B$2)) | I70: =IFERROR(XLOOKUP(C70,Investment!$B$2:$B$9,Investment!$C$2:$C$9,0,0),0) | J70: =(1-$B$3)*J69+I70 | K70: =IF(E70="","",E70+J70) | L70: =IF(OR(K70="",G70=""),"",EXP(G70)*(K70^$B$2)) | M70: =IF(OR(L70="",H70=""),"",L70/H70-1) | N70: =IF(OR(F70="",M70=""),"",F70*(1+M70)) | O70: =IF(OR(N69="",N70=""),"",N70/N69-1) | P70: =IFERROR(XLOOKUP(C70,WEO_Data!$B$8:$B$51,WEO_Data!$D$8:$D$51,0,0)/100,"")
C71: 2037 | D71: =$D$34 | E71: =$D$34*F71 | F71: =XLOOKUP(C71,WEO_Data!$B$8:$B$51,WEO_Data!$C$8:$C$51,"",0) | G71: =TREND($G$36:$G$57,$C$36:$C$57,C71) | H71: =IF(OR(E71="",G71=""),"",EXP(G71)*(E71^$B$2)) | I71: =IFERROR(XLOOKUP(C71,Investment!$B$2:$B$9,Investment!$C$2:$C$9,0,0),0) | J71: =(1-$B$3)*J70+I71 | K71: =IF(E71="","",E71+J71) | L71: =IF(OR(K71="",G71=""),"",EXP(G71)*(K71^$B$2)) | M71: =IF(OR(L71="",H71=""),"",L71/H71-1) | N71: =IF(OR(F71="",M71=""),"",F71*(1+M71)) | O71: =IF(OR(N70="",N71=""),"",N71/N70-1) | P71: =IFERROR(XLOOKUP(C71,WEO_Data!$B$8:$B$51,WEO_Data!$D$8:$D$51,0,0)/100,"")
... C75: 2041 | D75: =$D$34 | E75: =$D$34*F75 | F75: =XLOOKUP(C75,WEO_Data!$B$8:$B$51,WEO_Data!$C$8:$C$51,"",0) | G75: =TREND($G$36:$G$57,$C$36:$C$57,C75) | H75: =IF(OR(E75="",G75=""),"",EXP(G75)*(E75^$B$2)) | I75: =IFERROR(XLOOKUP(C75,Investment!$B$2:$B$9,Investment!$C$2:$C$9,0,0),0) | J75: =(1-$B$3)*J74+I75 | K75: =IF(E75="","",E75+J75) | L75: =IF(OR(K75="",G75=""),"",EXP(G75)*(K75^$B$2)) | M75: =IF(OR(L75="",H75=""),"",L75/H75-1) | N75: =IF(OR(F75="",M75=""),"",F75*(1+M75)) | O75: =IF(OR(N74="",N75=""),"",N75/N74-1) | P75: =IFERROR(XLOOKUP(C75,WEO_Data!$B$8:$B$51,WEO_Data!$D$8:$D$51,0,0)/100,"")

Sheet Investment
B1: Year | C1: Project Investment (Deflated)
B2: 2026 | C2: =6500/8
B3: 2027 | C3: =6500/8
B4: 2028 | C4: =6500/8
B5: 2029 | C5: =6500/8
B6: 2030 | C6: =6500/8
B7: 2031 | C7: =6500/8
B8: 2032 | C8: =6500/8
B9: 2033 | C9: =6500/8

Sheet CFC data
A1: DATE | B1: TIME PERIOD | C1: Consumption of fixed capital (IDCM.A.N.GE.W2.S1.S1.D.P51C.N1G._T._Z.XDC.V.N) | D1: Capital Stock | E1: Depreciation rate
A2: 35430 | B2: 1996 | C2: 3.0451509e+08 | D2: =XLOOKUP(B2,PWT!$A$2:$A$35,PWT!$C$2:$C$35,"",0) | E2: =IF(OR(C2="",D2=""),"",C2/D2)
A3: 35795 | B3: 1997 | C3: 3.8364166e+08 | D3: =XLOOKUP(B3,PWT!$A$2:$A$35,PWT!$C$2:$C$35,"",0) | E3: =IF(OR(C3="",D3=""),"",C3/D3)
A4: 36160 | B4: 1998 | C4: 5.1639712e+08 | D4: =XLOOKUP(B4,PWT!$A$2:$A$35,PWT!$C$2:$C$35,"",0) | E4: =IF(OR(C4="",D4=""),"",C4/D4)
A5: 36525 | B5: 1999 | C5: 6.6160383e+08 | D5: =XLOOKUP(B5,PWT!$A$2:$A$35,PWT!$C$2:$C$35,"",0) | E5: =IF(OR(C5="",D5=""),"",C5/D5)
A6: 36891 | B6: 2000 | C6: 6.31701e+08 | D6: =XLOOKUP(B6,PWT!$A$2:$A$35,PWT!$C$2:$C$35,"",0) | E6: =IF(OR(C6="",D6=""),"",C6/D6)
A7: 37256 | B7: 2001 | C7: 7.0698373e+08 | D7: =XLOOKUP(B7,PWT!$A$2:$A$35,PWT!$C$2:$C$35,"",0) | E7: =IF(OR(C7="",D7=""),"",C7/D7)
A8: 37621 | B8: 2002 | C8: 7.9011257e+08 | D8: =XLOOKUP(B8,PWT!$A$2:$A$35,PWT!$C$2:$C$35,"",0) | E8: =IF(OR(C8="",D8=""),"",C8/D8)
A9: 37986 | B9: 2003 | C9: 9.3291622e+08 | D9: =XLOOKUP(B9,PWT!$A$2:$A$35,PWT!$C$2:$C$35,"",0) | E9: =IF(OR(C9="",D9=""),"",C9/D9)
A10: 38352 | B10: 2004 | C10: 9.7681854e+08 | D10: =XLOOKUP(B10,PWT!$A$2:$A$35,PWT!$C$2:$C$35,"",0) | E10: =IF(OR(C10="",D10=""),"",C10/D10)
A11: 38717 | B11: 2005 | C11: 1.1134501e+09 | D11: =XLOOKUP(B11,PWT!$A$2:$A$35,PWT!$C$2:$C$35,"",0) | E11: =IF(OR(C11="",D11=""),"",C11/D11)
A12: 39082 | B12: 2006 | C12: 1.3063731e+09 | D12: =XLOOKUP(B12,PWT!$A$2:$A$35,PWT!$C$2:$C$35,"",0) | E12: =IF(OR(C12="",D12=""),"",C12/D12)
A13: 39447 | B13: 2007 | C13: 1.61703e+09 | D13: =XLOOKUP(B13,PWT!$A$2:$A$35,PWT!$C$2:$C$35,"",0) | E13: =IF(OR(C13="",D13=""),"",C13/D13)
... A29: 45291 | B29: 2023 | C29: 9.4106578e+09 | D29: =XLOOKUP(B29,PWT!$A$2:$A$35,PWT!$C$2:$C$35,"",0) | E29: =IF(OR(C29="",D29=""),"",C29/D29)

Sheet PWT
A1: year | B1: rnna | C1: rnna_extended | D1: avg_growth_2015_2019
A2: 1990 | B2: 269494.41 | C2: =B2 | D2: =AVERAGE((B28/B27)-1,(B29/B28)-1,(B30/B29)-1,(B31/B30)-1)
A3: 1991 | B3: 271117.44 | C3: =IF(ISNUMBER(B3),B3,C2*(1+$D$2))
A4: 1992 | B4: 266614.81 | C4: =IF(ISNUMBER(B4),B4,C3*(1+$D$2))
A5: 1993 | B5: 256535.47 | C5: =IF(ISNUMBER(B5),B5,C4*(1+$D$2))
A6: 1994 | B6: 249672.47 | C6: =IF(ISNUMBER(B6),B6,C5*(1+$D$2))
A7: 1995 | B7: 245497.81 | C7: =IF(ISNUMBER(B7),B7,C6*(1+$D$2))
A8: 1996 | B8: 242089.69 | C8: =IF(ISNUMBER(B8),B8,C7*(1+$D$2))
A9: 1997 | B9: 239425.36 | C9: =IF(ISNUMBER(B9),B9,C8*(1+$D$2))
A10: 1998 | B10: 239121.89 | C10: =IF(ISNUMBER(B10),B10,C9*(1+$D$2))
A11: 1999 | B11: 239199.27 | C11: =IF(ISNUMBER(B11),B11,C10*(1+$D$2))
A12: 2000 | B12: 239171.61 | C12: =IF(ISNUMBER(B12),B12,C11*(1+$D$2))
A13: 2001 | B13: 240066.27 | C13: =IF(ISNUMBER(B13),B13,C12*(1+$D$2))
A14: 2002 | B14: 240523.05 | C14: =IF(ISNUMBER(B14),B14,C13*(1+$D$2))
... A31: 2019 | B31: 298215.06 | C31: =IF(ISNUMBER(B31),B31,C30*(1+$D$2))
A32: 2020 | C32: =IF(ISNUMBER(B32),B32,C31*(1+$D$2))
A33: 2021 | C33: =IF(ISNUMBER(B33),B33,C32*(1+$D$2))
A34: 2022 | C34: =IF(ISNUMBER(B34),B34,C33*(1+$D$2))
A35: 2023 | C35: =IF(ISNUMBER(B35),B35,C34*(1+$D$2))

Sheet WEO_Data
B1: WEO Country Code | C1: 915 | D1: 915
B2: WEO Subject Code | C2: NGDP_R | D2: NGDP_RPCH
B3: Country | C3: Georgia | D3: Georgia
B4: Subject Descriptor | C4: Gross domestic product, constant prices | D4: Gross domestic product, constant prices
B5: Units | C5: National currency | D5: Percent change
B6: Scale | C6: Billions | D6: Units
B7: Country/Series-specific Notes | C7: Source: National Statistics Office. Historical data from 2010 revised in February 2024 Latest actual data: 2024 Notes: Data prior to 1996 cannot be confirmed by national sources. Data prior to 2010 are based on staff estimates. National accounts manual used: System of National Accounts (SNA) 2008 GDP valuation: Market prices Reporting in calendar year: Yes Start/end months of reporting year: January/December Base year: 2019 Chain-weighted: Yes, from 1996 Primary domestic currency: Georgian lari Data last updated: 04/09/2025 | D7: See notes for: Gross domestic product, constant prices (National currency).
B8: 2000 | C8: 6.3652115e+09
B9: 2001 | C9: 6.6712062e+09 | D9: =IF(OR(C8="",C9=""),"",(C9/C8-1)*100)
B10: 2002 | C10: 7.0363897e+09 | D10: =IF(OR(C9="",C10=""),"",(C10/C9-1)*100)
B11: 2003 | C11: 7.8144055e+09 | D11: =IF(OR(C10="",C11=""),"",(C11/C10-1)*100)
B12: 2004 | C12: 8.2670693e+09 | D12: =IF(OR(C11="",C12=""),"",(C12/C11-1)*100)
B13: 2005 | C13: 9.0599753e+09 | D13: =IF(OR(C12="",C13=""),"",(C13/C12-1)*100)
B14: 2006 | C14: 9.9135592e+09 | D14: =IF(OR(C13="",C14=""),"",(C14/C13-1)*100)
B15: 2007 | C15: 1.1160246e+10 | D15: =IF(OR(C14="",C15=""),"",(C15/C14-1)*100)
B16: 2008 | C16: 1.1430504e+10 | D16: =IF(OR(C15="",C16=""),"",(C16/C15-1)*100)
B17: 2009 | C17: 1.1013204e+10 | D17: =IF(OR(C16="",C17=""),"",(C17/C16-1)*100)
B18: 2010 | C18: 1.1701134e+10 | D18: =IF(OR(C17="",C18=""),"",(C18/C17-1)*100)
B19: 2011 | C19: 1.2629542e+10 | D19: =IF(OR(C18="",C19=""),"",(C19/C18-1)*100)
B20: 2012 | C20: 1.3460418e+10 | D20: =IF(OR(C19="",C20=""),"",(C20/C19-1)*100)
... B33: 2025 | C33: 2.7066204e+10 | D33: =IF(OR(C32="",C33=""),"",(C33/C32-1)*100)
B34: 2026 | C34: =C33*(1+D34/100) | D34: =$D$33
B35: 2027 | C35: =C34*(1+D35/100) | D35: =$D$33
B36: 2028 | C36: =C35*(1+D36/100) | D36: =$D$35
B37: 2029 | C37: =C36*(1+D37/100) | D37: =$D$35
B38: 2030 | C38: =C37*(1+D38/100) | D38: =$D$35
B39: 2031 | C39: =C38*(1+D39/100) | D39: =$D$35
B40: 2032 | C40: =C39*(1+D40/100) | D40: =$D$35
B41: 2033 | C41: =C40*(1+D41/100) | D41: =$D$35
B42: 2034 | C42: =C41*(1+D42/100) | D42: =$D$35
B43: 2035 | C43: =C42*(1+D43/100) | D43: =$D$35
B44: 2036 | C44: =C43*(1+D44/100) | D44: =$D$35
B45: 2037 | C45: =C44*(1+D45/100) | D45: =$D$35
B46: 2038 | C46: =C45*(1+D46/100) | D46: =$D$35
B47: 2039 | C47: =C46*(1+D47/100) | D47: =$D$35
... B51: 2043 | C51: =C50*(1+D51/100) | D51: =$D$35
B16385: WEO Country Code | C16385: 915 | D16385: 915
B16386: WEO Subject Code | C16386: NGDP_R | D16386: NGDP_RPCH
B16387: Country | C16387: Georgia | D16387: Georgia
B16388: Subject Descriptor | C16388: Gross domestic product, constant prices | D16388: Gross domestic product, constant prices
B16389: Units | C16389: National currency | D16389: Percent change
B16390: Scale | C16390: Billions | D16390: Units
B16391: Country/Series-specific Notes | C16391: Source: National Statistics Office. Historical data from 2010 revised in February 2024 Latest actual data: 2024 Notes: Data prior to 1996 cannot be confirmed by national sources. Data prior to 2010 are based on staff estimates. National accounts manual used: System of National Accounts (SNA) 2008 GDP valuation: Market prices Reporting in calendar year: Yes Start/end months of reporting year: January/December Base year: 2019 Chain-weighted: Yes, from 1996 Primary domestic currency: Georgian lari Data last updated: 04/09/2025 | D16391: See notes for: Gross domestic product, constant prices (National currency).
B16392: 2000 | C16392: 16.963 | D16392: 1.865
B16393: 2001 | C16393: 17.772 | D16393: 4.769
B16394: 2002 | C16394: 18.747 | D16394: 5.487
B16395: 2003 | C16395: 20.852 | D16395: 11.228
B16396: 2004 | C16396: 22.061 | D16396: 5.796
B16397: 2005 | C16397: 24.176 | D16397: 9.588
B16398: 2006 | C16398: 26.454 | D16398: 9.42
B16399: 2007 | C16399: 29.781 | D16399: 12.579
B16400: 2008 | C16400: 30.502 | D16400: 2.419
B16401: 2009 | C16401: 29.388 | D16401: -3.651
B16402: 2010 | C16402: 31.428 | D16402: 6.942
B16403: 2011 | C16403: 33.927 | D16403: 7.949
... B16419: 2027 | C16419: 78.873 | D16419: 5
B16420: Estimates Start After | C16420: 2024 | D16420: 2024
B32769: WEO Country Code | C32769: 915 | D32769: 915
B32770: WEO Subject Code | C32770: NGDP_R | D32770: NGDP_RPCH
B32771: Country | C32771: Georgia | D32771: Georgia
B32772: Subject Descriptor | C32772: Gross domestic product, constant prices | D32772: Gross domestic product, constant prices
B32773: Units | C32773: National currency | D32773: Percent change
B32774: Scale | C32774: Billions | D32774: Units
B32775: Country/Series-specific Notes | C32775: Source: National Statistics Office. Historical data from 2010 revised in February 2024 Latest actual data: 2024 Notes: Data prior to 1996 cannot be confirmed by national sources. Data prior to 2010 are based on staff estimates. National accounts manual used: System of National Accounts (SNA) 2008 GDP valuation: Market prices Reporting in calendar year: Yes Start/end months of reporting year: January/December Base year: 2019 Chain-weighted: Yes, from 1996 Primary domestic currency: Georgian lari Data last updated: 04/09/2025 | D32775: See notes for: Gross domestic product, constant prices (National currency).
B32776: 2000 | C32776: 16.963 | D32776: 1.865
B32777: 2001 | C32777: 17.772 | D32777: 4.769
B32778: 2002 | C32778: 18.747 | D32778: 5.487
B32779: 2003 | C32779: 20.852 | D32779: 11.228
B32780: 2004 | C32780: 22.061 | D32780: 5.796
B32781: 2005 | C32781: 24.176 | D32781: 9.588
B32782: 2006 | C32782: 26.454 | D32782: 9.42
B32783: 2007 | C32783: 29.781 | D32783: 12.579
B32784: 2008 | C32784: 30.502 | D32784: 2.419
B32785: 2009 | C32785: 29.388 | D32785: -3.651
B32786: 2010 | C32786: 31.428 | D32786: 6.942
B32787: 2011 | C32787: 33.927 | D32787: 7.949
... B32803: 2027 | C32803: 78.873 | D32803: 5
B32804: Estimates Start After | C32804: 2024 | D32804: 2024
B49153: WEO Country Code | C49153: 915 | D49153: 915
B49154: WEO Subject Code | C49154: NGDP_R | D49154: NGDP_RPCH
B49155: Country | C49155: Georgia | D49155: Georgia
B49156: Subject Descriptor | C49156: Gross domestic product, constant prices | D49156: Gross domestic product, constant prices
B49157: Units | C49157: National currency | D49157: Percent change
B49158: Scale | C49158: Billions | D49158: Units
B49159: Country/Series-specific Notes | C49159: Source: National Statistics Office. Historical data from 2010 revised in February 2024 Latest actual data: 2024 Notes: Data prior to 1996 cannot be confirmed by national sources. Data prior to 2010 are based on staff estimates. National accounts manual used: System of National Accounts (SNA) 2008 GDP valuation: Market prices Reporting in calendar year: Yes Start/end months of reporting year: January/December Base year: 2019 Chain-weighted: Yes, from 1996 Primary domestic currency: Georgian lari Data last updated: 04/09/2025 | D49159: See notes for: Gross domestic product, constant prices (National currency).
B49160: 2000 | C49160: 16.963 | D49160: 1.865
B49161: 2001 | C49161: 17.772 | D49161: 4.769
B49162: 2002 | C49162: 18.747 | D49162: 5.487
B49163: 2003 | C49163: 20.852 | D49163: 11.228
B49164: 2004 | C49164: 22.061 | D49164: 5.796
B49165: 2005 | C49165: 24.176 | D49165: 9.588
B49166: 2006 | C49166: 26.454 | D49166: 9.42
B49167: 2007 | C49167: 29.781 | D49167: 12.579
B49168: 2008 | C49168: 30.502 | D49168: 2.419
B49169: 2009 | C49169: 29.388 | D49169: -3.651
B49170: 2010 | C49170: 31.428 | D49170: 6.942
B49171: 2011 | C49171: 33.927 | D49171: 7.949
... B49187: 2027 | C49187: 78.873 | D49187: 5
B49188: Estimates Start After | C49188: 2024 | D49188: 2024
B65537: WEO Country Code | C65537: 915 | D65537: 915
...
