Workbook

Sheet Production
A1: Assumption
A2: capital's share | B2: 0.35
A3: annual depreciation rate
K4: HP Filter
D5: K | E5: Real GDP | F5: LnK | G5: LnY | K5: LnZ | L5: LnZ_HP | M5: Second-order difference | N5: LnA-Trend(Check) | O5: objective
C6: 2002
C7: 2003
C8: 2004
C9: 2005
C10: 2006
C11: 2007
C12: 2008
C13: 2009
C14: 2010
C15: 2011
C16: 2012
C17: 2013
... C27: 2023
D35: K/Y | E35: K | F35: Y | G35: LnZ trend | H35: Ystar_base | I35: Investment | J35: ΔK | K35: K_With | L35: Ystar_with | M35: Uplift | N35: Projected GDP | O35: Projected GDP Growth | P35: Baseline GDP Growth
C36: 2002
C37: 2003
C38: 2004
C39: 2005
C40: 2006
C41: 2007
C42: 2008
C43: 2009
C44: 2010
C45: 2011
C46: 2012
C47: 2013
... C75: 2041

Sheet Investment
B1: Year | C1: Project Investment (Deflated)
B2: 2026 | C2: 648.58931
B3: 2027 | C3: 1220.0802
B4: 2028 | C4: 1756.1737
B5: 2029 | C5: 2221.1947
B6: 2030 | C6: 2122.4679
B7: 2031 | C7: 1524.5246
B8: 2032 | C8: 738.17631
B9: 2033 | C9: 352.60598

Sheet CFC data
A1: DATE | B1: TIME PERIOD | C1: Consumption of fixed capital (IDCM.A.N.GE.W2.S1.S1.D.P51C.N1G._T._Z.XDC.V.N) | D1: Capital Stock | E1: Depreciation rate
A2: 35430 | B2: 1996 | C2: 3.0451509e+08 | D2: ='PWT'!B8 | E2: =C2/D2
A3: 35795 | B3: 1997 | C3: 3.8364166e+08 | D3: ='PWT'!B9 | E3: =C3/D3
A4: 36160 | B4: 1998 | C4: 5.1639712e+08 | D4: ='PWT'!B10 | E4: =C4/D4
A5: 36525 | B5: 1999 | C5: 6.6160383e+08 | D5: ='PWT'!B11 | E5: =C5/D5
A6: 36891 | B6: 2000 | C6: 6.31701e+08 | D6: ='PWT'!B12 | E6: =C6/D6
A7: 37256 | B7: 2001 | C7: 7.0698373e+08 | D7: ='PWT'!B13 | E7: =C7/D7
A8: 37621 | B8: 2002 | C8: 7.9011257e+08 | D8: ='PWT'!B14 | E8: =C8/D8
A9: 37986 | B9: 2003 | C9: 9.3291622e+08 | D9: ='PWT'!B15 | E9: =C9/D9
A10: 38352 | B10: 2004 | C10: 9.7681854e+08 | D10: ='PWT'!B16 | E10: =C10/D10
A11: 38717 | B11: 2005 | C11: 1.1134501e+09 | D11: ='PWT'!B17 | E11: =C11/D11
A12: 39082 | B12: 2006 | C12: 1.3063731e+09 | D12: ='PWT'!B18 | E12: =C12/D12
A13: 39447 | B13: 2007 | C13: 1.61703e+09 | D13: ='PWT'!B19 | E13: =C13/D13
... A29: 45291 | B29: 2023 | C29: 9.4106578e+09 | D29: ='PWT'!B35 | E29: =C29/D29

Sheet PWT
A1: year | B1: rnna
A2: 1990 | B2: 217572.27
A3: 1991 | B3: 219328.42
A4: 1992 | B4: 215882.45
A5: 1993 | B5: 207684.89
A6: 1994 | B6: 202188.81
A7: 1995 | B7: 198953.86
A8: 1996 | B8: 196366.45
A9: 1997 | B9: 194417.84
A10: 1998 | B10: 194516.3
A11: 1999 | B11: 194964.56
A12: 2000 | B12: 195327.08
A13: 2001 | B13: 196512.45
... A31: 2019 | B31: 264125.56
A32: 2020
A33: 2021
A34: 2022
A35: 2023

Sheet WEO_Data
B1: WEO Country Code | C1: 915 | D1: 915
B2: WEO Subject Code | C2: NGDP_R | D2: NGDP_RPCH
B3: Country | C3: Georgia | D3: Georgia
B4: Subject Descriptor | C4: Gross domestic product, constant prices | D4: Gross domestic product, constant prices
B5: Units | C5: National currency | D5: Percent change
B6: Scale | C6: Billions | D6: Units
B7: Country/Series-specific Notes | C7: Source: National Statistics Office. Historical data from 2010 revised in February 2024 Latest actual data: 2024 Notes: Data prior to 1996 cannot be confirmed by national sources. Data prior to 2010 are based on staff estimates. National accounts manual used: System of National Accounts (SNA) 2008 GDP valuation: Market prices Reporting in calendar year: Yes Start/end months of reporting year: January/December Base year: 2019 Chain-weighted: Yes, from 1996 Primary domestic currency: Georgian lari Data last updated: 04/09/2025 | D7: See notes for: Gross domestic product, constant prices (National currency).
B8: 2000 | C8: 22802.836 | D8: 1.9
B9: 2001 | C9: =C8*(1+D9/100) | D9: 4.8
B10: 2002 | C10: =C9*(1+D10/100) | D10: 5.5
B11: 2003 | C11: =C10*(1+D11/100) | D11: 11.2
B12: 2004 | C12: =C11*(1+D12/100) | D12: 5.8
B13: 2005 | C13: =C12*(1+D13/100) | D13: 9.6
B14: 2006 | C14: =C13*(1+D14/100) | D14: 9.4
B15: 2007 | C15: =C14*(1+D15/100) | D15: 12.6
B16: 2008 | C16: =C15*(1+D16/100) | D16: 2.4
B17: 2009 | C17: =C16*(1+D17/100) | D17: -3.7
B18: 2010 | C18: =C17*(1+D18/100) | D18: 6.9
B19: 2011 | C19: =C18*(1+D19/100) | D19: 7.9
B20: 2012 | C20: =C19*(1+D20/100) | D20: 6.6
... B51: 2043 | C51: =C50*(1+D51/100) | D51: 5
B16385: WEO Country Code | C16385: 915 | D16385: 915
B16386: WEO Subject Code | C16386: NGDP_R | D16386: NGDP_RPCH
B16387: Country | C16387: Georgia | D16387: Georgia
B16388: Subject Descriptor | C16388: Gross domestic product, constant prices | D16388: Gross domestic product, constant prices
B16389: Units | C16389: National currency | D16389: Percent change
B16390: Scale | C16390: Billions | D16390: Units
B16391: Country/Series-specific Notes | C16391: Source: National Statistics Office. Historical data from 2010 revised in February 2024 Latest actual data: 2024 Notes: Data prior to 1996 cannot be confirmed by national sources. Data prior to 2010 are based on staff estimates. National accounts manual used: System of National Accounts (SNA) 2008 GDP valuation: Market prices Reporting in calendar year: Yes Start/end months of reporting year: January/December Base year: 2019 Chain-weighted: Yes, from 1996 Primary domestic currency: Georgian lari Data last updated: 04/09/2025 | D16391: See notes for: Gross domestic product, constant prices (National currency).
B16392: 2000 | C16392: 16.963 | D16392: 1.865
B16393: 2001 | C16393: 17.772 | D16393: 4.769
B16394: 2002 | C16394: 18.747 | D16394: 5.487
B16395: 2003 | C16395: 20.852 | D16395: 11.228
B16396: 2004 | C16396: 22.061 | D16396: 5.796
B16397: 2005 | C16397: 24.176 | D16397: 9.588
B16398: 2006 | C16398: 26.454 | D16398: 9.42
B16399: 2007 | C16399: 29.781 | D16399: 12.579
B16400: 2008 | C16400: 30.502 | D16400: 2.419
B16401: 2009 | C16401: 29.388 | D16401: -3.651
B16402: 2010 | C16402: 31.428 | D16402: 6.942
B16403: 2011 | C16403: 33.927 | D16403: 7.949
... B16419: 2027 | C16419: 78.873 | D16419: 5
B16420: Estimates Start After | C16420: 2024 | D16420: 2024
B32769: WEO Country Code | C32769: 915 | D32769: 915
B32770: WEO Subject Code | C32770: NGDP_R | D32770: NGDP_RPCH
B32771: Country | C32771: Georgia | D32771: Georgia
B32772: Subject Descriptor | C32772: Gross domestic product, constant prices | D32772: Gross domestic product, constant prices
B32773: Units | C32773: National currency | D32773: Percent change
B32774: Scale | C32774: Billions | D32774: Units
B32775: Country/Series-specific Notes | C32775: Source: National Statistics Office. Historical data from 2010 revised in February 2024 Latest actual data: 2024 Notes: Data prior to 1996 cannot be confirmed by national sources. Data prior to 2010 are based on staff estimates. National accounts manual used: System of National Accounts (SNA) 2008 GDP valuation: Market prices Reporting in calendar year: Yes Start/end months of reporting year: January/December Base year: 2019 Chain-weighted: Yes, from 1996 Primary domestic currency: Georgian lari Data last updated: 04/09/2025 | D32775: See notes for: Gross domestic product, constant prices (National currency).
B32776: 2000 | C32776: 16.963 | D32776: 1.865
B32777: 2001 | C32777: 17.772 | D32777: 4.769
B32778: 2002 | C32778: 18.747 | D32778: 5.487
B32779: 2003 | C32779: 20.852 | D32779: 11.228
B32780: 2004 | C32780: 22.061 | D32780: 5.796
B32781: 2005 | C32781: 24.176 | D32781: 9.588
B32782: 2006 | C32782: 26.454 | D32782: 9.42
B32783: 2007 | C32783: 29.781 | D32783: 12.579
B32784: 2008 | C32784: 30.502 | D32784: 2.419
B32785: 2009 | C32785: 29.388 | D32785: -3.651
B32786: 2010 | C32786: 31.428 | D32786: 6.942
B32787: 2011 | C32787: 33.927 | D32787: 7.949
... B32803: 2027 | C32803: 78.873 | D32803: 5
B32804: Estimates Start After | C32804: 2024 | D32804: 2024
B49153: WEO Country Code | C49153: 915 | D49153: 915
B49154: WEO Subject Code | C49154: NGDP_R | D49154: NGDP_RPCH
B49155: Country | C49155: Georgia | D49155: Georgia
B49156: Subject Descriptor | C49156: Gross domestic product, constant prices | D49156: Gross domestic product, constant prices
B49157: Units | C49157: National currency | D49157: Percent change
B49158: Scale | C49158: Billions | D49158: Units
B49159: Country/Series-specific Notes | C49159: Source: National Statistics Office. Historical data from 2010 revised in February 2024 Latest actual data: 2024 Notes: Data prior to 1996 cannot be confirmed by national sources. Data prior to 2010 are based on staff estimates. National accounts manual used: System of National Accounts (SNA) 2008 GDP valuation: Market prices Reporting in calendar year: Yes Start/end months of reporting year: January/December Base year: 2019 Chain-weighted: Yes, from 1996 Primary domestic currency: Georgian lari Data last updated: 04/09/2025 | D49159: See notes for: Gross domestic product, constant prices (National currency).
B49160: 2000 | C49160: 16.963 | D49160: 1.865
B49161: 2001 | C49161: 17.772 | D49161: 4.769
B49162: 2002 | C49162: 18.747 | D49162: 5.487
B49163: 2003 | C49163: 20.852 | D49163: 11.228
B49164: 2004 | C49164: 22.061 | D49164: 5.796
B49165: 2005 | C49165: 24.176 | D49165: 9.588
B49166: 2006 | C49166: 26.454 | D49166: 9.42
B49167: 2007 | C49167: 29.781 | D49167: 12.579
B49168: 2008 | C49168: 30.502 | D49168: 2.419
B49169: 2009 | C49169: 29.388 | D49169: -3.651
B49170: 2010 | C49170: 31.428 | D49170: 6.942
B49171: 2011 | C49171: 33.927 | D49171: 7.949
... B49187: 2027 | C49187: 78.873 | D49187: 5
B49188: Estimates Start After | C49188: 2024 | D49188: 2024
B65537: WEO Country Code | C65537: 915 | D65537: 915
B65538: WEO Subject Code | C65538: NGDP_R | D65538: NGDP_RPCH
B65539: Country | C65539: Georgia | D65539: Georgia
B65540: Subject Descriptor | C65540: Gross domestic product, constant prices | D65540: Gross domestic product, constant prices
B65541: Units | C65541: National currency | D65541: Percent change
B65542: Scale | C65542: Billions | D65542: Units
B65543: Country/Series-specific Notes | C65543: Source: National Statistics Office. Historical data from 2010 revised in February 2024 Latest actual data: 2024 Notes: Data prior to 1996 cannot be confirmed by national sources. Data prior to 2010 are based on staff estimates. National accounts manual used: System of National Accounts (SNA) 2008 GDP valuation: Market prices Reporting in calendar year: Yes Start/end months of reporting year: January/December Base year: 2019 Chain-weighted: Yes, from 1996 Primary domestic currency: Georgian lari Data last updated: 04/09/2025 | D65543: See notes for: Gross domestic product, constant prices (National currency).
B65544: 2000 | C65544: 16.963 | D65544: 1.865
B65545: 2001 | C65545: 17.772 | D65545: 4.769
B65546: 2002 | C65546: 18.747 | D65546: 5.487
B65547: 2003 | C65547: 20.852 | D65547: 11.228
B65548: 2004 | C65548: 22.061 | D65548: 5.796
B65549: 2005 | C65549: 24.176 | D65549: 9.588
B65550: 2006 | C65550: 26.454 | D65550: 9.42
B65551: 2007 | C65551: 29.781 | D65551: 12.579
B65552: 2008 | C65552: 30.502 | D65552: 2.419
...
