Workbook

Sheet Production
A1: Assumption
A2: capital's share | B2: 0.35
A3: annual depreciation rate | B3: =AVERAGE('CFC data'!E22:E29) -> 20106.501 | O3: lambda | P3: 100
K4: HP Filter | O4: Objective total
D5: K | E5: Real GDP | F5: LnK | G5: LnY | K5: LnZ | L5: LnZ_HP | M5: Second-order difference | N5: LnA-Trend(Check) | O5: per-row (LnZ-LnZ_HP)^2 | P5: =SUM(O6:O27)+$P$3*SUMSQ(M7:M26) -> 6.8867344
C6: 2002 | D6: ='CFC data'!D8 -> 240523.05 | E6: =WEO_Data!C10 -> 18.747 | F6: =IFERROR(LN(D6),"") -> 12.390571 | G6: =IFERROR(LN(E6),"") -> 2.9310337 | K6: =IFERROR(G6-$B$2*F6,"") -> -1.4056662 | L6: =K6 -> -1.4056662 | N6: =IFERROR(K6-L6,"") -> 0 | O6: =IFERROR(N6^2,"") -> 0
C7: 2003 | D7: ='CFC data'!D9 -> 242715.27 | E7: =WEO_Data!C11 -> 20.852 | F7: =IFERROR(LN(D7),"") -> 12.399644 | G7: =IFERROR(LN(E7),"") -> 3.0374499 | K7: =IFERROR(G7-$B$2*F7,"") -> -1.3024256 | L7: =K7 -> -1.3024256 | M7: =IFERROR(L6-2*L7+L8,"") -> -0.05098608 | N7: =IFERROR(K7-L7,"") -> 0 | O7: =IFERROR(N7^2,"") -> 0
C8: 2004 | D8: ='CFC data'!D10 -> 245580.14 | E8: =WEO_Data!C12 -> 22.061 | F8: =IFERROR(LN(D8),"") -> 12.411379 | G8: =IFERROR(LN(E8),"") -> 3.0938113 | K8: =IFERROR(G8-$B$2*F8,"") -> -1.2501712 | L8: =K8 -> -1.2501712 | M8: =IFERROR(L7-2*L8+L9,"") -> 0.034104447 | N8: =IFERROR(K8-L8,"") -> 0 | O8: =IFERROR(N8^2,"") -> 0
C9: 2005 | D9: ='CFC data'!D11 -> 249248.98 | E9: =WEO_Data!C13 -> 24.176 | F9: =IFERROR(LN(D9),"") -> 12.426208 | G9: =IFERROR(LN(E9),"") -> 3.1853604 | K9: =IFERROR(G9-$B$2*F9,"") -> -1.1638123 | L9: =K9 -> -1.1638123 | M9: =IFERROR(L8-2*L9+L10,"") -> -0.00056617031 | N9: =IFERROR(K9-L9,"") -> 0 | O9: =IFERROR(N9^2,"") -> 0
C10: 2006 | D10: ='CFC data'!D12 -> 252297.08 | E10: =WEO_Data!C14 -> 26.454 | F10: =IFERROR(LN(D10),"") -> 12.438363 | G10: =IFERROR(LN(E10),"") -> 3.2754074 | K10: =IFERROR(G10-$B$2*F10,"") -> -1.0780195 | L10: =K10 -> -1.0780195 | M10: =IFERROR(L9-2*L10+L11,"") -> 0.027251005 | N10: =IFERROR(K10-L10,"") -> 0 | O10: =IFERROR(N10^2,"") -> 0
C11: 2007 | D11: ='CFC data'!D13 -> 256234.11 | E11: =WEO_Data!C15 -> 29.781 | F11: =IFERROR(LN(D11),"") -> 12.453847 | G11: =IFERROR(LN(E11),"") -> 3.3938706 | K11: =IFERROR(G11-$B$2*F11,"") -> -0.96497577 | L11: =K11 -> -0.96497577 | M11: =IFERROR(L10-2*L11+L12,"") -> -0.091139674 | N11: =IFERROR(K11-L11,"") -> 0 | O11: =IFERROR(N11^2,"") -> 0
C12: 2008 | D12: ='CFC data'!D14 -> 257715.44 | E12: =WEO_Data!C16 -> 30.502 | F12: =IFERROR(LN(D12),"") -> 12.459611 | G12: =IFERROR(LN(E12),"") -> 3.4177923 | K12: =IFERROR(G12-$B$2*F12,"") -> -0.9430717 | L12: =K12 -> -0.9430717 | M12: =IFERROR(L11-2*L12+L13,"") -> -0.056219725 | N12: =IFERROR(K12-L12,"") -> 0 | O12: =IFERROR(N12^2,"") -> 0
C13: 2009 | D13: ='CFC data'!D15 -> 255596.08 | E13: =WEO_Data!C17 -> 29.388 | F13: =IFERROR(LN(D13),"") -> 12.451354 | G13: =IFERROR(LN(E13),"") -> 3.3805864 | K13: =IFERROR(G13-$B$2*F13,"") -> -0.97738735 | L13: =K13 -> -0.97738735 | M13: =IFERROR(L12-2*L13+L14,"") -> 0.10062274 | N13: =IFERROR(K13-L13,"") -> 0 | O13: =IFERROR(N13^2,"") -> 0
C14: 2010 | D14: ='CFC data'!D16 -> 256185.14 | E14: =WEO_Data!C18 -> 31.428 | F14: =IFERROR(LN(D14),"") -> 12.453656 | G14: =IFERROR(LN(E14),"") -> 3.4476992 | K14: =IFERROR(G14-$B$2*F14,"") -> -0.91108027 | L14: =K14 -> -0.91108027 | M14: =IFERROR(L13-2*L14+L15,"") -> 0.0074664427 | N14: =IFERROR(K14-L14,"") -> 0 | O14: =IFERROR(N14^2,"") -> 0
C15: 2011 | D15: ='CFC data'!D17 -> 258197.41 | E15: =WEO_Data!C19 -> 33.927 | F15: =IFERROR(LN(D15),"") -> 12.46148 | G15: =IFERROR(LN(E15),"") -> 3.5242112 | K15: =IFERROR(G15-$B$2*F15,"") -> -0.83730674 | L15: =K15 -> -0.83730674 | M15: =IFERROR(L14-2*L15+L16,"") -> -0.013532815 | N15: =IFERROR(K15-L15,"") -> 0 | O15: =IFERROR(N15^2,"") -> 0
C16: 2012 | D16: ='CFC data'!D18 -> 260772.97 | E16: =WEO_Data!C20 -> 36.159 | F16: =IFERROR(LN(D16),"") -> 12.471405 | G16: =IFERROR(LN(E16),"") -> 3.5879259 | K16: =IFERROR(G16-$B$2*F16,"") -> -0.77706603 | L16: =K16 -> -0.77706603 | M16: =IFERROR(L15-2*L16+L17,"") -> -0.011752781 | N16: =IFERROR(K16-L16,"") -> 0 | O16: =IFERROR(N16^2,"") -> 0
C17: 2013 | D17: ='CFC data'!D19 -> 261943.11 | E17: =WEO_Data!C21 -> 38.015 | F17: =IFERROR(LN(D17),"") -> 12.475883 | G17: =IFERROR(LN(E17),"") -> 3.6379808 | K17: =IFERROR(G17-$B$2*F17,"") -> -0.7285781 | L17: =K17 -> -0.7285781 | M17: =IFERROR(L16-2*L17+L18,"") -> -0.013537613 | N17: =IFERROR(K17-L17,"") -> 0 | O17: =IFERROR(N17^2,"") -> 0
C18: 2014 | D18: ='CFC data'!D20 -> 265818.41 | E18: =WEO_Data!C22 -> 39.57 | F18: =IFERROR(LN(D18),"") -> 12.490569 | G18: =IFERROR(LN(E18),"") -> 3.6780713 | K18: =IFERROR(G18-$B$2*F18,"") -> -0.69362778 | L18: =K18 -> -0.69362778 | M18: =IFERROR(L17-2*L18+L19,"") -> -0.0092952826 | N18: =IFERROR(K18-L18,"") -> 0 | O18: =IFERROR(N18^2,"") -> 0
... C26: 2022 | D26: ='CFC data'!D28 -> 319518.71 | E26: =WEO_Data!C30 -> 57.208 | F26: =IFERROR(LN(D26),"") -> 12.674571 | G26: =IFERROR(LN(E26),"") -> 4.0466937 | K26: =IFERROR(G26-$B$2*F26,"") -> -0.38940614 | L26: =K26 -> -0.38940614 | M26: =IFERROR(L25-2*L26+L27,"") -> -0.028574477 | N26: =IFERROR(K26-L26,"") -> 0 | O26: =IFERROR(N26^2,"") -> 0
C27: 2023 | D27: ='CFC data'!D29 -> 326952.9 | E27: =WEO_Data!C31 -> 61.689 | F27: =IFERROR(LN(D27),"") -> 12.697571 | G27: =IFERROR(LN(E27),"") -> 4.1221056 | K27: =IFERROR(G27-$B$2*F27,"") -> -0.32204436 | L27: =K27 -> -0.32204436 | N27: =IFERROR(K27-L27,"") -> 0 | O27: =IFERROR(N27^2,"") -> 0
D35: K/Y | E35: K | F35: Y | G35: LnZ trend | H35: Ystar_base | I35: Investment | J35: ΔK | K35: K_With | L35: Ystar_with | M35: Uplift | N35: Projected GDP | O35: Projected GDP Growth | P35: Baseline GDP Growth
C36: 2002 | D36: =IFERROR(E36/F36,"") -> 12829.949 | E36: ='CFC data'!D8 -> 240523.05 | F36: =WEO_Data!C10 -> 18.747 | G36: =L6 -> -1.4056662 | H36: =EXP(G36+$B$2*LN(E36)) -> 18.747 | I36: 0 | J36: 0 | K36: =E36+J36 -> 240523.05 | L36: =EXP(G36+$B$2*LN(K36)) -> 18.747 | M36: =L36/H36-1 -> 0 | N36: =F36*(1+M36) -> 18.747
C37: 2003 | D37: =IFERROR(E37/F37,"") -> 11639.903 | E37: ='CFC data'!D9 -> 242715.27 | F37: =WEO_Data!C11 -> 20.852 | G37: =L7 -> -1.3024256 | H37: =EXP(G37+$B$2*LN(E37)) -> 20.852 | I37: 0 | J37: 0 | K37: =E37+J37 -> 242715.27 | L37: =EXP(G37+$B$2*LN(K37)) -> 20.852 | M37: =L37/H37-1 -> 0 | N37: =F37*(1+M37) -> 20.852 | O37: =IFERROR(N37/N36-1,"") -> 0.11228463 | P37: =IFERROR(F37/F36-1,"") -> 0.11228463
C38: 2004 | D38: =IFERROR(E38/F38,"") -> 11131.868 | E38: ='CFC data'!D10 -> 245580.14 | F38: =WEO_Data!C12 -> 22.061 | G38: =L8 -> -1.2501712 | H38: =EXP(G38+$B$2*LN(E38)) -> 22.061 | I38: 0 | J38: 0 | K38: =E38+J38 -> 245580.14 | L38: =EXP(G38+$B$2*LN(K38)) -> 22.061 | M38: =L38/H38-1 -> 0 | N38: =F38*(1+M38) -> 22.061 | O38: =IFERROR(N38/N37-1,"") -> 0.05798005 | P38: =IFERROR(F38/F37-1,"") -> 0.05798005
C39: 2005 | D39: =IFERROR(E39/F39,"") -> 10309.769 | E39: ='CFC data'!D11 -> 249248.98 | F39: =WEO_Data!C13 -> 24.176 | G39: =L9 -> -1.1638123 | H39: =EXP(G39+$B$2*LN(E39)) -> 24.176 | I39: 0 | J39: 0 | K39: =E39+J39 -> 249248.98 | L39: =EXP(G39+$B$2*LN(K39)) -> 24.176 | M39: =L39/H39-1 -> 0 | N39: =F39*(1+M39) -> 24.176 | O39: =IFERROR(N39/N38-1,"") -> 0.095870541 | P39: =IFERROR(F39/F38-1,"") -> 0.095870541
C40: 2006 | D40: =IFERROR(E40/F40,"") -> 9537.1996 | E40: ='CFC data'!D12 -> 252297.08 | F40: =WEO_Data!C14 -> 26.454 | G40: =L10 -> -1.0780195 | H40: =EXP(G40+$B$2*LN(E40)) -> 26.454 | I40: 0 | J40: 0 | K40: =E40+J40 -> 252297.08 | L40: =EXP(G40+$B$2*LN(K40)) -> 26.454 | M40: =L40/H40-1 -> 0 | N40: =F40*(1+M40) -> 26.454 | O40: =IFERROR(N40/N39-1,"") -> 0.094225678 | P40: =IFERROR(F40/F39-1,"") -> 0.094225678
C41: 2007 | D41: =IFERROR(E41/F41,"") -> 8603.9458 | E41: ='CFC data'!D13 -> 256234.11 | F41: =WEO_Data!C15 -> 29.781 | G41: =L11 -> -0.96497577 | H41: =EXP(G41+$B$2*LN(E41)) -> 29.781 | I41: 0 | J41: 0 | K41: =E41+J41 -> 256234.11 | L41: =EXP(G41+$B$2*LN(K41)) -> 29.781 | M41: =L41/H41-1 -> 0 | N41: =F41*(1+M41) -> 29.781 | O41: =IFERROR(N41/N40-1,"") -> 0.12576548 | P41: =IFERROR(F41/F40-1,"") -> 0.12576548
C42: 2008 | D42: =IFERROR(E42/F42,"") -> 8449.1324 | E42: ='CFC data'!D14 -> 257715.44 | F42: =WEO_Data!C16 -> 30.502 | G42: =L12 -> -0.9430717 | H42: =EXP(G42+$B$2*LN(E42)) -> 30.502 | I42: 0 | J42: 0 | K42: =E42+J42 -> 257715.44 | L42: =EXP(G42+$B$2*LN(K42)) -> 30.502 | M42: =L42/H42-1 -> 0 | N42: =F42*(1+M42) -> 30.502 | O42: =IFERROR(N42/N41-1,"") -> 0.024210067 | P42: =IFERROR(F42/F41-1,"") -> 0.024210067
C43: 2009 | D43: =IFERROR(E43/F43,"") -> 8697.2941 | E43: ='CFC data'!D15 -> 255596.08 | F43: =WEO_Data!C17 -> 29.388 | G43: =L13 -> -0.97738735 | H43: =EXP(G43+$B$2*LN(E43)) -> 29.388 | I43: 0 | J43: 0 | K43: =E43+J43 -> 255596.08 | L43: =EXP(G43+$B$2*LN(K43)) -> 29.388 | M43: =L43/H43-1 -> 0 | N43: =F43*(1+M43) -> 29.388 | O43: =IFERROR(N43/N42-1,"") -> -0.036522195 | P43: =IFERROR(F43/F42-1,"") -> -0.036522195
C44: 2010 | D44: =IFERROR(E44/F44,"") -> 8151.4936 | E44: ='CFC data'!D16 -> 256185.14 | F44: =WEO_Data!C18 -> 31.428 | G44: =L14 -> -0.91108027 | H44: =EXP(G44+$B$2*LN(E44)) -> 31.428 | I44: 0 | J44: 0 | K44: =E44+J44 -> 256185.14 | L44: =EXP(G44+$B$2*LN(K44)) -> 31.428 | M44: =L44/H44-1 -> 0 | N44: =F44*(1+M44) -> 31.428 | O44: =IFERROR(N44/N43-1,"") -> 0.069416088 | P44: =IFERROR(F44/F43-1,"") -> 0.069416088
C45: 2011 | D45: =IFERROR(E45/F45,"") -> 7610.3813 | E45: ='CFC data'!D17 -> 258197.41 | F45: =WEO_Data!C19 -> 33.927 | G45: =L15 -> -0.83730674 | H45: =EXP(G45+$B$2*LN(E45)) -> 33.927 | I45: 0 | J45: 0 | K45: =E45+J45 -> 258197.41 | L45: =EXP(G45+$B$2*LN(K45)) -> 33.927 | M45: =L45/H45-1 -> 0 | N45: =F45*(1+M45) -> 33.927 | O45: =IFERROR(N45/N44-1,"") -> 0.079515082 | P45: =IFERROR(F45/F44-1,"") -> 0.079515082
C46: 2012 | D46: =IFERROR(E46/F46,"") -> 7211.8413 | E46: ='CFC data'!D18 -> 260772.97 | F46: =WEO_Data!C20 -> 36.159 | G46: =L16 -> -0.77706603 | H46: =EXP(G46+$B$2*LN(E46)) -> 36.159 | I46: 0 | J46: 0 | K46: =E46+J46 -> 260772.97 | L46: =EXP(G46+$B$2*LN(K46)) -> 36.159 | M46: =L46/H46-1 -> 0 | N46: =F46*(1+M46) -> 36.159 | O46: =IFERROR(N46/N45-1,"") -> 0.06578831 | P46: =IFERROR(F46/F45-1,"") -> 0.06578831
C47: 2013 | D47: =IFERROR(E47/F47,"") -> 6890.5198 | E47: ='CFC data'!D19 -> 261943.11 | F47: =WEO_Data!C21 -> 38.015 | G47: =L17 -> -0.7285781 | H47: =EXP(G47+$B$2*LN(E47)) -> 38.015 | I47: 0 | J47: 0 | K47: =E47+J47 -> 261943.11 | L47: =EXP(G47+$B$2*LN(K47)) -> 38.015 | M47: =L47/H47-1 -> 0 | N47: =F47*(1+M47) -> 38.015 | O47: =IFERROR(N47/N46-1,"") -> 0.051328853 | P47: =IFERROR(F47/F46-1,"") -> 0.051328853
C48: 2014 | D48: =IFERROR(E48/F48,"") -> 6717.6752 | E48: ='CFC data'!D20 -> 265818.41 | F48: =WEO_Data!C22 -> 39.57 | G48: =L18 -> -0.69362778 | H48: =EXP(G48+$B$2*LN(E48)) -> 39.57 | I48: 0 | J48: 0 | K48: =E48+J48 -> 265818.41 | L48: =EXP(G48+$B$2*LN(K48)) -> 39.57 | M48: =L48/H48-1 -> 0 | N48: =F48*(1+M48) -> 39.57 | O48: =IFERROR(N48/N47-1,"") -> 0.040904906 | P48: =IFERROR(F48/F47-1,"") -> 0.040904906
... C57: 2023 | D57: =IFERROR(E57/F57,"") -> 5300.0195 | E57: ='CFC data'!D29 -> 326952.9 | F57: =WEO_Data!C31 -> 61.689 | G57: =L27 -> -0.32204436 | H57: =EXP(G57+$B$2*LN(E57)) -> 61.689 | I57: 0 | J57: 0 | K57: =E57+J57 -> 326952.9 | L57: =EXP(G57+$B$2*LN(K57)) -> 61.689 | M57: =L57/H57-1 -> 0 | N57: =F57*(1+M57) -> 61.689 | O57: =IFERROR(N57/N56-1,"") -> 0.078328206 | P57: =IFERROR(F57/F56-1,"") -> 0.078328206
C58: 2024 | D58: =IFERROR(E58/F58,"") -> 6133.1567 | E58: =(AVERAGE(D49:D57))*F58 -> 414018.74 | F58: =WEO_Data!C32 -> 67.505 | G58: =TREND($G$36:$G$57,$C$36:$C$57,C58) -> -0.28138368 | H58: =EXP(G58+$B$2*LN(E58)) -> 69.783641 | I58: 0 | J58: 0 | K58: =E58+J58 -> 414018.74 | L58: =EXP(G58+$B$2*LN(K58)) -> 69.783641 | M58: =L58/H58-1 -> 0 | N58: =F58*(1+M58) -> 67.505 | O58: =IFERROR(N58/N57-1,"") -> 0.094279369 | P58: =IFERROR(F58/F57-1,"") -> 0.094279369
C59: 2025 | D59: =IFERROR(E59/F59,"") -> 6133.1567 | E59: =(AVERAGE(D49:D57))*F59 -> 438766.03 | F59: =WEO_Data!C33 -> 71.54 | G59: =TREND($G$36:$G$57,$C$36:$C$57,C59) -> -0.23561288 | H59: =EXP(G59+$B$2*LN(E59)) -> 74.551463 | I59: 0 | J59: 0 | K59: =E59+J59 -> 438766.03 | L59: =EXP(G59+$B$2*LN(K59)) -> 74.551463 | M59: =L59/H59-1 -> 0 | N59: =F59*(1+M59) -> 71.54 | O59: =IFERROR(N59/N58-1,"") -> 0.05977335 | P59: =IFERROR(F59/F58-1,"") -> 0.05977335
C60: 2026 | D60: =IFERROR(E60/F60,"") -> 6133.1567 | E60: =(AVERAGE(D49:D57))*F60 -> 460704.33 | F60: =WEO_Data!C34 -> 75.117 | G60: =TREND($G$36:$G$57,$C$36:$C$57,C60) -> -0.18984209 | H60: =EXP(G60+$B$2*LN(E60)) -> 79.38719 | I60: =Investment!C2 -> 648.58931 | J60: =(1-$B$3)*J59+I60 -> 648.58931 | K60: =E60+J60 -> 461352.92 | L60: =EXP(G60+$B$2*LN(K60)) -> 79.426289 | M60: =L60/H60-1 -> 0.00049251214 | N60: =F60*(1+M60) -> 75.153996 | O60: =IFERROR(N60/N59-1,"") -> 0.050517138 | P60: =IFERROR(F60/F59-1,"") -> 0.05
C61: 2027 | D61: =IFERROR(E61/F61,"") -> 6133.1567 | E61: =(AVERAGE(D49:D57))*F61 -> 483740.47 | F61: =WEO_Data!C35 -> 78.873 | G61: =TREND($G$36:$G$57,$C$36:$C$57,C61) -> -0.1440713 | H61: =EXP(G61+$B$2*LN(E61)) -> 84.536639 | I61: =Investment!C3 -> 1220.0802 | J61: =(1-$B$3)*J60+I61 -> -13038993 | K61: =E61+J61 -> -12555252 | L61: =EXP(G61+$B$2*LN(K61)) -> #VALUE! | M61: =L61/H61-1 -> #VALUE! | N61: =F61*(1+M61) -> #VALUE! | O61: =IFERROR(N61/N60-1,"") | P61: =IFERROR(F61/F60-1,"") -> 0.050001997
C62: 2028 | D62: =IFERROR(E62/F62,"") -> 6133.1567 | E62: =(AVERAGE(D49:D57))*F62 -> 507927.49 | F62: =WEO_Data!C36 -> 82.81665 | G62: =TREND($G$36:$G$57,$C$36:$C$57,C62) -> -0.098300512 | H62: =EXP(G62+$B$2*LN(E62)) -> 90.020046 | I62: =Investment!C4 -> 1756.1737 | J62: =(1-$B$3)*J61+I62 -> 2.6215548e+11 | K62: =E62+J62 -> 2.6215599e+11 | L62: =EXP(G62+$B$2*LN(K62)) -> 8990.9287 | M62: =L62/H62-1 -> 98.876961 | N62: =F62*(1+M62) -> 8271.4754 | O62: =IFERROR(N62/N61-1,"") | P62: =IFERROR(F62/F61-1,"") -> 0.05
C63: 2029 | D63: =IFERROR(E63/F63,"") -> 6133.1567 | E63: =(AVERAGE(D49:D57))*F63 -> 533323.87 | F63: =WEO_Data!C37 -> 86.957482 | G63: =TREND($G$36:$G$57,$C$36:$C$57,C63) -> -0.052529721 | H63: =EXP(G63+$B$2*LN(E63)) -> 95.859131 | I63: =Investment!C5 -> 2221.1947 | J63: =(1-$B$3)*J62+I63 -> -5.2707672e+15 | K63: =E63+J63 -> -5.2707672e+15 | L63: =EXP(G63+$B$2*LN(K63)) -> #VALUE! | M63: =L63/H63-1 -> #VALUE! | N63: =F63*(1+M63) -> #VALUE! | O63: =IFERROR(N63/N62-1,"") | P63: =IFERROR(F63/F62-1,"") -> 0.05
C64: 2030 | D64: =IFERROR(E64/F64,"") -> 6133.1567 | E64: =(AVERAGE(D49:D57))*F64 -> 559990.06 | F64: =WEO_Data!C38 -> 91.305357 | G64: =TREND($G$36:$G$57,$C$36:$C$57,C64) -> -0.0067589303 | H64: =EXP(G64+$B$2*LN(E64)) -> 102.07696 | I64: =Investment!C6 -> 2122.4679 | J64: =(1-$B$3)*J63+I64 -> 1.0597141e+20 | K64: =E64+J64 -> 1.0597141e+20 | L64: =EXP(G64+$B$2*LN(K64)) -> 10136329 | M64: =L64/H64-1 -> 99299.844 | N64: =F64*(1+M64) -> 9066699 | O64: =IFERROR(N64/N63-1,"") | P64: =IFERROR(F64/F63-1,"") -> 0.05
C65: 2031 | D65: =IFERROR(E65/F65,"") -> 6133.1567 | E65: =(AVERAGE(D49:D57))*F65 -> 587989.56 | F65: =WEO_Data!C39 -> 95.870624 | G65: =TREND($G$36:$G$57,$C$36:$C$57,C65) -> 0.039011861 | H65: =EXP(G65+$B$2*LN(E65)) -> 108.69811 | I65: =Investment!C7 -> 1524.5246 | J65: =(1-$B$3)*J64+I65 -> -2.1306083e+24 | K65: =E65+J65 -> -2.1306083e+24 | L65: =EXP(G65+$B$2*LN(K65)) -> #VALUE! | M65: =L65/H65-1 -> #VALUE! | N65: =F65*(1+M65) -> #VALUE! | O65: =IFERROR(N65/N64-1,"") | P65: =IFERROR(F65/F64-1,"") -> 0.05
C66: 2032 | D66: =IFERROR(E66/F66,"") -> 6133.1567 | E66: =(AVERAGE(D49:D57))*F66 -> 617389.04 | F66: =WEO_Data!C40 -> 100.66416 | G66: =TREND($G$36:$G$57,$C$36:$C$57,C66) -> 0.084782651 | H66: =EXP(G66+$B$2*LN(E66)) -> 115.74874 | I66: =Investment!C8 -> 738.17631 | J66: =(1-$B$3)*J65+I66 -> 4.2836946e+28 | K66: =E66+J66 -> 4.2836946e+28 | L66: =EXP(G66+$B$2*LN(K66)) -> 1.1427655e+10 | M66: =L66/H66-1 -> 98728117 | N66: =F66*(1+M66) -> 9.9383826e+09 | O66: =IFERROR(N66/N65-1,"") | P66: =IFERROR(F66/F65-1,"") -> 0.05
C67: 2033 | D67: =IFERROR(E67/F67,"") -> 6133.1567 | E67: =(AVERAGE(D49:D57))*F67 -> 648258.49 | F67: =WEO_Data!C41 -> 105.69736 | G67: =TREND($G$36:$G$57,$C$36:$C$57,C67) -> 0.13055344 | H67: =EXP(G67+$B$2*LN(E67)) -> 123.25669 | I67: =Investment!C9 -> 352.60598 | J67: =(1-$B$3)*J66+I67 -> -8.6125825e+32 | K67: =E67+J67 -> -8.6125825e+32 | L67: =EXP(G67+$B$2*LN(K67)) -> #VALUE! | M67: =L67/H67-1 -> #VALUE! | N67: =F67*(1+M67) -> #VALUE! | O67: =IFERROR(N67/N66-1,"") | P67: =IFERROR(F67/F66-1,"") -> 0.05
C68: 2034 | D68: =IFERROR(E68/F68,"") -> 6133.1567 | E68: =(AVERAGE(D49:D57))*F68 -> 680671.42 | F68: =WEO_Data!C42 -> 110.98223 | G68: =TREND($G$36:$G$57,$C$36:$C$57,C68) -> 0.17632423 | H68: =EXP(G68+$B$2*LN(E68)) -> 131.25165 | I68: 0 | J68: =(1-$B$3)*J67+I68 -> 1.7316028e+37 | K68: =E68+J68 -> 1.7316028e+37 | L68: =EXP(G68+$B$2*LN(K68)) -> 1.2883491e+13 | M68: =L68/H68-1 -> 9.8158694e+10 | N68: =F68*(1+M68) -> 1.0893871e+13 | O68: =IFERROR(N68/N67-1,"") | P68: =IFERROR(F68/F67-1,"") -> 0.05
C69: 2035 | D69: =IFERROR(E69/F69,"") -> 6133.1567 | E69: =(AVERAGE(D49:D57))*F69 -> 714704.99 | F69: =WEO_Data!C43 -> 116.53134 | G69: =TREND($G$36:$G$57,$C$36:$C$57,C69) -> 0.22209502 | H69: =EXP(G69+$B$2*LN(E69)) -> 139.76519 | I69: 0 | J69: =(1-$B$3)*J68+I69 -> -3.4814742e+41 | K69: =E69+J69 -> -3.4814742e+41 | L69: =EXP(G69+$B$2*LN(K69)) -> #VALUE! | M69: =L69/H69-1 -> #VALUE! | N69: =F69*(1+M69) -> #VALUE! | O69: =IFERROR(N69/N68-1,"") | P69: =IFERROR(F69/F68-1,"") -> 0.05
C70: 2036 | D70: =IFERROR(E70/F70,"") -> 6133.1567 | E70: =(AVERAGE(D49:D57))*F70 -> 750440.24 | F70: =WEO_Data!C44 -> 122.35791 | G70: =TREND($G$36:$G$57,$C$36:$C$57,C70) -> 0.26786582 | H70: =EXP(G70+$B$2*LN(E70)) -> 148.83096 | I70: 0 | J70: =(1-$B$3)*J69+I70 -> 6.9996782e+45 | K70: =E70+J70 -> 6.9996782e+45 | L70: =EXP(G70+$B$2*LN(K70)) -> 1.4524794e+16 | M70: =L70/H70-1 -> 9.7592555e+13 | N70: =F70*(1+M70) -> 1.1941221e+16 | O70: =IFERROR(N70/N69-1,"") | P70: =IFERROR(F70/F69-1,"") -> 0.05
C71: 2037 | D71: =IFERROR(E71/F71,"") -> 6133.1567 | E71: =(AVERAGE(D49:D57))*F71 -> 787962.25 | F71: =WEO_Data!C45 -> 128.47581 | G71: =TREND($G$36:$G$57,$C$36:$C$57,C71) -> 0.31363661 | H71: =EXP(G71+$B$2*LN(E71)) -> 158.48477 | I71: 0 | J71: =(1-$B$3)*J70+I71 -> -1.4073203e+50 | K71: =E71+J71 -> -1.4073203e+50 | L71: =EXP(G71+$B$2*LN(K71)) -> #VALUE! | M71: =L71/H71-1 -> #VALUE! | N71: =F71*(1+M71) -> #VALUE! | O71: =IFERROR(N71/N70-1,"") | P71: =IFERROR(F71/F70-1,"") -> 0.05
C72: 2038 | D72: =IFERROR(E72/F72,"") -> 6133.1567 | E72: =(AVERAGE(D49:D57))*F72 -> 827360.36 | F72: =WEO_Data!C46 -> 134.8996 | G72: =TREND($G$36:$G$57,$C$36:$C$57,C72) -> 0.3594074 | H72: =EXP(G72+$B$2*LN(E72)) -> 168.76477 | I72: 0 | J72: =(1-$B$3)*J71+I72 -> 2.829488e+54 | K72: =E72+J72 -> 2.829488e+54 | L72: =EXP(G72+$B$2*LN(K72)) -> 1.6375192e+19 | M72: =L72/H72-1 -> 9.702968e+16 | N72: =F72*(1+M72) -> 1.3089265e+19 | O72: =IFERROR(N72/N71-1,"") | P72: =IFERROR(F72/F71-1,"") -> 0.05
C73: 2039 | D73: =IFERROR(E73/F73,"") -> 6133.1567 | E73: =(AVERAGE(D49:D57))*F73 -> 868728.38 | F73: =WEO_Data!C47 -> 141.64458 | G73: =TREND($G$36:$G$57,$C$36:$C$57,C73) -> 0.40517819 | H73: =EXP(G73+$B$2*LN(E73)) -> 179.71158 | I73: 0 | J73: =(1-$B$3)*J72+I73 -> -5.6888273e+58 | K73: =E73+J73 -> -5.6888273e+58 | L73: =EXP(G73+$B$2*LN(K73)) -> #VALUE! | M73: =L73/H73-1 -> #VALUE! | N73: =F73*(1+M73) -> #VALUE! | O73: =IFERROR(N73/N72-1,"") | P73: =IFERROR(F73/F72-1,"") -> 0.05
C74: 2040 | D74: =IFERROR(E74/F74,"") -> 6133.1567 | E74: =(AVERAGE(D49:D57))*F74 -> 912164.8 | F74: =WEO_Data!C48 -> 148.7268 | G74: =TREND($G$36:$G$57,$C$36:$C$57,C74) -> 0.45094898 | H74: =EXP(G74+$B$2*LN(E74)) -> 191.36844 | I74: 0 | J74: =(1-$B$3)*J73+I74 -> 1.1437672e+63 | K74: =E74+J74 -> 1.1437672e+63 | L74: =EXP(G74+$B$2*LN(K74)) -> 1.8461323e+22 | M74: =L74/H74-1 -> 9.6470053e+19 | N74: =F74*(1+M74) -> 1.4347683e+22 | O74: =IFERROR(N74/N73-1,"") | P74: =IFERROR(F74/F73-1,"") -> 0.05
C75: 2041 | D75: =IFERROR(E75/F75,"") -> 6133.1567 | E75: =(AVERAGE(D49:D57))*F75 -> 957773.04 | F75: =WEO_Data!C49 -> 156.16315 | G75: =TREND($G$36:$G$57,$C$36:$C$57,C75) -> 0.49671977 | H75: =EXP(G75+$B$2*LN(E75)) -> 203.78141 | I75: 0 | J75: =(1-$B$3)*J74+I75 -> -2.2996012e+67 | K75: =E75+J75 -> -2.2996012e+67 | L75: =EXP(G75+$B$2*LN(K75)) -> #VALUE! | M75: =L75/H75-1 -> #VALUE! | N75: =F75*(1+M75) -> #VALUE! | O75: =IFERROR(N75/N74-1,"") | P75: =IFERROR(F75/F74-1,"") -> 0.05

Sheet Investment
B1: Year | C1: Project Investment (Deflated)
B2: 2026 | C2: 648.58931
B3: 2027 | C3: 1220.0802
B4: 2028 | C4: 1756.1737
B5: 2029 | C5: 2221.1947
B6: 2030 | C6: 2122.4679
B7: 2031 | C7: 1524.5246
B8: 2032 | C8: 738.17631
B9: 2033 | C9: 352.60598

Sheet CFC data
A1: DATE | B1: TIME PERIOD | C1: Consumption of fixed capital (IDCM.A.N.GE.W2.S1.S1.D.P51C.N1G._T._Z.XDC.V.N) | D1: Capital Stock | E1: Depreciation rate
A2: 35430 | B2: 1996 | C2: 3.0451509e+08 | D2: =PWT!B8 -> 242089.69 | E2: =IFERROR(C2/D2,"") -> 1257.8607
A3: 35795 | B3: 1997 | C3: 3.8364166e+08 | D3: =PWT!B9 -> 239425.36 | E3: =IFERROR(C3/D3,"") -> 1602.3435
A4: 36160 | B4: 1998 | C4: 5.1639712e+08 | D4: =PWT!B10 -> 239121.89 | E4: =IFERROR(C4/D4,"") -> 2159.556
A5: 36525 | B5: 1999 | C5: 6.6160383e+08 | D5: =PWT!B11 -> 239199.27 | E5: =IFERROR(C5/D5,"") -> 2765.9108
A6: 36891 | B6: 2000 | C6: 6.31701e+08 | D6: =PWT!B12 -> 239171.61 | E6: =IFERROR(C6/D6,"") -> 2641.204
A7: 37256 | B7: 2001 | C7: 7.0698373e+08 | D7: =PWT!B13 -> 240066.27 | E7: =IFERROR(C7/D7,"") -> 2944.9524
A8: 37621 | B8: 2002 | C8: 7.9011257e+08 | D8: =PWT!B14 -> 240523.05 | E8: =IFERROR(C8/D8,"") -> 3284.9765
A9: 37986 | B9: 2003 | C9: 9.3291622e+08 | D9: =PWT!B15 -> 242715.27 | E9: =IFERROR(C9/D9,"") -> 3843.6652
A10: 38352 | B10: 2004 | C10: 9.7681854e+08 | D10: =PWT!B16 -> 245580.14 | E10: =IFERROR(C10/D10,"") -> 3977.5958
A11: 38717 | B11: 2005 | C11: 1.1134501e+09 | D11: =PWT!B17 -> 249248.98 | E11: =IFERROR(C11/D11,"") -> 4467.22
A12: 39082 | B12: 2006 | C12: 1.3063731e+09 | D12: =PWT!B18 -> 252297.08 | E12: =IFERROR(C12/D12,"") -> 5177.916
A13: 39447 | B13: 2007 | C13: 1.61703e+09 | D13: =PWT!B19 -> 256234.11 | E13: =IFERROR(C13/D13,"") -> 6310.7522
... A29: 45291 | B29: 2023 | C29: 9.4106578e+09 | D29: =PWT!B35 -> 326952.9 | E29: =IFERROR(C29/D29,"") -> 28782.916

Sheet PWT
A1: year | B1: rnna | C1: rgdpna
A2: 1990 | B2: 269494.41 | C2: 60484.336
A3: 1991 | B3: 271117.44 | C3: 47581.012
A4: 1992 | B4: 266614.81 | C4: 26406.215
A5: 1993 | B5: 256535.47 | C5: 18671.656
A6: 1994 | B6: 249672.47 | C6: 16733.326
A7: 1995 | B7: 245497.81 | C7: 17164.639
A8: 1996 | B8: 242089.69 | C8: 19101.854
A9: 1997 | B9: 239425.36 | C9: 21111.174
A10: 1998 | B10: 239121.89 | C10: 21766.67
A11: 1999 | B11: 239199.27 | C11: 22391.207
A12: 2000 | B12: 239171.61 | C12: 22802.836
A13: 2001 | B13: 240066.27 | C13: 23898.615
... A31: 2019 | B31: 298215.06 | C31: 63508.824
A32: 2020 | B32: =B31*(B$31/B$26)^(1/5) -> 305153.59 | C32: =C31*(C$31/C$26)^(1/5) -> 66143.6
A33: 2021 | B33: =B32*(B$31/B$26)^(1/5) -> 312253.55 | C33: =C32*(C$31/C$26)^(1/5) -> 68887.684
A34: 2022 | B34: =B33*(B$31/B$26)^(1/5) -> 319518.71 | C34: =C33*(C$31/C$26)^(1/5) -> 71745.61
A35: 2023 | B35: =B34*(B$31/B$26)^(1/5) -> 326952.9 | C35: =C34*(C$31/C$26)^(1/5) -> 74722.104

Sheet WEO_Data
B1: WEO Country Code | C1: 915 | D1: 915
B2: WEO Subject Code | C2: NGDP_R | D2: NGDP_RPCH
B3: Country | C3: Georgia | D3: Georgia
B4: Subject Descriptor | C4: Gross domestic product, constant prices | D4: Gross domestic product, constant prices
B5: Units | C5: National currency | D5: Percent change
B6: Scale | C6: Billions | D6: Units
B7: Country/Series-specific Notes | C7: Source: National Statistics Office. Historical data from 2010 revised in February 2024 Latest actual data: 2024 Notes: Data prior to 1996 cannot be confirmed by national sources. Data prior to 2010 are based on staff estimates. National accounts manual used: System of National Accounts (SNA) 2008 GDP valuation: Market prices Reporting in calendar year: Yes Start/end months of reporting year: January/December Base year: 2019 Chain-weighted: Yes, from 1996 Primary domestic currency: Georgian lari Data last updated: 04/09/2025 | D7: See notes for: Gross domestic product, constant prices (National currency).
B8: 2000 | C8: 16.963 | D8: 1.865
B9: 2001 | C9: 17.772 | D9: 4.769
B10: 2002 | C10: 18.747 | D10: 5.487
B11: 2003 | C11: 20.852 | D11: 11.228
B12: 2004 | C12: 22.061 | D12: 5.796
B13: 2005 | C13: 24.176 | D13: 9.588
B14: 2006 | C14: 26.454 | D14: 9.42
B15: 2007 | C15: 29.781 | D15: 12.579
B16: 2008 | C16: 30.502 | D16: 2.419
B17: 2009 | C17: 29.388 | D17: -3.651
B18: 2010 | C18: 31.428 | D18: 6.942
B19: 2011 | C19: 33.927 | D19: 7.949
... B35: 2027 | C35: 78.873 | D35: 5
B36: 2028 | C36: =C35*(1+D36/100) -> 82.81665 | D36: =$D$35 -> 5
B37: 2029 | C37: =C36*(1+D37/100) -> 86.957482 | D37: =$D$35 -> 5
B38: 2030 | C38: =C37*(1+D38/100) -> 91.305357 | D38: =$D$35 -> 5
B39: 2031 | C39: =C38*(1+D39/100) -> 95.870624 | D39: =$D$35 -> 5
B40: 2032 | C40: =C39*(1+D40/100) -> 100.66416 | D40: =$D$35 -> 5
B41: 2033 | C41: =C40*(1+D41/100) -> 105.69736 | D41: =$D$35 -> 5
B42: 2034 | C42: =C41*(1+D42/100) -> 110.98223 | D42: =$D$35 -> 5
B43: 2035 | C43: =C42*(1+D43/100) -> 116.53134 | D43: =$D$35 -> 5
B44: 2036 | C44: =C43*(1+D44/100) -> 122.35791 | D44: =$D$35 -> 5
B45: 2037 | C45: =C44*(1+D45/100) -> 128.47581 | D45: =$D$35 -> 5
B46: 2038 | C46: =C45*(1+D46/100) -> 134.8996 | D46: =$D$35 -> 5
B47: 2039 | C47: =C46*(1+D47/100) -> 141.64458 | D47: =$D$35 -> 5
... B51: 2043 | C51: =C50*(1+D51/100) -> 172.16987 | D51: =$D$35 -> 5
