Workbook

Sheet Production
A1: Assumption
A2: capital's share | B2: 0.35
A3: annual depreciation rate | B3: =AVERAGE('CFC data'!E18:E25) -> 0.015248298
K4: HP Filter | O4: lambda | P4: 100
D5: K | E5: Real GDP | F5: LnK | G5: LnY | K5: LnZ | L5: LnZ_HP | M5: Second-order difference | N5: LnA-Trend(Check) | O5: Objective | P5: =SUMSQ(N6:N27)+P4*SUMSQ(M7:M26) -> 7.9943574
C6: 2002 | D6: =PWT!B14 -> 197317.59 | E6: =WEO_Data!C10 -> 18.747 | F6: =LN(D6) -> 12.19257 | G6: =LN(E6) -> 2.9310337 | K6: =G6-$B$2*F6 -> -1.3363657 | L6: =K6 -> -1.3363657 | N6: =K6-L6 -> 0
C7: 2003 | D7: =PWT!B15 -> 199678.92 | E7: =WEO_Data!C11 -> 20.852 | F7: =LN(D7) -> 12.204466 | G7: =LN(E7) -> 3.0374499 | K7: =G7-$B$2*F7 -> -1.2341132 | L7: =K7 -> -1.2341132 | M7: =L8-2*L7+L6 -> -0.051075617 | N7: =K7-L7 -> 0
C8: 2004 | D8: =PWT!B16 -> 202658.81 | E8: =WEO_Data!C12 -> 22.061 | F8: =LN(D8) -> 12.219279 | G8: =LN(E8) -> 3.0938113 | K8: =G8-$B$2*F8 -> -1.1829363 | L8: =K8 -> -1.1829363 | M8: =L9-2*L8+L7 -> 0.033969072 | N8: =K8-L8 -> 0
C9: 2005 | D9: =PWT!B17 -> 206400.5 | E9: =WEO_Data!C13 -> 24.176 | F9: =LN(D9) -> 12.237574 | G9: =LN(E9) -> 3.1853604 | K9: =G9-$B$2*F9 -> -1.0977904 | L9: =K9 -> -1.0977904 | M9: =L10-2*L9+L8 -> -0.00058344314 | N9: =K9-L9 -> 0
C10: 2006 | D10: =PWT!B18 -> 209660.25 | E10: =WEO_Data!C14 -> 26.454 | F10: =LN(D10) -> 12.253244 | G10: =LN(E10) -> 3.2754074 | K10: =G10-$B$2*F10 -> -1.0132279 | L10: =K10 -> -1.0132279 | M10: =L11-2*L10+L9 -> 0.027022316 | N10: =K10-L10 -> 0
C11: 2007 | D11: =PWT!B19 -> 213821.38 | E11: =WEO_Data!C15 -> 29.781 | F11: =LN(D11) -> 12.272896 | G11: =LN(E11) -> 3.3938706 | K11: =G11-$B$2*F11 -> -0.90164308 | L11: =K11 -> -0.90164308 | M11: =L12-2*L11+L10 -> -0.090929062 | N11: =K11-L11 -> 0
C12: 2008 | D12: =PWT!B20 -> 215825.91 | E12: =WEO_Data!C16 -> 30.502 | F12: =LN(D12) -> 12.282227 | G12: =LN(E12) -> 3.4177923 | K12: =G12-$B$2*F12 -> -0.88098733 | L12: =K12 -> -0.88098733 | M12: =L13-2*L12+L11 -> -0.055714396 | N12: =K12-L12 -> 0
C13: 2009 | D13: =PWT!B21 -> 214505.91 | E13: =WEO_Data!C17 -> 29.388 | F13: =LN(D13) -> 12.276093 | G13: =LN(E13) -> 3.3805864 | K13: =G13-$B$2*F13 -> -0.91604597 | L13: =K13 -> -0.91604597 | M13: =L14-2*L13+L12 -> 0.10016312 | N13: =K13-L13 -> 0
C14: 2010 | D14: =PWT!B22 -> 215740.28 | E14: =WEO_Data!C18 -> 31.428 | F14: =LN(D14) -> 12.281831 | G14: =LN(E14) -> 3.4476992 | K14: =G14-$B$2*F14 -> -0.85094148 | L14: =K14 -> -0.85094148 | M14: =L15-2*L14+L13 -> 0.0072251827 | N14: =K14-L14 -> 0
C15: 2011 | D15: =PWT!B23 -> 218333.7 | E15: =WEO_Data!C19 -> 33.927 | F15: =LN(D15) -> 12.29378 | G15: =LN(E15) -> 3.5242112 | K15: =G15-$B$2*F15 -> -0.77861181 | L15: =K15 -> -0.77861181 | M15: =L16-2*L15+L14 -> -0.013764966 | N15: =K15-L15 -> 0
C16: 2012 | D16: =PWT!B24 -> 221570.09 | E16: =WEO_Data!C20 -> 36.159 | F16: =LN(D16) -> 12.308494 | G16: =LN(E16) -> 3.5879259 | K16: =G16-$B$2*F16 -> -0.72004711 | L16: =K16 -> -0.72004711 | M16: =L17-2*L16+L15 -> -0.011438411 | N16: =K16-L16 -> 0
C17: 2013 | D17: =PWT!B25 -> 223431.88 | E17: =WEO_Data!C21 -> 38.015 | F17: =LN(D17) -> 12.316862 | G17: =LN(E17) -> 3.6379808 | K17: =G17-$B$2*F17 -> -0.67292082 | L17: =K17 -> -0.67292082 | M17: =L18-2*L17+L16 -> -0.013984366 | N17: =K17-L17 -> 0
C18: 2014 | D18: =PWT!B26 -> 227911.97 | E18: =WEO_Data!C22 -> 39.57 | F18: =LN(D18) -> 12.336715 | G18: =LN(E18) -> 3.6780713 | K18: =G18-$B$2*F18 -> -0.6397789 | L18: =K18 -> -0.6397789 | M18: =L19-2*L18+L17 -> -0.009654 | N18: =K18-L18 -> 0
... C23: 2019 | D23: =PWT!B31 -> 264125.56 | E23: =WEO_Data!C27 -> 49.726 | F23: =LN(D23) -> 12.48418 | G23: =LN(E23) -> 3.9065279 | K23: =G23-$B$2*F23 -> -0.46293502 | L23: =K23 -> -0.46293502 | M23: =L24-2*L23+L22 -> -0.14707274 | N23: =K23-L23 -> 0
C24: 2020 | D24: =D23*'CFC data'!C26/'CFC data'!C25 -> 298022.44 | E24: =WEO_Data!C28 -> 46.598 | F24: =LN(D24) -> 12.604924 | G24: =LN(E24) -> 3.8415576 | K24: =G24-$B$2*F24 -> -0.5701658 | L24: =K24 -> -0.5701658 | M24: =L25-2*L24+L23 -> 0.15961522 | N24: =K24-L24 -> 0
C25: 2021 | D25: =D24*'CFC data'!C27/'CFC data'!C26 -> 342577.62 | E25: =WEO_Data!C29 -> 51.558 | F25: =LN(D25) -> 12.744254 | G25: =LN(E25) -> 3.9427074 | K25: =G25-$B$2*F25 -> -0.51778135 | L25: =K25 -> -0.51778135 | M25: =L26-2*L25+L24 -> 0.023612654 | N25: =K25-L25 -> 0
C26: 2022 | D26: =D25*'CFC data'!C28/'CFC data'!C27 -> 371098.52 | E26: =WEO_Data!C30 -> 57.208 | F26: =LN(D26) -> 12.824223 | G26: =LN(E26) -> 4.0466937 | K26: =G26-$B$2*F26 -> -0.44178425 | L26: =K26 -> -0.44178425 | M26: =L27-2*L26+L25 -> -0.072559846 | N26: =K26-L26 -> 0
C27: 2023 | D27: =D26*'CFC data'!C29/'CFC data'!C28 -> 455825.18 | E27: =WEO_Data!C31 -> 61.689 | F27: =LN(D27) -> 13.029865 | G27: =LN(E27) -> 4.1221056 | K27: =G27-$B$2*F27 -> -0.43834699 | L27: =K27 -> -0.43834699 | N27: =K27-L27 -> 0
C30: HP filter Solver setup:
C31: Data -> Solver: Set Objective P5 to Min, By Changing Variable Cells L6:L27, no constraints, Solving Method: GRG Nonlinear. Lambda in P4 (default 100).
D35: K/Y | E35: K | F35: Y | G35: LnZ trend | H35: Ystar_base | I35: Investment | J35: ΔK | K35: K_With | L35: Ystar_with | M35: Uplift | N35: Projected GDP | O35: Projected GDP Growth | P35: Baseline GDP Growth
C36: 2002 | D36: =E36/F36 -> 10525.289 | E36: =D6 -> 197317.59 | F36: =WEO_Data!C10 -> 18.747 | G36: =L6 -> -1.3363657 | H36: =EXP(G36)*E36^$B$2 -> 18.747 | I36: 0 | J36: =I36 -> 0 | K36: =E36+J36 -> 197317.59 | L36: =EXP(G36)*K36^$B$2 -> 18.747 | M36: =L36-H36 -> 0 | N36: =L36 -> 18.747
C37: 2003 | D37: =E37/F37 -> 9576.0081 | E37: =D7 -> 199678.92 | F37: =WEO_Data!C11 -> 20.852 | G37: =L7 -> -1.2341132 | H37: =EXP(G37)*E37^$B$2 -> 20.852 | I37: 0 | J37: =J36*(1-$B$3)+I37 -> 0 | K37: =E37+J37 -> 199678.92 | L37: =EXP(G37)*K37^$B$2 -> 20.852 | M37: =L37-H37 -> 0 | N37: =L37 -> 20.852 | O37: =N37/N36-1 -> 0.11228463 | P37: =H37/H36-1 -> 0.11228463
C38: 2004 | D38: =E38/F38 -> 9186.2931 | E38: =D8 -> 202658.81 | F38: =WEO_Data!C12 -> 22.061 | G38: =L8 -> -1.1829363 | H38: =EXP(G38)*E38^$B$2 -> 22.061 | I38: 0 | J38: =J37*(1-$B$3)+I38 -> 0 | K38: =E38+J38 -> 202658.81 | L38: =EXP(G38)*K38^$B$2 -> 22.061 | M38: =L38-H38 -> 0 | N38: =L38 -> 22.061 | O38: =N38/N37-1 -> 0.05798005 | P38: =H38/H37-1 -> 0.05798005
C39: 2005 | D39: =E39/F39 -> 8537.4131 | E39: =D9 -> 206400.5 | F39: =WEO_Data!C13 -> 24.176 | G39: =L9 -> -1.0977904 | H39: =EXP(G39)*E39^$B$2 -> 24.176 | I39: 0 | J39: =J38*(1-$B$3)+I39 -> 0 | K39: =E39+J39 -> 206400.5 | L39: =EXP(G39)*K39^$B$2 -> 24.176 | M39: =L39-H39 -> 0 | N39: =L39 -> 24.176 | O39: =N39/N38-1 -> 0.095870541 | P39: =H39/H38-1 -> 0.095870541
C40: 2006 | D40: =E40/F40 -> 7925.465 | E40: =D10 -> 209660.25 | F40: =WEO_Data!C14 -> 26.454 | G40: =L10 -> -1.0132279 | H40: =EXP(G40)*E40^$B$2 -> 26.454 | I40: 0 | J40: =J39*(1-$B$3)+I40 -> 0 | K40: =E40+J40 -> 209660.25 | L40: =EXP(G40)*K40^$B$2 -> 26.454 | M40: =L40-H40 -> 0 | N40: =L40 -> 26.454 | O40: =N40/N39-1 -> 0.094225678 | P40: =H40/H39-1 -> 0.094225678
C41: 2007 | D41: =E41/F41 -> 7179.7916 | E41: =D11 -> 213821.38 | F41: =WEO_Data!C15 -> 29.781 | G41: =L11 -> -0.90164308 | H41: =EXP(G41)*E41^$B$2 -> 29.781 | I41: 0 | J41: =J40*(1-$B$3)+I41 -> 0 | K41: =E41+J41 -> 213821.38 | L41: =EXP(G41)*K41^$B$2 -> 29.781 | M41: =L41-H41 -> 0 | N41: =L41 -> 29.781 | O41: =N41/N40-1 -> 0.12576548 | P41: =H41/H40-1 -> 0.12576548
C42: 2008 | D42: =E42/F42 -> 7075.7952 | E42: =D12 -> 215825.91 | F42: =WEO_Data!C16 -> 30.502 | G42: =L12 -> -0.88098733 | H42: =EXP(G42)*E42^$B$2 -> 30.502 | I42: 0 | J42: =J41*(1-$B$3)+I42 -> 0 | K42: =E42+J42 -> 215825.91 | L42: =EXP(G42)*K42^$B$2 -> 30.502 | M42: =L42-H42 -> 0 | N42: =L42 -> 30.502 | O42: =N42/N41-1 -> 0.024210067 | P42: =H42/H41-1 -> 0.024210067
C43: 2009 | D43: =E43/F43 -> 7299.0985 | E43: =D13 -> 214505.91 | F43: =WEO_Data!C17 -> 29.388 | G43: =L13 -> -0.91604597 | H43: =EXP(G43)*E43^$B$2 -> 29.388 | I43: 0 | J43: =J42*(1-$B$3)+I43 -> 0 | K43: =E43+J43 -> 214505.91 | L43: =EXP(G43)*K43^$B$2 -> 29.388 | M43: =L43-H43 -> 0 | N43: =L43 -> 29.388 | O43: =N43/N42-1 -> -0.036522195 | P43: =H43/H42-1 -> -0.036522195
C44: 2010 | D44: =E44/F44 -> 6864.5883 | E44: =D14 -> 215740.28 | F44: =WEO_Data!C18 -> 31.428 | G44: =L14 -> -0.85094148 | H44: =EXP(G44)*E44^$B$2 -> 31.428 | I44: 0 | J44: =J43*(1-$B$3)+I44 -> 0 | K44: =E44+J44 -> 215740.28 | L44: =EXP(G44)*K44^$B$2 -> 31.428 | M44: =L44-H44 -> 0 | N44: =L44 -> 31.428 | O44: =N44/N43-1 -> 0.069416088 | P44: =H44/H43-1 -> 0.069416088
C45: 2011 | D45: =E45/F45 -> 6435.3967 | E45: =D15 -> 218333.7 | F45: =WEO_Data!C19 -> 33.927 | G45: =L15 -> -0.77861181 | H45: =EXP(G45)*E45^$B$2 -> 33.927 | I45: 0 | J45: =J44*(1-$B$3)+I45 -> 0 | K45: =E45+J45 -> 218333.7 | L45: =EXP(G45)*K45^$B$2 -> 33.927 | M45: =L45-H45 -> 0 | N45: =L45 -> 33.927 | O45: =N45/N44-1 -> 0.079515082 | P45: =H45/H44-1 -> 0.079515082
C46: 2012 | D46: =E46/F46 -> 6127.661 | E46: =D16 -> 221570.09 | F46: =WEO_Data!C20 -> 36.159 | G46: =L16 -> -0.72004711 | H46: =EXP(G46)*E46^$B$2 -> 36.159 | I46: 0 | J46: =J45*(1-$B$3)+I46 -> 0 | K46: =E46+J46 -> 221570.09 | L46: =EXP(G46)*K46^$B$2 -> 36.159 | M46: =L46-H46 -> 0 | N46: =L46 -> 36.159 | O46: =N46/N45-1 -> 0.06578831 | P46: =H46/H45-1 -> 0.06578831
C47: 2013 | D47: =E47/F47 -> 5877.4661 | E47: =D17 -> 223431.88 | F47: =WEO_Data!C21 -> 38.015 | G47: =L17 -> -0.67292082 | H47: =EXP(G47)*E47^$B$2 -> 38.015 | I47: 0 | J47: =J46*(1-$B$3)+I47 -> 0 | K47: =E47+J47 -> 223431.88 | L47: =EXP(G47)*K47^$B$2 -> 38.015 | M47: =L47-H47 -> 0 | N47: =L47 -> 38.015 | O47: =N47/N46-1 -> 0.051328853 | P47: =H47/H46-1 -> 0.051328853
C48: 2014 | D48: =E48/F48 -> 5759.7162 | E48: =D18 -> 227911.97 | F48: =WEO_Data!C22 -> 39.57 | G48: =L18 -> -0.6397789 | H48: =EXP(G48)*E48^$B$2 -> 39.57 | I48: 0 | J48: =J47*(1-$B$3)+I48 -> 0 | K48: =E48+J48 -> 227911.97 | L48: =EXP(G48)*K48^$B$2 -> 39.57 | M48: =L48-H48 -> 0 | N48: =L48 -> 39.57 | O48: =N48/N47-1 -> 0.040904906 | P48: =H48/H47-1 -> 0.040904906
... C57: 2023 | D57: =E57/F57 -> 7389.0837 | E57: =D27 -> 455825.18 | F57: =WEO_Data!C31 -> 61.689 | G57: =L27 -> -0.43834699 | H57: =EXP(G57)*E57^$B$2 -> 61.689 | I57: 0 | J57: =J56*(1-$B$3)+I57 -> 0 | K57: =E57+J57 -> 455825.18 | L57: =EXP(G57)*K57^$B$2 -> 61.689 | M57: =L57-H57 -> 0 | N57: =L57 -> 61.689 | O57: =N57/N56-1 -> 0.078328206 | P57: =H57/H56-1 -> 0.078328206
C58: 2024 | D58: =E58/F58 -> 6069.8074 | E58: =AVERAGE($D$49:$D$57)*F58 -> 409742.35 | F58: =WEO_Data!C32 -> 67.505 | G58: =TREND($G$36:$G$57,$C$36:$C$57,C58) -> -0.30458768 | H58: =EXP(G58)*E58^$B$2 -> 67.935699 | I58: 0 | J58: =J57*(1-$B$3)+I58 -> 0 | K58: =E58+J58 -> 409742.35 | L58: =EXP(G58)*K58^$B$2 -> 67.935699 | M58: =L58-H58 -> 0 | N58: =L58 -> 67.935699 | O58: =N58/N57-1 -> 0.10126115 | P58: =H58/H57-1 -> 0.10126115
C59: 2025 | D59: =E59/F59 -> 6069.8074 | E59: =AVERAGE($D$49:$D$57)*F59 -> 434234.02 | F59: =WEO_Data!C33 -> 71.54 | G59: =TREND($G$36:$G$57,$C$36:$C$57,C59) -> -0.26419479 | H59: =EXP(G59)*E59^$B$2 -> 72.188 | I59: 0 | J59: =J58*(1-$B$3)+I59 -> 0 | K59: =E59+J59 -> 434234.02 | L59: =EXP(G59)*K59^$B$2 -> 72.188 | M59: =L59-H59 -> 0 | N59: =L59 -> 72.188 | O59: =N59/N58-1 -> 0.062593015 | P59: =H59/H58-1 -> 0.062593015
C60: 2026 | D60: =E60/F60 -> 6069.8074 | E60: =AVERAGE($D$49:$D$57)*F60 -> 455945.72 | F60: =WEO_Data!C34 -> 75.117 | G60: =TREND($G$36:$G$57,$C$36:$C$57,C60) -> -0.2238019 | H60: =EXP(G60)*E60^$B$2 -> 76.45813 | I60: =Investment!C2 -> 648.58931 | J60: =J59*(1-$B$3)+I60 -> 648.58931 | K60: =E60+J60 -> 456594.31 | L60: =EXP(G60)*K60^$B$2 -> 76.496179 | M60: =L60-H60 -> 0.038049389 | N60: =L60 -> 76.496179 | O60: =N60/N59-1 -> 0.059679996 | P60: =H60/H59-1 -> 0.059152909
C61: 2027 | D61: =E61/F61 -> 6069.8074 | E61: =AVERAGE($D$49:$D$57)*F61 -> 478743.92 | F61: =WEO_Data!C35 -> 78.873 | G61: =TREND($G$36:$G$57,$C$36:$C$57,C61) -> -0.18340901 | H61: =EXP(G61)*E61^$B$2 -> 80.980904 | I61: =Investment!C3 -> 1220.0802 | J61: =J60*(1-$B$3)+I61 -> 1858.7796 | K61: =E61+J61 -> 480602.7 | L61: =EXP(G61)*K61^$B$2 -> 81.090812 | M61: =L61-H61 -> 0.1099077 | N61: =L61 -> 81.090812 | O61: =N61/N60-1 -> 0.060063562 | P61: =H61/H60-1 -> 0.059153614
C62: 2028 | D62: =E62/F62 -> 6069.8074 | E62: =AVERAGE($D$49:$D$57)*F62 -> 502681.12 | F62: =WEO_Data!C36 -> 82.81665 | G62: =TREND($G$36:$G$57,$C$36:$C$57,C62) -> -0.14301612 | H62: =EXP(G62)*E62^$B$2 -> 85.771161 | I62: =Investment!C4 -> 1756.1737 | J62: =J61*(1-$B$3)+I62 -> 3586.6101 | K62: =E62+J62 -> 506267.73 | L62: =EXP(G62)*K62^$B$2 -> 85.984857 | M62: =L62-H62 -> 0.21369612 | N62: =L62 -> 85.984857 | O62: =N62/N61-1 -> 0.060352639 | P62: =H62/H61-1 -> 0.059152909
C63: 2029 | D63: =E63/F63 -> 6069.8074 | E63: =AVERAGE($D$49:$D$57)*F63 -> 527815.17 | F63: =WEO_Data!C37 -> 86.957482 | G63: =TREND($G$36:$G$57,$C$36:$C$57,C63) -> -0.10262323 | H63: =EXP(G63)*E63^$B$2 -> 90.844774 | I63: =Investment!C5 -> 2221.1947 | J63: =J62*(1-$B$3)+I63 -> 5753.1151 | K63: =E63+J63 -> 533568.29 | L63: =EXP(G63)*K63^$B$2 -> 91.190122 | M63: =L63-H63 -> 0.34534818 | N63: =L63 -> 91.190122 | O63: =N63/N62-1 -> 0.060537005 | P63: =H63/H62-1 -> 0.059152909
C64: 2030 | D64: =E64/F64 -> 6069.8074 | E64: =AVERAGE($D$49:$D$57)*F64 -> 554205.93 | F64: =WEO_Data!C38 -> 91.305357 | G64: =TREND($G$36:$G$57,$C$36:$C$57,C64) -> -0.062230346 | H64: =EXP(G64)*E64^$B$2 -> 96.218507 | I64: =Investment!C6 -> 2122.4679 | J64: =J63*(1-$B$3)+I64 -> 7787.8577 | K64: =E64+J64 -> 561993.79 | L64: =EXP(G64)*K64^$B$2 -> 96.689594 | M64: =L64-H64 -> 0.47108665 | N64: =L64 -> 96.689594 | O64: =N64/N63-1 -> 0.06030775 | P64: =H64/H63-1 -> 0.059152909
C65: 2031 | D65: =E65/F65 -> 6069.8074 | E65: =AVERAGE($D$49:$D$57)*F65 -> 581916.23 | F65: =WEO_Data!C39 -> 95.870624 | G65: =TREND($G$36:$G$57,$C$36:$C$57,C65) -> -0.021837457 | H65: =EXP(G65)*E65^$B$2 -> 101.91011 | I65: =Investment!C7 -> 1524.5246 | J65: =J64*(1-$B$3)+I65 -> 9193.6308 | K65: =E65+J65 -> 591109.86 | L65: =EXP(G65)*K65^$B$2 -> 102.47077 | M65: =L65-H65 -> 0.56065474 | N65: =L65 -> 102.47077 | O65: =N65/N64-1 -> 0.059791054 | P65: =H65/H64-1 -> 0.059152909
C66: 2032 | D66: =E66/F66 -> 6069.8074 | E66: =AVERAGE($D$49:$D$57)*F66 -> 611012.04 | F66: =WEO_Data!C40 -> 100.66416 | G66: =TREND($G$36:$G$57,$C$36:$C$57,C66) -> 0.018555431 | H66: =EXP(G66)*E66^$B$2 -> 107.93839 | I66: =Investment!C8 -> 738.17631 | J66: =J65*(1-$B$3)+I66 -> 9791.6198 | K66: =E66+J66 -> 620803.66 | L66: =EXP(G66)*K66^$B$2 -> 108.54067 | M66: =L66-H66 -> 0.60228325 | N66: =L66 -> 108.54067 | O66: =N66/N65-1 -> 0.05923551 | P66: =H66/H65-1 -> 0.059152909
C67: 2033 | D67: =E67/F67 -> 6069.8074 | E67: =AVERAGE($D$49:$D$57)*F67 -> 641562.64 | F67: =WEO_Data!C41 -> 105.69736 | G67: =TREND($G$36:$G$57,$C$36:$C$57,C67) -> 0.05894832 | H67: =EXP(G67)*E67^$B$2 -> 114.32326 | I67: =Investment!C9 -> 352.60598 | J67: =J66*(1-$B$3)+I67 -> 9994.9203 | K67: =E67+J67 -> 651557.56 | L67: =EXP(G67)*K67^$B$2 -> 114.9435 | M67: =L67-H67 -> 0.62023627 | N67: =L67 -> 114.9435 | O67: =N67/N66-1 -> 0.058990078 | P67: =H67/H66-1 -> 0.059152909
C68: 2034 | D68: =E68/F68 -> 6069.8074 | E68: =AVERAGE($D$49:$D$57)*F68 -> 673640.77 | F68: =WEO_Data!C42 -> 110.98223 | G68: =TREND($G$36:$G$57,$C$36:$C$57,C68) -> 0.099341209 | H68: =EXP(G68)*E68^$B$2 -> 121.08581 | I68: 0 | J68: =J67*(1-$B$3)+I68 -> 9842.5148 | K68: =E68+J68 -> 683483.29 | L68: =EXP(G68)*K68^$B$2 -> 121.70211 | M68: =L68-H68 -> 0.61629456 | N68: =L68 -> 121.70211 | O68: =N68/N67-1 -> 0.058799427 | P68: =H68/H67-1 -> 0.059152909
C69: 2035 | D69: =E69/F69 -> 6069.8074 | E69: =AVERAGE($D$49:$D$57)*F69 -> 707322.81 | F69: =WEO_Data!C43 -> 116.53134 | G69: =TREND($G$36:$G$57,$C$36:$C$57,C69) -> 0.1397341 | H69: =EXP(G69)*E69^$B$2 -> 128.24839 | I69: 0 | J69: =J68*(1-$B$3)+I69 -> 9692.4332 | K69: =E69+J69 -> 717015.24 | L69: =EXP(G69)*K69^$B$2 -> 128.86076 | M69: =L69-H69 -> 0.61236618 | N69: =L69 -> 128.86076 | O69: =N69/N68-1 -> 0.058821082 | P69: =H69/H68-1 -> 0.059152909
C70: 2036 | D70: =E70/F70 -> 6069.8074 | E70: =AVERAGE($D$49:$D$57)*F70 -> 742688.95 | F70: =WEO_Data!C44 -> 122.35791 | G70: =TREND($G$36:$G$57,$C$36:$C$57,C70) -> 0.18012699 | H70: =EXP(G70)*E70^$B$2 -> 135.83466 | I70: 0 | J70: =J69*(1-$B$3)+I70 -> 9544.6401 | K70: =E70+J70 -> 752233.59 | L70: =EXP(G70)*K70^$B$2 -> 136.44311 | M70: =L70-H70 -> 0.60845192 | N70: =L70 -> 136.44311 | O70: =N70/N69-1 -> 0.058841429 | P70: =H70/H69-1 -> 0.059152909
C71: 2037 | D71: =E71/F71 -> 6069.8074 | E71: =AVERAGE($D$49:$D$57)*F71 -> 779823.4 | F71: =WEO_Data!C45 -> 128.47581 | G71: =TREND($G$36:$G$57,$C$36:$C$57,C71) -> 0.22051987 | H71: =EXP(G71)*E71^$B$2 -> 143.86967 | I71: 0 | J71: =J70*(1-$B$3)+I71 -> 9399.1005 | K71: =E71+J71 -> 789222.5 | L71: =EXP(G71)*K71^$B$2 -> 144.47423 | M71: =L71-H71 -> 0.60455249 | N71: =L71 -> 144.47423 | O71: =N71/N70-1 -> 0.058860544 | P71: =H71/H70-1 -> 0.059152909
C72: 2038 | D72: =E72/F72 -> 6069.8074 | E72: =AVERAGE($D$49:$D$57)*F72 -> 818814.57 | F72: =WEO_Data!C46 -> 134.8996 | G72: =TREND($G$36:$G$57,$C$36:$C$57,C72) -> 0.26091276 | H72: =EXP(G72)*E72^$B$2 -> 152.37998 | I72: 0 | J72: =J71*(1-$B$3)+I72 -> 9255.7803 | K72: =E72+J72 -> 828070.35 | L72: =EXP(G72)*K72^$B$2 -> 152.98065 | M72: =L72-H72 -> 0.60066854 | N72: =L72 -> 152.98065 | O72: =N72/N71-1 -> 0.0588785 | P72: =H72/H71-1 -> 0.059152909
C73: 2039 | D73: =E73/F73 -> 6069.8074 | E73: =AVERAGE($D$49:$D$57)*F73 -> 859755.3 | F73: =WEO_Data!C47 -> 141.64458 | G73: =TREND($G$36:$G$57,$C$36:$C$57,C73) -> 0.30130565 | H73: =EXP(G73)*E73^$B$2 -> 161.3937 | I73: 0 | J73: =J72*(1-$B$3)+I73 -> 9114.6454 | K73: =E73+J73 -> 868869.94 | L73: =EXP(G73)*K73^$B$2 -> 161.9905 | M73: =L73-H73 -> 0.59680067 | N73: =L73 -> 161.9905 | O73: =N73/N72-1 -> 0.058895366 | P73: =H73/H72-1 -> 0.059152909
C74: 2040 | D74: =E74/F74 -> 6069.8074 | E74: =AVERAGE($D$49:$D$57)*F74 -> 902743.06 | F74: =WEO_Data!C48 -> 148.7268 | G74: =TREND($G$36:$G$57,$C$36:$C$57,C74) -> 0.34169854 | H74: =EXP(G74)*E74^$B$2 -> 170.94061 | I74: 0 | J74: =J73*(1-$B$3)+I74 -> 8975.6625 | K74: =E74+J74 -> 911718.72 | L74: =EXP(G74)*K74^$B$2 -> 171.53356 | M74: =L74-H74 -> 0.59294944 | N74: =L74 -> 171.53356 | O74: =N74/N73-1 -> 0.058911205 | P74: =H74/H73-1 -> 0.059152909
C75: 2041 | D75: =E75/F75 -> 6069.8074 | E75: =AVERAGE($D$49:$D$57)*F75 -> 947880.22 | F75: =WEO_Data!C49 -> 156.16315 | G75: =TREND($G$36:$G$57,$C$36:$C$57,C75) -> 0.38209143 | H75: =EXP(G75)*E75^$B$2 -> 181.05224 | I75: 0 | J75: =J74*(1-$B$3)+I75 -> 8838.799 | K75: =E75+J75 -> 956719.01 | L75: =EXP(G75)*K75^$B$2 -> 181.64136 | M75: =L75-H75 -> 0.58911533 | N75: =L75 -> 181.64136 | O75: =N75/N74-1 -> 0.05892608 | P75: =H75/H74-1 -> 0.059152909

Sheet Investment
B1: Year | C1: Project Investment (Deflated)
B2: 2026 | C2: 648.58931
B3: 2027 | C3: 1220.0802
B4: 2028 | C4: 1756.1737
B5: 2029 | C5: 2221.1947
B6: 2030 | C6: 2122.4679
B7: 2031 | C7: 1524.5246
B8: 2032 | C8: 738.17631
B9: 2033 | C9: 352.60598

Sheet CFC data
A1: DATE | B1: TIME PERIOD | C1: Consumption of fixed capital (IDCM.A.N.GE.W2.S1.S1.D.P51C.N1G._T._Z.XDC.V.N) | D1: Capital Stock | E1: Depreciation rate
A2: 35430 | B2: 1996 | C2: 304.51509 | D2: =PWT!B8 -> 196366.45 | E2: =IFERROR(C2/D2,"") -> 0.0015507491
A3: 35795 | B3: 1997 | C3: 383.64166 | D3: =PWT!B9 -> 194417.84 | E3: =IFERROR(C3/D3,"") -> 0.0019732842
A4: 36160 | B4: 1998 | C4: 516.39712 | D4: =PWT!B10 -> 194516.3 | E4: =IFERROR(C4/D4,"") -> 0.0026547756
A5: 36525 | B5: 1999 | C5: 661.60383 | D5: =PWT!B11 -> 194964.56 | E5: =IFERROR(C5/D5,"") -> 0.0033934569
A6: 36891 | B6: 2000 | C6: 631.701 | D6: =PWT!B12 -> 195327.08 | E6: =IFERROR(C6/D6,"") -> 0.0032340677
A7: 37256 | B7: 2001 | C7: 706.98373 | D7: =PWT!B13 -> 196512.45 | E7: =IFERROR(C7/D7,"") -> 0.0035976536
A8: 37621 | B8: 2002 | C8: 790.11257 | D8: =PWT!B14 -> 197317.59 | E8: =IFERROR(C8/D8,"") -> 0.0040042682
A9: 37986 | B9: 2003 | C9: 932.91622 | D9: =PWT!B15 -> 199678.92 | E9: =IFERROR(C9/D9,"") -> 0.0046720816
A10: 38352 | B10: 2004 | C10: 976.81854 | D10: =PWT!B16 -> 202658.81 | E10: =IFERROR(C10/D10,"") -> 0.0048200151
A11: 38717 | B11: 2005 | C11: 1113.4501 | D11: =PWT!B17 -> 206400.5 | E11: =IFERROR(C11/D11,"") -> 0.0053946093
A12: 39082 | B12: 2006 | C12: 1306.3731 | D12: =PWT!B18 -> 209660.25 | E12: =IFERROR(C12/D12,"") -> 0.0062309049
A13: 39447 | B13: 2007 | C13: 1617.03 | D13: =PWT!B19 -> 213821.38 | E13: =IFERROR(C13/D13,"") -> 0.0075625272
... A25: 43830 | B25: 2019 | C25: 5452.9574 | D25: =PWT!B31 -> 264125.56 | E25: =IFERROR(C25/D25,"") -> 0.020645322
A26: 44196 | B26: 2020 | C26: 6152.7693 | E26: =IFERROR(C26/D26,"")
A27: 44561 | B27: 2021 | C27: 7072.6253 | E27: =IFERROR(C27/D27,"")
A28: 44926 | B28: 2022 | C28: 7661.4485 | E28: =IFERROR(C28/D28,"")
A29: 45291 | B29: 2023 | C29: 9410.6578 | E29: =IFERROR(C29/D29,"")

Sheet PWT
A1: year | B1: rnna | C1: delta
A2: 1990 | B2: 217572.27 | C2: 0.040987693
A3: 1991 | B3: 219328.42 | C3: 0.041110139
A4: 1992 | B4: 215882.45 | C4: 0.040221777
A5: 1993 | B5: 207684.89 | C5: 0.038381036
A6: 1994 | B6: 202188.81 | C6: 0.036329336
A7: 1995 | B7: 198953.86 | C7: 0.034592818
A8: 1996 | B8: 196366.45 | C8: 0.03327617
A9: 1997 | B9: 194417.84 | C9: 0.032420319
A10: 1998 | B10: 194516.3 | C10: 0.032081783
A11: 1999 | B11: 194964.56 | C11: 0.032050826
A12: 2000 | B12: 195327.08 | C12: 0.03192779
A13: 2001 | B13: 196512.45 | C13: 0.031839453
... A31: 2019 | B31: 264125.56 | C31: 0.043566011
A32: 2020
A33: 2021
A34: 2022
A35: 2023

Sheet WEO_Data
B1: WEO Country Code | C1: 915 | D1: 915
B2: WEO Subject Code | C2: NGDP_R | D2: NGDP_RPCH
B3: Country | C3: Georgia | D3: Georgia
B4: Subject Descriptor | C4: Gross domestic product, constant prices | D4: Gross domestic product, constant prices
B5: Units | C5: National currency | D5: Percent change
B6: Scale | C6: Billions | D6: Units
B7: Country/Series-specific Notes | C7: Source: National Statistics Office. Historical data from 2010 revised in February 2024 Latest actual data: 2024 Notes: Data prior to 1996 cannot be confirmed by national sources. Data prior to 2010 are based on staff estimates. National accounts manual used: System of National Accounts (SNA) 2008 GDP valuation: Market prices Reporting in calendar year: Yes Start/end months of reporting year: January/December Base year: 2019 Chain-weighted: Yes, from 1996 Primary domestic currency: Georgian lari Data last updated: 04/09/2025 | D7: See notes for: Gross domestic product, constant prices (National currency).
B8: 2000 | C8: 16.963 | D8: 1.865
B9: 2001 | C9: 17.772 | D9: 4.769
B10: 2002 | C10: 18.747 | D10: 5.487
B11: 2003 | C11: 20.852 | D11: 11.228
B12: 2004 | C12: 22.061 | D12: 5.796
B13: 2005 | C13: 24.176 | D13: 9.588
B14: 2006 | C14: 26.454 | D14: 9.42
B15: 2007 | C15: 29.781 | D15: 12.579
B16: 2008 | C16: 30.502 | D16: 2.419
B17: 2009 | C17: 29.388 | D17: -3.651
B18: 2010 | C18: 31.428 | D18: 6.942
B19: 2011 | C19: 33.927 | D19: 7.949
... B35: 2027 | C35: 78.873 | D35: 5
B36: 2028 | C36: =C35*(1+D36/100) -> 82.81665 | D36: =D35 -> 5
B37: 2029 | C37: =C36*(1+D37/100) -> 86.957482 | D37: =D36 -> 5
B38: 2030 | C38: =C37*(1+D38/100) -> 91.305357 | D38: =D37 -> 5
B39: 2031 | C39: =C38*(1+D39/100) -> 95.870624 | D39: =D38 -> 5
B40: 2032 | C40: =C39*(1+D40/100) -> 100.66416 | D40: =D39 -> 5
B41: 2033 | C41: =C40*(1+D41/100) -> 105.69736 | D41: =D40 -> 5
B42: 2034 | C42: =C41*(1+D42/100) -> 110.98223 | D42: =D41 -> 5
B43: 2035 | C43: =C42*(1+D43/100) -> 116.53134 | D43: =D42 -> 5
B44: 2036 | C44: =C43*(1+D44/100) -> 122.35791 | D44: =D43 -> 5
B45: 2037 | C45: =C44*(1+D45/100) -> 128.47581 | D45: =D44 -> 5
B46: 2038 | C46: =C45*(1+D46/100) -> 134.8996 | D46: =D45 -> 5
B47: 2039 | C47: =C46*(1+D47/100) -> 141.64458 | D47: =D46 -> 5
... B51: 2043 | C51: =C50*(1+D51/100) -> 172.16987 | D51: =D50 -> 5
