Workbook

Sheet Production
A1: Assumption
A2: capital's share | B2: 0.35
A3: annual depreciation rate | B3: =AVERAGE(E22:E29) -> #NAME?
K4: HP Filter
D5: K | E5: Real GDP | F5: LnK | G5: LnY | K5: LnZ | L5: LnZ_HP | M5: Second-order difference | N5: LnA-Trend(Check) | O5: =SUMPRODUCT(M8:M25,M8:M25)+100*SUMPRODUCT(N6:N27,N6:N27) -> #NAME?
C6: 2002 | D6: =xlookup(C6,PWT!$A$2:$A$35,PWT!$B$2:$B$35,"") -> #NAME? | E6: =xlookup(C6,WEO_Data!$B$8:$B$51,WEO_Data!$C$8:$C$51,"") -> #NAME? | F6: =LN(D6) -> #NAME? | G6: =LN(E6) -> #NAME? | K6: =G6-(1-$B$2)*F6 -> #NAME? | L6: =K6 -> #NAME? | N6: =L6-K6 -> #NAME?
C7: 2003 | D7: =xlookup(C7,PWT!$A$2:$A$35,PWT!$B$2:$B$35,"") -> #NAME? | E7: =xlookup(C7,WEO_Data!$B$8:$B$51,WEO_Data!$C$8:$C$51,"") -> #NAME? | F7: =LN(D7) -> #NAME? | G7: =LN(E7) -> #NAME? | K7: =G7-(1-$B$2)*F7 -> #NAME? | L7: =K7 -> #NAME? | N7: =L7-K7 -> #NAME?
C8: 2004 | D8: =xlookup(C8,PWT!$A$2:$A$35,PWT!$B$2:$B$35,"") -> #NAME? | E8: =xlookup(C8,WEO_Data!$B$8:$B$51,WEO_Data!$C$8:$C$51,"") -> #NAME? | F8: =LN(D8) -> #NAME? | G8: =LN(E8) -> #NAME? | K8: =G8-(1-$B$2)*F8 -> #NAME? | L8: =K8 -> #NAME? | M8: =L9-2*L8+L7 -> #NAME? | N8: =L8-K8 -> #NAME?
C9: 2005 | D9: =xlookup(C9,PWT!$A$2:$A$35,PWT!$B$2:$B$35,"") -> #NAME? | E9: =xlookup(C9,WEO_Data!$B$8:$B$51,WEO_Data!$C$8:$C$51,"") -> #NAME? | F9: =LN(D9) -> #NAME? | G9: =LN(E9) -> #NAME? | K9: =G9-(1-$B$2)*F9 -> #NAME? | L9: =K9 -> #NAME? | M9: =L10-2*L9+L8 -> #NAME? | N9: =L9-K9 -> #NAME?
C10: 2006 | D10: =xlookup(C10,PWT!$A$2:$A$35,PWT!$B$2:$B$35,"") -> #NAME? | E10: =xlookup(C10,WEO_Data!$B$8:$B$51,WEO_Data!$C$8:$C$51,"") -> #NAME? | F10: =LN(D10) -> #NAME? | G10: =LN(E10) -> #NAME? | K10: =G10-(1-$B$2)*F10 -> #NAME? | L10: =K10 -> #NAME? | M10: =L11-2*L10+L9 -> #NAME? | N10: =L10-K10 -> #NAME?
C11: 2007 | D11: =xlookup(C11,PWT!$A$2:$A$35,PWT!$B$2:$B$35,"") -> #NAME? | E11: =xlookup(C11,WEO_Data!$B$8:$B$51,WEO_Data!$C$8:$C$51,"") -> #NAME? | F11: =LN(D11) -> #NAME? | G11: =LN(E11) -> #NAME? | K11: =G11-(1-$B$2)*F11 -> #NAME? | L11: =K11 -> #NAME? | M11: =L12-2*L11+L10 -> #NAME? | N11: =L11-K11 -> #NAME?
C12: 2008 | D12: =xlookup(C12,PWT!$A$2:$A$35,PWT!$B$2:$B$35,"") -> #NAME? | E12: =xlookup(C12,WEO_Data!$B$8:$B$51,WEO_Data!$C$8:$C$51,"") -> #NAME? | F12: =LN(D12) -> #NAME? | G12: =LN(E12) -> #NAME? | K12: =G12-(1-$B$2)*F12 -> #NAME? | L12: =K12 -> #NAME? | M12: =L13-2*L12+L11 -> #NAME? | N12: =L12-K12 -> #NAME?
C13: 2009 | D13: =xlookup(C13,PWT!$A$2:$A$35,PWT!$B$2:$B$35,"") -> #NAME? | E13: =xlookup(C13,WEO_Data!$B$8:$B$51,WEO_Data!$C$8:$C$51,"") -> #NAME? | F13: =LN(D13) -> #NAME? | G13: =LN(E13) -> #NAME? | K13: =G13-(1-$B$2)*F13 -> #NAME? | L13: =K13 -> #NAME? | M13: =L14-2*L13+L12 -> #NAME? | N13: =L13-K13 -> #NAME?
C14: 2010 | D14: =xlookup(C14,PWT!$A$2:$A$35,PWT!$B$2:$B$35,"") -> #NAME? | E14: =xlookup(C14,WEO_Data!$B$8:$B$51,WEO_Data!$C$8:$C$51,"") -> #NAME? | F14: =LN(D14) -> #NAME? | G14: =LN(E14) -> #NAME? | K14: =G14-(1-$B$2)*F14 -> #NAME? | L14: =K14 -> #NAME? | M14: =L15-2*L14+L13 -> #NAME? | N14: =L14-K14 -> #NAME?
C15: 2011 | D15: =xlookup(C15,PWT!$A$2:$A$35,PWT!$B$2:$B$35,"") -> #NAME? | E15: =xlookup(C15,WEO_Data!$B$8:$B$51,WEO_Data!$C$8:$C$51,"") -> #NAME? | F15: =LN(D15) -> #NAME? | G15: =LN(E15) -> #NAME? | K15: =G15-(1-$B$2)*F15 -> #NAME? | L15: =K15 -> #NAME? | M15: =L16-2*L15+L14 -> #NAME? | N15: =L15-K15 -> #NAME?
C16: 2012 | D16: =xlookup(C16,PWT!$A$2:$A$35,PWT!$B$2:$B$35,"") -> #NAME? | E16: =xlookup(C16,WEO_Data!$B$8:$B$51,WEO_Data!$C$8:$C$51,"") -> #NAME? | F16: =LN(D16) -> #NAME? | G16: =LN(E16) -> #NAME? | K16: =G16-(1-$B$2)*F16 -> #NAME? | L16: =K16 -> #NAME? | M16: =L17-2*L16+L15 -> #NAME? | N16: =L16-K16 -> #NAME?
C17: 2013 | D17: =xlookup(C17,PWT!$A$2:$A$35,PWT!$B$2:$B$35,"") -> #NAME? | E17: =xlookup(C17,WEO_Data!$B$8:$B$51,WEO_Data!$C$8:$C$51,"") -> #NAME? | F17: =LN(D17) -> #NAME? | G17: =LN(E17) -> #NAME? | K17: =G17-(1-$B$2)*F17 -> #NAME? | L17: =K17 -> #NAME? | M17: =L18-2*L17+L16 -> #NAME? | N17: =L17-K17 -> #NAME?
C18: 2014 | D18: =xlookup(C18,PWT!$A$2:$A$35,PWT!$B$2:$B$35,"") -> #NAME? | E18: =xlookup(C18,WEO_Data!$B$8:$B$51,WEO_Data!$C$8:$C$51,"") -> #NAME? | F18: =LN(D18) -> #NAME? | G18: =LN(E18) -> #NAME? | K18: =G18-(1-$B$2)*F18 -> #NAME? | L18: =K18 -> #NAME? | M18: =L19-2*L18+L17 -> #NAME? | N18: =L18-K18 -> #NAME?
C19: 2015 | D19: =xlookup(C19,PWT!$A$2:$A$35,PWT!$B$2:$B$35,"") -> #NAME? | E19: =xlookup(C19,WEO_Data!$B$8:$B$51,WEO_Data!$C$8:$C$51,"") -> #NAME? | F19: =LN(D19) -> #NAME? | G19: =LN(E19) -> #NAME? | K19: =G19-(1-$B$2)*F19 -> #NAME? | L19: =K19 -> #NAME? | M19: =L20-2*L19+L18 -> #NAME? | N19: =L19-K19 -> #NAME?
... C25: 2021 | D25: =xlookup(C25,PWT!$A$2:$A$35,PWT!$B$2:$B$35,"") -> #NAME? | E25: =xlookup(C25,WEO_Data!$B$8:$B$51,WEO_Data!$C$8:$C$51,"") -> #NAME? | F25: =LN(D25) -> #NAME? | G25: =LN(E25) -> #NAME? | K25: =G25-(1-$B$2)*F25 -> #NAME? | L25: =K25 -> #NAME? | M25: =L26-2*L25+L24 -> #NAME? | N25: =L25-K25 -> #NAME?
C26: 2022 | D26: =xlookup(C26,PWT!$A$2:$A$35,PWT!$B$2:$B$35,"") -> #NAME? | E26: =xlookup(C26,WEO_Data!$B$8:$B$51,WEO_Data!$C$8:$C$51,"") -> #NAME? | F26: =LN(D26) -> #NAME? | G26: =LN(E26) -> #NAME? | K26: =G26-(1-$B$2)*F26 -> #NAME? | L26: =K26 -> #NAME? | N26: =L26-K26 -> #NAME?
C27: 2023 | D27: =xlookup(C27,PWT!$A$2:$A$35,PWT!$B$2:$B$35,"") -> #NAME? | E27: =xlookup(C27,WEO_Data!$B$8:$B$51,WEO_Data!$C$8:$C$51,"") -> #NAME? | F27: =LN(D27) -> #NAME? | G27: =LN(E27) -> #NAME? | K27: =G27-(1-$B$2)*F27 -> #NAME? | L27: =K27 -> #NAME? | N27: =L27-K27 -> #NAME?
D35: K/Y | E35: K | F35: Y | G35: LnZ trend | H35: Ystar_base | I35: Investment | J35: ΔK | K35: K_With | L35: Ystar_with | M35: Uplift | N35: Projected GDP | O35: Projected GDP Growth | P35: Baseline GDP Growth
C36: 2002 | D36: =IFERROR(E36/F36,"") | E36: =xlookup(C36,PWT!$A$2:$A$35,PWT!$B$2:$B$35,"") -> #NAME? | F36: =xlookup(C36,WEO_Data!$B$8:$B$51,WEO_Data!$C$8:$C$51,"") -> #NAME? | G36: =L6 -> #NAME? | H36: =EXP(G36)*(E36^$B$2) -> #NAME? | I36: 0 | J36: 0 | K36: =E36+I36 -> #NAME? | L36: =EXP(G36)*(K36^$B$2) -> #NAME? | M36: =L36-H36 -> #NAME? | N36: =F36+M36 -> #NAME?
C37: 2003 | D37: =IFERROR(E37/F37,"") | E37: =xlookup(C37,PWT!$A$2:$A$35,PWT!$B$2:$B$35,"") -> #NAME? | F37: =xlookup(C37,WEO_Data!$B$8:$B$51,WEO_Data!$C$8:$C$51,"") -> #NAME? | G37: =L7 -> #NAME? | H37: =EXP(G37)*(E37^$B$2) -> #NAME? | I37: 0 | J37: =I37-$B$3*K36 -> #NAME? | K37: =K36+J37 -> #NAME? | L37: =EXP(G37)*(K37^$B$2) -> #NAME? | M37: =L37-H37 -> #NAME? | N37: =F37+M37 -> #NAME? | O37: =N37/N36-1 -> #NAME? | P37: =F37/F36-1 -> #NAME?
C38: 2004 | D38: =IFERROR(E38/F38,"") | E38: =xlookup(C38,PWT!$A$2:$A$35,PWT!$B$2:$B$35,"") -> #NAME? | F38: =xlookup(C38,WEO_Data!$B$8:$B$51,WEO_Data!$C$8:$C$51,"") -> #NAME? | G38: =L8 -> #NAME? | H38: =EXP(G38)*(E38^$B$2) -> #NAME? | I38: 0 | J38: =I38-$B$3*K37 -> #NAME? | K38: =K37+J38 -> #NAME? | L38: =EXP(G38)*(K38^$B$2) -> #NAME? | M38: =L38-H38 -> #NAME? | N38: =F38+M38 -> #NAME? | O38: =N38/N37-1 -> #NAME? | P38: =F38/F37-1 -> #NAME?
C39: 2005 | D39: =IFERROR(E39/F39,"") | E39: =xlookup(C39,PWT!$A$2:$A$35,PWT!$B$2:$B$35,"") -> #NAME? | F39: =xlookup(C39,WEO_Data!$B$8:$B$51,WEO_Data!$C$8:$C$51,"") -> #NAME? | G39: =L9 -> #NAME? | H39: =EXP(G39)*(E39^$B$2) -> #NAME? | I39: 0 | J39: =I39-$B$3*K38 -> #NAME? | K39: =K38+J39 -> #NAME? | L39: =EXP(G39)*(K39^$B$2) -> #NAME? | M39: =L39-H39 -> #NAME? | N39: =F39+M39 -> #NAME? | O39: =N39/N38-1 -> #NAME? | P39: =F39/F38-1 -> #NAME?
C40: 2006 | D40: =IFERROR(E40/F40,"") | E40: =xlookup(C40,PWT!$A$2:$A$35,PWT!$B$2:$B$35,"") -> #NAME? | F40: =xlookup(C40,WEO_Data!$B$8:$B$51,WEO_Data!$C$8:$C$51,"") -> #NAME? | G40: =L10 -> #NAME? | H40: =EXP(G40)*(E40^$B$2) -> #NAME? | I40: 0 | J40: =I40-$B$3*K39 -> #NAME? | K40: =K39+J40 -> #NAME? | L40: =EXP(G40)*(K40^$B$2) -> #NAME? | M40: =L40-H40 -> #NAME? | N40: =F40+M40 -> #NAME? | O40: =N40/N39-1 -> #NAME? | P40: =F40/F39-1 -> #NAME?
C41: 2007 | D41: =IFERROR(E41/F41,"") | E41: =xlookup(C41,PWT!$A$2:$A$35,PWT!$B$2:$B$35,"") -> #NAME? | F41: =xlookup(C41,WEO_Data!$B$8:$B$51,WEO_Data!$C$8:$C$51,"") -> #NAME? | G41: =L11 -> #NAME? | H41: =EXP(G41)*(E41^$B$2) -> #NAME? | I41: 0 | J41: =I41-$B$3*K40 -> #NAME? | K41: =K40+J41 -> #NAME? | L41: =EXP(G41)*(K41^$B$2) -> #NAME? | M41: =L41-H41 -> #NAME? | N41: =F41+M41 -> #NAME? | O41: =N41/N40-1 -> #NAME? | P41: =F41/F40-1 -> #NAME?
C42: 2008 | D42: =IFERROR(E42/F42,"") | E42: =xlookup(C42,PWT!$A$2:$A$35,PWT!$B$2:$B$35,"") -> #NAME? | F42: =xlookup(C42,WEO_Data!$B$8:$B$51,WEO_Data!$C$8:$C$51,"") -> #NAME? | G42: =L12 -> #NAME? | H42: =EXP(G42)*(E42^$B$2) -> #NAME? | I42: 0 | J42: =I42-$B$3*K41 -> #NAME? | K42: =K41+J42 -> #NAME? | L42: =EXP(G42)*(K42^$B$2) -> #NAME? | M42: =L42-H42 -> #NAME? | N42: =F42+M42 -> #NAME? | O42: =N42/N41-1 -> #NAME? | P42: =F42/F41-1 -> #NAME?
C43: 2009 | D43: =IFERROR(E43/F43,"") | E43: =xlookup(C43,PWT!$A$2:$A$35,PWT!$B$2:$B$35,"") -> #NAME? | F43: =xlookup(C43,WEO_Data!$B$8:$B$51,WEO_Data!$C$8:$C$51,"") -> #NAME? | G43: =L13 -> #NAME? | H43: =EXP(G43)*(E43^$B$2) -> #NAME? | I43: 0 | J43: =I43-$B$3*K42 -> #NAME? | K43: =K42+J43 -> #NAME? | L43: =EXP(G43)*(K43^$B$2) -> #NAME? | M43: =L43-H43 -> #NAME? | N43: =F43+M43 -> #NAME? | O43: =N43/N42-1 -> #NAME? | P43: =F43/F42-1 -> #NAME?
C44: 2010 | D44: =IFERROR(E44/F44,"") | E44: =xlookup(C44,PWT!$A$2:$A$35,PWT!$B$2:$B$35,"") -> #NAME? | F44: =xlookup(C44,WEO_Data!$B$8:$B$51,WEO_Data!$C$8:$C$51,"") -> #NAME? | G44: =L14 -> #NAME? | H44: =EXP(G44)*(E44^$B$2) -> #NAME? | I44: 0 | J44: =I44-$B$3*K43 -> #NAME? | K44: =K43+J44 -> #NAME? | L44: =EXP(G44)*(K44^$B$2) -> #NAME? | M44: =L44-H44 -> #NAME? | N44: =F44+M44 -> #NAME? | O44: =N44/N43-1 -> #NAME? | P44: =F44/F43-1 -> #NAME?
C45: 2011 | D45: =IFERROR(E45/F45,"") | E45: =xlookup(C45,PWT!$A$2:$A$35,PWT!$B$2:$B$35,"") -> #NAME? | F45: =xlookup(C45,WEO_Data!$B$8:$B$51,WEO_Data!$C$8:$C$51,"") -> #NAME? | G45: =L15 -> #NAME? | H45: =EXP(G45)*(E45^$B$2) -> #NAME? | I45: 0 | J45: =I45-$B$3*K44 -> #NAME? | K45: =K44+J45 -> #NAME? | L45: =EXP(G45)*(K45^$B$2) -> #NAME? | M45: =L45-H45 -> #NAME? | N45: =F45+M45 -> #NAME? | O45: =N45/N44-1 -> #NAME? | P45: =F45/F44-1 -> #NAME?
C46: 2012 | D46: =IFERROR(E46/F46,"") | E46: =xlookup(C46,PWT!$A$2:$A$35,PWT!$B$2:$B$35,"") -> #NAME? | F46: =xlookup(C46,WEO_Data!$B$8:$B$51,WEO_Data!$C$8:$C$51,"") -> #NAME? | G46: =L16 -> #NAME? | H46: =EXP(G46)*(E46^$B$2) -> #NAME? | I46: 0 | J46: =I46-$B$3*K45 -> #NAME? | K46: =K45+J46 -> #NAME? | L46: =EXP(G46)*(K46^$B$2) -> #NAME? | M46: =L46-H46 -> #NAME? | N46: =F46+M46 -> #NAME? | O46: =N46/N45-1 -> #NAME? | P46: =F46/F45-1 -> #NAME?
C47: 2013 | D47: =IFERROR(E47/F47,"") | E47: =xlookup(C47,PWT!$A$2:$A$35,PWT!$B$2:$B$35,"") -> #NAME? | F47: =xlookup(C47,WEO_Data!$B$8:$B$51,WEO_Data!$C$8:$C$51,"") -> #NAME? | G47: =L17 -> #NAME? | H47: =EXP(G47)*(E47^$B$2) -> #NAME? | I47: 0 | J47: =I47-$B$3*K46 -> #NAME? | K47: =K46+J47 -> #NAME? | L47: =EXP(G47)*(K47^$B$2) -> #NAME? | M47: =L47-H47 -> #NAME? | N47: =F47+M47 -> #NAME? | O47: =N47/N46-1 -> #NAME? | P47: =F47/F46-1 -> #NAME?
C48: 2014 | D48: =IFERROR(E48/F48,"") | E48: =xlookup(C48,PWT!$A$2:$A$35,PWT!$B$2:$B$35,"") -> #NAME? | F48: =xlookup(C48,WEO_Data!$B$8:$B$51,WEO_Data!$C$8:$C$51,"") -> #NAME? | G48: =L18 -> #NAME? | H48: =EXP(G48)*(E48^$B$2) -> #NAME? | I48: 0 | J48: =I48-$B$3*K47 -> #NAME? | K48: =K47+J48 -> #NAME? | L48: =EXP(G48)*(K48^$B$2) -> #NAME? | M48: =L48-H48 -> #NAME? | N48: =F48+M48 -> #NAME? | O48: =N48/N47-1 -> #NAME? | P48: =F48/F47-1 -> #NAME?
... C57: 2023 | D57: =IFERROR(E57/F57,"") | E57: =xlookup(C57,PWT!$A$2:$A$35,PWT!$B$2:$B$35,"") -> #NAME? | F57: =xlookup(C57,WEO_Data!$B$8:$B$51,WEO_Data!$C$8:$C$51,"") -> #NAME? | G57: =L27 -> #NAME? | H57: =EXP(G57)*(E57^$B$2) -> #NAME? | I57: 0 | J57: =I57-$B$3*K56 -> #NAME? | K57: =K56+J57 -> #NAME? | L57: =EXP(G57)*(K57^$B$2) -> #NAME? | M57: =L57-H57 -> #NAME? | N57: =F57+M57 -> #NAME? | O57: =N57/N56-1 -> #NAME? | P57: =F57/F56-1 -> #NAME?
C58: 2024 | D58: =AVERAGE($D$49:$D$57) -> #DIV/0! | E58: =D58*F58 -> #NAME? | F58: =xlookup(C58,WEO_Data!$B$8:$B$51,WEO_Data!$C$8:$C$51,"") -> #NAME? | G58: =TREND($G$36:$G$57,$C$36:$C$57,C58) -> #NAME? | H58: =EXP(G58)*(E58^$B$2) -> #NAME? | I58: 0 | J58: =I58-$B$3*K57 -> #NAME? | K58: =K57+J58 -> #NAME? | L58: =EXP(G58)*(K58^$B$2) -> #NAME? | M58: =L58-H58 -> #NAME? | N58: =F58+M58 -> #NAME? | O58: =N58/N57-1 -> #NAME? | P58: =F58/F57-1 -> #NAME?
C59: 2025 | D59: =AVERAGE($D$49:$D$57) -> #DIV/0! | E59: =D59*F59 -> #NAME? | F59: =xlookup(C59,WEO_Data!$B$8:$B$51,WEO_Data!$C$8:$C$51,"") -> #NAME? | G59: =TREND($G$36:$G$57,$C$36:$C$57,C59) -> #NAME? | H59: =EXP(G59)*(E59^$B$2) -> #NAME? | I59: 0 | J59: =I59-$B$3*K58 -> #NAME? | K59: =K58+J59 -> #NAME? | L59: =EXP(G59)*(K59^$B$2) -> #NAME? | M59: =L59-H59 -> #NAME? | N59: =F59+M59 -> #NAME? | O59: =N59/N58-1 -> #NAME? | P59: =F59/F58-1 -> #NAME?
C60: 2026 | D60: =AVERAGE($D$49:$D$57) -> #DIV/0! | E60: =D60*F60 -> #NAME? | F60: =xlookup(C60,WEO_Data!$B$8:$B$51,WEO_Data!$C$8:$C$51,"") -> #NAME? | G60: =TREND($G$36:$G$57,$C$36:$C$57,C60) -> #NAME? | H60: =EXP(G60)*(E60^$B$2) -> #NAME? | I60: =Investment!C2 -> 648.58931 | J60: =I60-$B$3*K59 -> #NAME? | K60: =K59+J60 -> #NAME? | L60: =EXP(G60)*(K60^$B$2) -> #NAME? | M60: =L60-H60 -> #NAME? | N60: =F60+M60 -> #NAME? | O60: =N60/N59-1 -> #NAME? | P60: =F60/F59-1 -> #NAME?
C61: 2027 | D61: =AVERAGE($D$49:$D$57) -> #DIV/0! | E61: =D61*F61 -> #NAME? | F61: =xlookup(C61,WEO_Data!$B$8:$B$51,WEO_Data!$C$8:$C$51,"") -> #NAME? | G61: =TREND($G$36:$G$57,$C$36:$C$57,C61) -> #NAME? | H61: =EXP(G61)*(E61^$B$2) -> #NAME? | I61: =Investment!C3 -> 1220.0802 | J61: =I61-$B$3*K60 -> #NAME? | K61: =K60+J61 -> #NAME? | L61: =EXP(G61)*(K61^$B$2) -> #NAME? | M61: =L61-H61 -> #NAME? | N61: =F61+M61 -> #NAME? | O61: =N61/N60-1 -> #NAME? | P61: =F61/F60-1 -> #NAME?
C62: 2028 | D62: =AVERAGE($D$49:$D$57) -> #DIV/0! | E62: =D62*F62 -> #NAME? | F62: =xlookup(C62,WEO_Data!$B$8:$B$51,WEO_Data!$C$8:$C$51,"") -> #NAME? | G62: =TREND($G$36:$G$57,$C$36:$C$57,C62) -> #NAME? | H62: =EXP(G62)*(E62^$B$2) -> #NAME? | I62: =Investment!C4 -> 1756.1737 | J62: =I62-$B$3*K61 -> #NAME? | K62: =K61+J62 -> #NAME? | L62: =EXP(G62)*(K62^$B$2) -> #NAME? | M62: =L62-H62 -> #NAME? | N62: =F62+M62 -> #NAME? | O62: =N62/N61-1 -> #NAME? | P62: =F62/F61-1 -> #NAME?
C63: 2029 | D63: =AVERAGE($D$49:$D$57) -> #DIV/0! | E63: =D63*F63 -> #NAME? | F63: =xlookup(C63,WEO_Data!$B$8:$B$51,WEO_Data!$C$8:$C$51,"") -> #NAME? | G63: =TREND($G$36:$G$57,$C$36:$C$57,C63) -> #NAME? | H63: =EXP(G63)*(E63^$B$2) -> #NAME? | I63: =Investment!C5 -> 2221.1947 | J63: =I63-$B$3*K62 -> #NAME? | K63: =K62+J63 -> #NAME? | L63: =EXP(G63)*(K63^$B$2) -> #NAME? | M63: =L63-H63 -> #NAME? | N63: =F63+M63 -> #NAME? | O63: =N63/N62-1 -> #NAME? | P63: =F63/F62-1 -> #NAME?
C64: 2030 | D64: =AVERAGE($D$49:$D$57) -> #DIV/0! | E64: =D64*F64 -> #NAME? | F64: =xlookup(C64,WEO_Data!$B$8:$B$51,WEO_Data!$C$8:$C$51,"") -> #NAME? | G64: =TREND($G$36:$G$57,$C$36:$C$57,C64) -> #NAME? | H64: =EXP(G64)*(E64^$B$2) -> #NAME? | I64: =Investment!C6 -> 2122.4679 | J64: =I64-$B$3*K63 -> #NAME? | K64: =K63+J64 -> #NAME? | L64: =EXP(G64)*(K64^$B$2) -> #NAME? | M64: =L64-H64 -> #NAME? | N64: =F64+M64 -> #NAME? | O64: =N64/N63-1 -> #NAME? | P64: =F64/F63-1 -> #NAME?
C65: 2031 | D65: =AVERAGE($D$49:$D$57) -> #DIV/0! | E65: =D65*F65 -> #NAME? | F65: =xlookup(C65,WEO_Data!$B$8:$B$51,WEO_Data!$C$8:$C$51,"") -> #NAME? | G65: =TREND($G$36:$G$57,$C$36:$C$57,C65) -> #NAME? | H65: =EXP(G65)*(E65^$B$2) -> #NAME? | I65: =Investment!C7 -> 1524.5246 | J65: =I65-$B$3*K64 -> #NAME? | K65: =K64+J65 -> #NAME? | L65: =EXP(G65)*(K65^$B$2) -> #NAME? | M65: =L65-H65 -> #NAME? | N65: =F65+M65 -> #NAME? | O65: =N65/N64-1 -> #NAME? | P65: =F65/F64-1 -> #NAME?
C66: 2032 | D66: =AVERAGE($D$49:$D$57) -> #DIV/0! | E66: =D66*F66 -> #NAME? | F66: =xlookup(C66,WEO_Data!$B$8:$B$51,WEO_Data!$C$8:$C$51,"") -> #NAME? | G66: =TREND($G$36:$G$57,$C$36:$C$57,C66) -> #NAME? | H66: =EXP(G66)*(E66^$B$2) -> #NAME? | I66: =Investment!C8 -> 738.17631 | J66: =I66-$B$3*K65 -> #NAME? | K66: =K65+J66 -> #NAME? | L66: =EXP(G66)*(K66^$B$2) -> #NAME? | M66: =L66-H66 -> #NAME? | N66: =F66+M66 -> #NAME? | O66: =N66/N65-1 -> #NAME? | P66: =F66/F65-1 -> #NAME?
C67: 2033 | D67: =AVERAGE($D$49:$D$57) -> #DIV/0! | E67: =D67*F67 -> #NAME? | F67: =xlookup(C67,WEO_Data!$B$8:$B$51,WEO_Data!$C$8:$C$51,"") -> #NAME? | G67: =TREND($G$36:$G$57,$C$36:$C$57,C67) -> #NAME? | H67: =EXP(G67)*(E67^$B$2) -> #NAME? | I67: =Investment!C9 -> 352.60598 | J67: =I67-$B$3*K66 -> #NAME? | K67: =K66+J67 -> #NAME? | L67: =EXP(G67)*(K67^$B$2) -> #NAME? | M67: =L67-H67 -> #NAME? | N67: =F67+M67 -> #NAME? | O67: =N67/N66-1 -> #NAME? | P67: =F67/F66-1 -> #NAME?
C68: 2034 | D68: =AVERAGE($D$49:$D$57) -> #DIV/0! | E68: =D68*F68 -> #NAME? | F68: =xlookup(C68,WEO_Data!$B$8:$B$51,WEO_Data!$C$8:$C$51,"") -> #NAME? | G68: =TREND($G$36:$G$57,$C$36:$C$57,C68) -> #NAME? | H68: =EXP(G68)*(E68^$B$2) -> #NAME? | I68: 0 | J68: =I68-$B$3*K67 -> #NAME? | K68: =K67+J68 -> #NAME? | L68: =EXP(G68)*(K68^$B$2) -> #NAME? | M68: =L68-H68 -> #NAME? | N68: =F68+M68 -> #NAME? | O68: =N68/N67-1 -> #NAME? | P68: =F68/F67-1 -> #NAME?
C69: 2035 | D69: =AVERAGE($D$49:$D$57) -> #DIV/0! | E69: =D69*F69 -> #NAME? | F69: =xlookup(C69,WEO_Data!$B$8:$B$51,WEO_Data!$C$8:$C$51,"") -> #NAME? | G69: =TREND($G$36:$G$57,$C$36:$C$57,C69) -> #NAME? | H69: =EXP(G69)*(E69^$B$2) -> #NAME? | I69: 0 | J69: =I69-$B$3*K68 -> #NAME? | K69: =K68+J69 -> #NAME? | L69: =EXP(G69)*(K69^$B$2) -> #NAME? | M69: =L69-H69 -> #NAME? | N69: =F69+M69 -> #NAME? | O69: =N69/N68-1 -> #NAME? | P69: =F69/F68-1 -> #NAME?
C70: 2036 | D70: =AVERAGE($D$49:$D$57) -> #DIV/0! | E70: =D70*F70 -> #NAME? | F70: =xlookup(C70,WEO_Data!$B$8:$B$51,WEO_Data!$C$8:$C$51,"") -> #NAME? | G70: =TREND($G$36:$G$57,$C$36:$C$57,C70) -> #NAME? | H70: =EXP(G70)*(E70^$B$2) -> #NAME? | I70: 0 | J70: =I70-$B$3*K69 -> #NAME? | K70: =K69+J70 -> #NAME? | L70: =EXP(G70)*(K70^$B$2) -> #NAME? | M70: =L70-H70 -> #NAME? | N70: =F70+M70 -> #NAME? | O70: =N70/N69-1 -> #NAME? | P70: =F70/F69-1 -> #NAME?
C71: 2037 | D71: =AVERAGE($D$49:$D$57) -> #DIV/0! | E71: =D71*F71 -> #NAME? | F71: =xlookup(C71,WEO_Data!$B$8:$B$51,WEO_Data!$C$8:$C$51,"") -> #NAME? | G71: =TREND($G$36:$G$57,$C$36:$C$57,C71) -> #NAME? | H71: =EXP(G71)*(E71^$B$2) -> #NAME? | I71: 0 | J71: =I71-$B$3*K70 -> #NAME? | K71: =K70+J71 -> #NAME? | L71: =EXP(G71)*(K71^$B$2) -> #NAME? | M71: =L71-H71 -> #NAME? | N71: =F71+M71 -> #NAME? | O71: =N71/N70-1 -> #NAME? | P71: =F71/F70-1 -> #NAME?
C72: 2038 | D72: =AVERAGE($D$49:$D$57) -> #DIV/0! | E72: =D72*F72 -> #NAME? | F72: =xlookup(C72,WEO_Data!$B$8:$B$51,WEO_Data!$C$8:$C$51,"") -> #NAME? | G72: =TREND($G$36:$G$57,$C$36:$C$57,C72) -> #NAME? | H72: =EXP(G72)*(E72^$B$2) -> #NAME? | I72: 0 | J72: =I72-$B$3*K71 -> #NAME? | K72: =K71+J72 -> #NAME? | L72: =EXP(G72)*(K72^$B$2) -> #NAME? | M72: =L72-H72 -> #NAME? | N72: =F72+M72 -> #NAME? | O72: =N72/N71-1 -> #NAME? | P72: =F72/F71-1 -> #NAME?
C73: 2039 | D73: =AVERAGE($D$49:$D$57) -> #DIV/0! | E73: =D73*F73 -> #NAME? | F73: =xlookup(C73,WEO_Data!$B$8:$B$51,WEO_Data!$C$8:$C$51,"") -> #NAME? | G73: =TREND($G$36:$G$57,$C$36:$C$57,C73) -> #NAME? | H73: =EXP(G73)*(E73^$B$2) -> #NAME? | I73: 0 | J73: =I73-$B$3*K72 -> #NAME? | K73: =K72+J73 -> #NAME? | L73: =EXP(G73)*(K73^$B$2) -> #NAME? | M73: =L73-H73 -> #NAME? | N73: =F73+M73 -> #NAME? | O73: =N73/N72-1 -> #NAME? | P73: =F73/F72-1 -> #NAME?
C74: 2040 | D74: =AVERAGE($D$49:$D$57) -> #DIV/0! | E74: =D74*F74 -> #NAME? | F74: =xlookup(C74,WEO_Data!$B$8:$B$51,WEO_Data!$C$8:$C$51,"") -> #NAME? | G74: =TREND($G$36:$G$57,$C$36:$C$57,C74) -> #NAME? | H74: =EXP(G74)*(E74^$B$2) -> #NAME? | I74: 0 | J74: =I74-$B$3*K73 -> #NAME? | K74: =K73+J74 -> #NAME? | L74: =EXP(G74)*(K74^$B$2) -> #NAME? | M74: =L74-H74 -> #NAME? | N74: =F74+M74 -> #NAME? | O74: =N74/N73-1 -> #NAME? | P74: =F74/F73-1 -> #NAME?
C75: 2041 | D75: =AVERAGE($D$49:$D$57) -> #DIV/0! | E75: =D75*F75 -> #NAME? | F75: =xlookup(C75,WEO_Data!$B$8:$B$51,WEO_Data!$C$8:$C$51,"") -> #NAME? | G75: =TREND($G$36:$G$57,$C$36:$C$57,C75) -> #NAME? | H75: =EXP(G75)*(E75^$B$2) -> #NAME? | I75: 0 | J75: =I75-$B$3*K74 -> #NAME? | K75: =K74+J75 -> #NAME? | L75: =EXP(G75)*(K75^$B$2) -> #NAME? | M75: =L75-H75 -> #NAME? | N75: =F75+M75 -> #NAME? | O75: =N75/N74-1 -> #NAME? | P75: =F75/F74-1 -> #NAME?

Sheet Investment
B1: Year | C1: Project Investment (Deflated)
B2: 2026 | C2: 648.58931
B3: 2027 | C3: 1220.0802
B4: 2028 | C4: 1756.1737
B5: 2029 | C5: 2221.1947
B6: 2030 | C6: 2122.4679
B7: 2031 | C7: 1524.5246
B8: 2032 | C8: 738.17631
B9: 2033 | C9: 352.60598

Sheet CFC data
A1: DATE | B1: TIME PERIOD | C1: Consumption of fixed capital (IDCM.A.N.GE.W2.S1.S1.D.P51C.N1G._T._Z.XDC.V.N) | D1: Capital Stock | E1: Depreciation rate
A2: 35430 | B2: 1996 | C2: 3.0451509e+08 | D2: =xlookup(B2,PWT!$A$2:$A$35,PWT!$B$2:$B$35,"") -> #NAME? | E2: =IFERROR(C2/D2,"")
A3: 35795 | B3: 1997 | C3: 3.8364166e+08 | D3: =xlookup(B3,PWT!$A$2:$A$35,PWT!$B$2:$B$35,"") -> #NAME? | E3: =IFERROR(C3/D3,"")
A4: 36160 | B4: 1998 | C4: 5.1639712e+08 | D4: =xlookup(B4,PWT!$A$2:$A$35,PWT!$B$2:$B$35,"") -> #NAME? | E4: =IFERROR(C4/D4,"")
A5: 36525 | B5: 1999 | C5: 6.6160383e+08 | D5: =xlookup(B5,PWT!$A$2:$A$35,PWT!$B$2:$B$35,"") -> #NAME? | E5: =IFERROR(C5/D5,"")
A6: 36891 | B6: 2000 | C6: 6.31701e+08 | D6: =xlookup(B6,PWT!$A$2:$A$35,PWT!$B$2:$B$35,"") -> #NAME? | E6: =IFERROR(C6/D6,"")
A7: 37256 | B7: 2001 | C7: 7.0698373e+08 | D7: =xlookup(B7,PWT!$A$2:$A$35,PWT!$B$2:$B$35,"") -> #NAME? | E7: =IFERROR(C7/D7,"")
A8: 37621 | B8: 2002 | C8: 7.9011257e+08 | D8: =xlookup(B8,PWT!$A$2:$A$35,PWT!$B$2:$B$35,"") -> #NAME? | E8: =IFERROR(C8/D8,"")
A9: 37986 | B9: 2003 | C9: 9.3291622e+08 | D9: =xlookup(B9,PWT!$A$2:$A$35,PWT!$B$2:$B$35,"") -> #NAME? | E9: =IFERROR(C9/D9,"")
A10: 38352 | B10: 2004 | C10: 9.7681854e+08 | D10: =xlookup(B10,PWT!$A$2:$A$35,PWT!$B$2:$B$35,"") -> #NAME? | E10: =IFERROR(C10/D10,"")
A11: 38717 | B11: 2005 | C11: 1.1134501e+09 | D11: =xlookup(B11,PWT!$A$2:$A$35,PWT!$B$2:$B$35,"") -> #NAME? | E11: =IFERROR(C11/D11,"")
A12: 39082 | B12: 2006 | C12: 1.3063731e+09 | D12: =xlookup(B12,PWT!$A$2:$A$35,PWT!$B$2:$B$35,"") -> #NAME? | E12: =IFERROR(C12/D12,"")
A13: 39447 | B13: 2007 | C13: 1.61703e+09 | D13: =xlookup(B13,PWT!$A$2:$A$35,PWT!$B$2:$B$35,"") -> #NAME? | E13: =IFERROR(C13/D13,"")
... A29: 45291 | B29: 2023 | C29: 9.4106578e+09 | D29: =xlookup(B29,PWT!$A$2:$A$35,PWT!$B$2:$B$35,"") -> #NAME? | E29: =IFERROR(C29/D29,"")

Sheet PWT
A1: year | B1: rnna
A2: 1990 | B2: 333953.91
A3: 1991 | B3: 336800.12
A4: 1992 | B4: 331575.34
A5: 1993 | B5: 318977.56
A6: 1994 | B6: 310557.22
A7: 1995 | B7: 305633.28
A8: 1996 | B8: 301706.47
A9: 1997 | B9: 298764.62
A10: 1998 | B10: 298990.5
A11: 1999 | B11: 299754.78
A12: 2000 | B12: 300383.31
A13: 2001 | B13: 302284.06
... A35: 2023 | B35: 426190.5

Sheet WEO_Data
B1: WEO Country Code | C1: 915 | D1: 915
B2: WEO Subject Code | C2: NGDP_R | D2: NGDP_RPCH
B3: Country | C3: Georgia | D3: Georgia
B4: Subject Descriptor | C4: Gross domestic product, constant prices | D4: Gross domestic product, constant prices
B5: Units | C5: National currency | D5: Percent change
B6: Scale | C6: Billions | D6: Units
B7: Country/Series-specific Notes | C7: Source: National Statistics Office. Historical data from 2010 revised in February 2024 Latest actual data: 2024 Notes: Data prior to 1996 cannot be confirmed by national sources. Data prior to 2010 are based on staff estimates. National accounts manual used: System of National Accounts (SNA) 2008 GDP valuation: Market prices Reporting in calendar year: Yes Start/end months of reporting year: January/December Base year: 2019 Chain-weighted: Yes, from 1996 Primary domestic currency: Georgian lari Data last updated: 04/09/2025 | D7: See notes for: Gross domestic product, constant prices (National currency).
B8: 2000 | C8: 17.099
B9: 2001 | C9: 17.921 | D9: 4.8072987
B10: 2002 | C10: 18.902 | D10: 5.4740249
B11: 2003 | C11: 20.992 | D11: 11.057031
B12: 2004 | C12: 22.208 | D12: 5.7926829
B13: 2005 | C13: 24.338 | D13: 9.5911383
B14: 2006 | C14: 26.631 | D14: 9.4214808
B15: 2007 | C15: 29.98 | D15: 12.57557
B16: 2008 | C16: 30.706 | D16: 2.4216144
B17: 2009 | C17: 29.585 | D17: -3.6507523
B18: 2010 | C18: 31.433 | D18: 6.2464087
B19: 2011 | C19: 33.927 | D19: 7.9343365
B20: 2012 | C20: 36.159 | D20: 6.578831
... B35: 2027 | C35: 80.161129 | D35: 5
B36: 2028 | C36: =C35*(1+D36/100) -> 84.169185 | D36: =D35 -> 5
B37: 2029 | C37: =C36*(1+D37/100) -> 88.377644 | D37: =D35 -> 5
B38: 2030 | C38: =C37*(1+D38/100) -> 92.796526 | D38: =D35 -> 5
B39: 2031 | C39: =C38*(1+D39/100) -> 97.436353 | D39: =D35 -> 5
B40: 2032 | C40: =C39*(1+D40/100) -> 102.30817 | D40: =D35 -> 5
B41: 2033 | C41: =C40*(1+D41/100) -> 107.42358 | D41: =D35 -> 5
B42: 2034 | C42: =C41*(1+D42/100) -> 112.79476 | D42: =D35 -> 5
B43: 2035 | C43: =C42*(1+D43/100) -> 118.4345 | D43: =D35 -> 5
B44: 2036 | C44: =C43*(1+D44/100) -> 124.35622 | D44: =D35 -> 5
B45: 2037 | C45: =C44*(1+D45/100) -> 130.57403 | D45: =D35 -> 5
B46: 2038 | C46: =C45*(1+D46/100) -> 137.10273 | D46: =D35 -> 5
B47: 2039 | C47: =C46*(1+D47/100) -> 143.95787 | D47: =D35 -> 5
B48: 2040 | C48: =C47*(1+D48/100) -> 151.15576 | D48: =D35 -> 5
B49: 2041 | C49: =C48*(1+D49/100) -> 158.71355 | D49: =D35 -> 5
B50: 2042 | C50: =C49*(1+D50/100) -> 166.64923 | D50: =D35 -> 5
B51: 2043 | C51: =C50*(1+D51/100) -> 174.98169 | D51: =D35 -> 5
B16385: WEO Country Code | C16385: 915 | D16385: 915
B16386: WEO Subject Code | C16386: NGDP_R | D16386: NGDP_RPCH
B16387: Country | C16387: Georgia | D16387: Georgia
B16388: Subject Descriptor | C16388: Gross domestic product, constant prices | D16388: Gross domestic product, constant prices
B16389: Units | C16389: National currency | D16389: Percent change
B16390: Scale | C16390: Billions | D16390: Units
B16391: Country/Series-specific Notes | C16391: Source: National Statistics Office. Historical data from 2010 revised in February 2024 Latest actual data: 2024 Notes: Data prior to 1996 cannot be confirmed by national sources. Data prior to 2010 are based on staff estimates. National accounts manual used: System of National Accounts (SNA) 2008 GDP valuation: Market prices Reporting in calendar year: Yes Start/end months of reporting year: January/December Base year: 2019 Chain-weighted: Yes, from 1996 Primary domestic currency: Georgian lari Data last updated: 04/09/2025 | D16391: See notes for: Gross domestic product, constant prices (National currency).
B16392: 2000 | C16392: 16.963 | D16392: 1.865
B16393: 2001 | C16393: 17.772 | D16393: 4.769
B16394: 2002 | C16394: 18.747 | D16394: 5.487
B16395: 2003 | C16395: 20.852 | D16395: 11.228
B16396: 2004 | C16396: 22.061 | D16396: 5.796
B16397: 2005 | C16397: 24.176 | D16397: 9.588
B16398: 2006 | C16398: 26.454 | D16398: 9.42
B16399: 2007 | C16399: 29.781 | D16399: 12.579
B16400: 2008 | C16400: 30.502 | D16400: 2.419
B16401: 2009 | C16401: 29.388 | D16401: -3.651
B16402: 2010 | C16402: 31.428 | D16402: 6.942
B16403: 2011 | C16403: 33.927 | D16403: 7.949
... B16419: 2027 | C16419: 78.873 | D16419: 5
B16420: Estimates Start After | C16420: 2024 | D16420: 2024
B32769: WEO Country Code | C32769: 915 | D32769: 915
B32770: WEO Subject Code | C32770: NGDP_R | D32770: NGDP_RPCH
B32771: Country | C32771: Georgia | D32771: Georgia
B32772: Subject Descriptor | C32772: Gross domestic product, constant prices | D32772: Gross domestic product, constant prices
B32773: Units | C32773: National currency | D32773: Percent change
B32774: Scale | C32774: Billions | D32774: Units
B32775: Country/Series-specific Notes | C32775: Source: National Statistics Office. Historical data from 2010 revised in February 2024 Latest actual data: 2024 Notes: Data prior to 1996 cannot be confirmed by national sources. Data prior to 2010 are based on staff estimates. National accounts manual used: System of National Accounts (SNA) 2008 GDP valuation: Market prices Reporting in calendar year: Yes Start/end months of reporting year: January/December Base year: 2019 Chain-weighted: Yes, from 1996 Primary domestic currency: Georgian lari Data last updated: 04/09/2025 | D32775: See notes for: Gross domestic product, constant prices (National currency).
B32776: 2000 | C32776: 16.963 | D32776: 1.865
B32777: 2001 | C32777: 17.772 | D32777: 4.769
B32778: 2002 | C32778: 18.747 | D32778: 5.487
B32779: 2003 | C32779: 20.852 | D32779: 11.228
B32780: 2004 | C32780: 22.061 | D32780: 5.796
B32781: 2005 | C32781: 24.176 | D32781: 9.588
B32782: 2006 | C32782: 26.454 | D32782: 9.42
B32783: 2007 | C32783: 29.781 | D32783: 12.579
B32784: 2008 | C32784: 30.502 | D32784: 2.419
B32785: 2009 | C32785: 29.388 | D32785: -3.651
B32786: 2010 | C32786: 31.428 | D32786: 6.942
B32787: 2011 | C32787: 33.927 | D32787: 7.949
... B32803: 2027 | C32803: 78.873 | D32803: 5
B32804: Estimates Start After | C32804: 2024 | D32804: 2024
B49153: WEO Country Code | C49153: 915 | D49153: 915
B49154: WEO Subject Code | C49154: NGDP_R | D49154: NGDP_RPCH
B49155: Country | C49155: Georgia | D49155: Georgia
B49156: Subject Descriptor | C49156: Gross domestic product, constant prices | D49156: Gross domestic product, constant prices
B49157: Units | C49157: National currency | D49157: Percent change
B49158: Scale | C49158: Billions | D49158: Units
B49159: Country/Series-specific Notes | C49159: Source: National Statistics Office. Historical data from 2010 revised in February 2024 Latest actual data: 2024 Notes: Data prior to 1996 cannot be confirmed by national sources. Data prior to 2010 are based on staff estimates. National accounts manual used: System of National Accounts (SNA) 2008 GDP valuation: Market prices Reporting in calendar year: Yes Start/end months of reporting year: January/December Base year: 2019 Chain-weighted: Yes, from 1996 Primary domestic currency: Georgian lari Data last updated: 04/09/2025 | D49159: See notes for: Gross domestic product, constant prices (National currency).
B49160: 2000 | C49160: 16.963 | D49160: 1.865
B49161: 2001 | C49161: 17.772 | D49161: 4.769
B49162: 2002 | C49162: 18.747 | D49162: 5.487
B49163: 2003 | C49163: 20.852 | D49163: 11.228
B49164: 2004 | C49164: 22.061 | D49164: 5.796
B49165: 2005 | C49165: 24.176 | D49165: 9.588
B49166: 2006 | C49166: 26.454 | D49166: 9.42
B49167: 2007 | C49167: 29.781 | D49167: 12.579
B49168: 2008 | C49168: 30.502 | D49168: 2.419
B49169: 2009 | C49169: 29.388 | D49169: -3.651
B49170: 2010 | C49170: 31.428 | D49170: 6.942
B49171: 2011 | C49171: 33.927 | D49171: 7.949
... B49187: 2027 | C49187: 78.873 | D49187: 5
B49188: Estimates Start After | C49188: 2024 | D49188: 2024
...
